Workbook
Name SegmentaciónDeDatos_Finca: #N/A
Name SegmentaciónDeDatos_Finca1: #N/A
Name SegmentaciónDeDatos_Variedad: #N/A

Sheet PA_Gen
A1: Faenas | B1: Finca | C1: Variedad | D1: Jornales
A2: Riego | B2: Puente Alto | C2: Selma | D2: 20.649307
A3: Calicatas | B3: Puente Alto | C3: Selma | D3: 2
A4: Malezas Mochila | B4: Puente Alto | C4: Selma | D4: 20.660754
A5: Desmalezar manual | B5: Puente Alto | C5: Selma | D5: 4.1298615
A6: Mugrones | B6: Puente Alto | C6: Selma | D6: 23.333734
A7: Seguridad | B7: Puente Alto | C7: Selma | D7: 4.1298615
A8: Hormigas | B8: Puente Alto | C8: Selma | D8: 3.3038921
A9: Limpieza | B9: Puente Alto | C9: Selma | D9: 9.2994012
A10: Datos | B10: Puente Alto | C10: Selma | D10: 4.1298615
A11: Reparar Estructura | B11: Puente Alto | C11: Selma | D11: 6.6077608
A12: Tractorista Generales | B12: Puente Alto | C12: Selma | D12: 9.9116693
A13: Hoyar y Replantar | B13: Puente Alto | C13: Selma | D13: 3.5109269
... A49: Feriados | B49: Puente Alto | C49: Arizul | D49: 7.5849139

Sheet PA_Esp
A1: Faenas | B1: Finca | C1: Variedad | D1: Jornales
A2: Poda | B2: Puente Alto | C2: Selma | D2: 67.938182
A3: Atada | B3: Puente Alto | C3: Selma | D3: 45.292121
A4: Desbrote de troncos | B4: Puente Alto | C4: Selma | D4: 71.676923
A5: Acomodo de brotes | B5: Puente Alto | C5: Selma | D5: 31.06
A6: Desniete Deshoje | B6: Puente Alto | C6: Selma | D6: 0
A7: Desbrote con criterio de Poda | B7: Puente Alto | C7: Selma | D7: 18.636
A8: Raleo de Racimos | B8: Puente Alto | C8: Selma | D8: 0
A9: Tractorista Subsolado | B9: Puente Alto | C9: Selma | D9: 3.3038892
A10: Tractorista Triturado de sarmiento | B10: Puente Alto | C10: Selma | D10: 1.4454515
A11: Tractorista Cincelado | B11: Puente Alto | C11: Selma | D11: 0.61950668
A12: Tractorista Rastra | B12: Puente Alto | C12: Selma | D12: 13.009064
A13: Tractor Herbicida | B13: Puente Alto | C13: Selma | D13: 1.5488697
... A40: Tractor Atomizadora | B40: Puente Alto | C40: Arizul | D40: 15.212

Sheet CT_Gen
A1: Faenas | B1: Finca | C1: Jornales
A2: Riego | B2: Camino Truncado | C2: 543.99445
A3: Mantenimiento | B3: Camino Truncado | C3: 40
A4: Mangueras | B4: Camino Truncado | C4: 120
A5: Calicatas | B5: Camino Truncado | C5: 12.000612
A6: Malezas Mochila | B6: Camino Truncado | C6: 255.79565
A7: Desmalezar manual | B7: Camino Truncado | C7: 100
A8: Jardinería | B8: Camino Truncado | C8: 10
A9: Hormigas | B9: Camino Truncado | C9: 62.01695
A10: Limpieza | B10: Camino Truncado | C10: 32.999966
A11: Taller | B11: Camino Truncado | C11: 99.996601
A12: Datos | B12: Camino Truncado | C12: 75
A13: Reparar Estructura | B13: Camino Truncado | C13: 40
... A19: Feriados | B19: Camino Truncado | C19: 180
C20: =SUBTOTAL(109,CT_Gen[Jornales]) -> 2001.8096

Sheet CT_Esp
A1: Faenas | B1: Finca | C1: Variedad | D1: Jornales
A2: Poda | B2: Camino Truncado | C2: Flame | D2: 270.4452
A3: Atada | B3: Camino Truncado | C3: Flame | D3: 180.2968
A4: Desbrote de troncos | B4: Camino Truncado | C4: Flame | D4: 67.338
A5: Acomodo de brotes | B5: Camino Truncado | C5: Flame | D5: 0
A6: Desniete Deshoje | B6: Camino Truncado | C6: Flame | D6: 0
A7: Desbrote con criterio de Poda | B7: Camino Truncado | C7: Flame | D7: 48.098571
A8: Raleo de Racimos | B8: Camino Truncado | C8: Flame | D8: 67.338
A9: Tractorista Subsolado | B9: Camino Truncado | C9: Flame | D9: 10
A10: Tractorista Triturado de sarmiento | B10: Camino Truncado | C10: Flame | D10: 6.4999952
A11: Tractorista Cincelado | B11: Camino Truncado | C11: Flame | D11: 4.8800037
A12: Tractorista Rastra | B12: Camino Truncado | C12: Flame | D12: 12.990034
A13: Tractor Herbicida | B13: Camino Truncado | C13: Flame | D13: 20
... A66: Tractor Atomizadora | B66: Camino Truncado | C66: Superior | D66: 3.58
D67: =SUBTOTAL(109,CT_Esp[Jornales]) -> 2444.6877

Sheet LCH_Gen
A1: Faenas | B1: Finca | C1: Variedad | D1: Jornales
A2: Riego | B2: La Chimbera | C2: Flame | D2: 42.693236
A3: Mantenimiento | B3: La Chimbera | C3: Flame | D3: 23.244135
A4: Calicatas | B4: La Chimbera | C4: Flame | D4: 1.4231072
A5: Malezas Mochila | B5: La Chimbera | C5: Flame | D5: 45.065086
A6: Desmalezar manual | B6: La Chimbera | C6: Flame | D6: 11.384837
A7: Mugrones | B7: La Chimbera | C7: Flame | D7: 52.180557
A8: Seguridad | B8: La Chimbera | C8: Flame | D8: 5.6924288
A9: Hormigas | B9: La Chimbera | C9: Flame | D9: 8.7758325
A10: Limpieza | B10: La Chimbera | C10: Flame | D10: 21.356498
A11: Datos | B11: La Chimbera | C11: Flame | D11: 7.8278146
A12: Reparar Estructura | B12: La Chimbera | C12: Flame | D12: 14.711345
A13: Tractorista Generales | B13: La Chimbera | C13: Flame | D13: 21.356498
... A52: Feriados | B52: La Chimbera | C52: Arizul | D52: 8.459472

Sheet LHC_Esp
A1: Faenas | B1: Finca | C1: Variedad | D1: Jornales
A2: Poda | B2: La Chimbera | C2: Flame | D2: 236.4
A3: Atada | B3: La Chimbera | C3: Flame | D3: 157.6
A4: Desbrote de troncos | B4: La Chimbera | C4: Flame | D4: 151.38916
A5: Acomodo de brotes | B5: La Chimbera | C5: Flame | D5: 61.464
A6: Desniete Deshoje | B6: La Chimbera | C6: Flame | D6: 61.464
A7: Desbrote con criterio de Poda | B7: La Chimbera | C7: Flame | D7: 61.464
A8: Raleo de Racimos | B8: La Chimbera | C8: Flame | D8: 102.44
A9: Tractorista Subsolado | B9: La Chimbera | C9: Flame | D9: 9.0123167
A10: Tractorista Triturado de sarmiento | B10: La Chimbera | C10: Flame | D10: 2.3718453
A11: Tractorista Cincelado | B11: La Chimbera | C11: Flame | D11: 1.8982088
A12: Tractorista Rastra | B12: La Chimbera | C12: Flame | D12: 2.3718453
A13: Tractor Herbicida | B13: La Chimbera | C13: Flame | D13: 11.384858
... A40: Tractor Atomizadora | B40: La Chimbera | C40: Arizul | D40: 20.29807

Sheet EE_Esp
A1: Faenas | B1: Finca | C1: Variedad | D1: Año de plantación | E1: Jornales | F1: Txt ref
A2: Poda | B2: El Espejo I | C2: Flame | D2: 2019 | E2: 541.91667 | F2: =+EE_Esp[[#This Row],[Variedad]]&" "&EE_Esp[[#This Row],[Año de plantación]] -> Flame 2019
A3: Atada | B3: El Espejo I | C3: Flame | D3: 2019 | E3: 541.91667 | F3: =+EE_Esp[[#This Row],[Variedad]]&" "&EE_Esp[[#This Row],[Año de plantación]] -> Flame 2019
A4: Desbrote de troncos | B4: El Espejo I | C4: Flame | D4: 2019 | E4: 130.06 | F4: =+EE_Esp[[#This Row],[Variedad]]&" "&EE_Esp[[#This Row],[Año de plantación]] -> Flame 2019
A5: Acomodo de brotes | B5: El Espejo I | C5: Flame | D5: 2019 | E5: 130.06 | F5: =+EE_Esp[[#This Row],[Variedad]]&" "&EE_Esp[[#This Row],[Año de plantación]] -> Flame 2019
A6: Desniete Deshoje | B6: El Espejo I | C6: Flame | D6: 2019 | E6: 65.03 | F6: =+EE_Esp[[#This Row],[Variedad]]&" "&EE_Esp[[#This Row],[Año de plantación]] -> Flame 2019
A7: Desbrote con criterio de Poda | B7: El Espejo I | C7: Flame | D7: 2019 | E7: 130.06 | F7: =+EE_Esp[[#This Row],[Variedad]]&" "&EE_Esp[[#This Row],[Año de plantación]] -> Flame 2019
A8: Raleo de Racimos | B8: El Espejo I | C8: Flame | D8: 2019 | E8: 650.3 | F8: =+EE_Esp[[#This Row],[Variedad]]&" "&EE_Esp[[#This Row],[Año de plantación]] -> Flame 2019
A9: Tractorista Subsolado | B9: El Espejo I | C9: Flame | D9: 2019 | E9: 0.77644331 | F9: =+EE_Esp[[#This Row],[Variedad]]&" "&EE_Esp[[#This Row],[Año de plantación]] -> Flame 2019
A10: Tractor Herbicida | B10: El Espejo I | C10: Flame | D10: 2019 | E10: 8.597985 | F10: =+EE_Esp[[#This Row],[Variedad]]&" "&EE_Esp[[#This Row],[Año de plantación]] -> Flame 2019
A11: Tractor Atomizadora | B11: El Espejo I | C11: Flame | D11: 2019 | E11: 30.80105 | F11: =+EE_Esp[[#This Row],[Variedad]]&" "&EE_Esp[[#This Row],[Año de plantación]] -> Flame 2019
A12: Poda | B12: El Espejo I | C12: Flame | D12: 2020 | E12: 88.412522 | F12: =+EE_Esp[[#This Row],[Variedad]]&" "&EE_Esp[[#This Row],[Año de plantación]] -> Flame 2020
A13: Atada | B13: El Espejo I | C13: Flame | D13: 2020 | E13: 58.941682 | F13: =+EE_Esp[[#This Row],[Variedad]]&" "&EE_Esp[[#This Row],[Año de plantación]] -> Flame 2020
... A81: Tractor Atomizadora | B81: El Espejo III | C81: Selma | D81: 2021 | E81: 8.2914429 | F81: =+EE_Esp[[#This Row],[Variedad]]&" "&EE_Esp[[#This Row],[Año de plantación]] -> Selma 2021

Sheet EE_Gen
A1: Faenas | B1: Finca | C1: Variedad | D1: Jornales
A2: Riego | B2: El Espejo I | C2: Flame | D2: 573.64539
A3: Mantenimiento | B3: El Espejo I | C3: Flame | D3: 122.04135
A4: Mangueras | B4: El Espejo I | C4: Flame | D4: 87.430621
A5: Calicatas | B5: El Espejo I | C5: Flame | D5: 7.0091505
A6: Malezas Mochila | B6: El Espejo I | C6: Flame | D6: 151.25148
A7: Desmalezar manual | B7: El Espejo I | C7: Flame | D7: 260.74301
A8: Seguridad | B8: El Espejo I | C8: Flame | D8: 104.76836
A9: Hormigas | B9: El Espejo I | C9: Flame | D9: 36.890266
A10: Limpieza | B10: El Espejo I | C10: Flame | D10: 11.804888
A11: Taller | B11: El Espejo I | C11: Flame | D11: 320.44571
A12: Datos | B12: El Espejo I | C12: Flame | D12: 34.307913
A13: Reparar Estructura | B13: El Espejo I | C13: Flame | D13: 105.50596
... A127: Feriados | B127: El Espejo III | C127: Selma | D127: 5.9891737

Sheet Visualización Jornales EE III
A1: Detalle | B1: MES | C1: Valor | D1: Finca
A2: Contratados | B2: Mayo | C2: 1338.0034 | D2: El Espejo III
A3: Contratados | B3: Junio | C3: 7374.1011 | D3: El Espejo III
A4: Contratados | B4: Julio | C4: 7152.1865 | D4: El Espejo III
A5: Contratados | B5: Agosto | C5: 8830.8809 | D5: El Espejo III
A6: Contratados | B6: Septiembre | C6: 9637.7644 | D6: El Espejo III
A7: Contratados | B7: Octubre | C7: 12599.25 | D7: El Espejo III
A8: Contratados | B8: Noviembre | C8: 12799.175 | D8: El Espejo III
A9: Contratados | B9: Diciembre | C9: 12049.274 | D9: El Espejo III
A10: Contratados | B10: Enero | C10: 2132.5928 | D10: El Espejo III
A11: Contratados | B11: Febrero | C11: 9264.5315 | D11: El Espejo III
A12: Contratados | B12: Marzo | C12: 9599.4266 | D12: El Espejo III
A13: Contratados | B13: Abril | C13: 3307.664 | D13: El Espejo III
... A25: Combustible y Lubricantes | B25: Abril | C25: 0 | D25: El Espejo III

Sheet Visualización Jornales EE I y I
A1: Detalle | B1: MES | C1: Valor | D1: Finca
A2: Contratados | B2: Mayo | C2: 3183.9696 | D2: El Espejo I y II
A3: Contratados | B3: Junio | C3: 17547.723 | D3: El Espejo I y II
A4: Contratados | B4: Julio | C4: 17019.646 | D4: El Espejo I y II
A5: Contratados | B5: Agosto | C5: 21014.338 | D5: El Espejo I y II
A6: Contratados | B6: Septiembre | C6: 22934.433 | D6: El Espejo I y II
A7: Contratados | B7: Octubre | C7: 29981.709 | D7: El Espejo I y II
A8: Contratados | B8: Noviembre | C8: 30457.46 | D8: El Espejo I y II
A9: Contratados | B9: Diciembre | C9: 28672.964 | D9: El Espejo I y II
A10: Contratados | B10: Enero | C10: 5074.8081 | D10: El Espejo I y II
A11: Contratados | B11: Febrero | C11: 22046.272 | D11: El Espejo I y II
A12: Contratados | B12: Marzo | C12: 22843.202 | D12: El Espejo I y II
A13: Contratados | B13: Abril | C13: 7871.0573 | D13: El Espejo I y II
... A25: Combustible y Lubricantes | B25: Abril | C25: 0 | D25: El Espejo I y II

Sheet Visualización Jornales PA (2)
A1: Detalle | B1: MES | C1: Valor | D1: Finca
A2: Contratados | B2: Mayo | C2: 2832.4121 | D2: Puente Alto
A3: Contratados | B3: Junio | C3: 3124.2459 | D3: Puente Alto
A4: Contratados | B4: Julio | C4: 2762.1809 | D4: Puente Alto
A5: Contratados | B5: Agosto | C5: 4135.9623 | D5: Puente Alto
A6: Contratados | B6: Septiembre | C6: 661.23757 | D6: Puente Alto
A7: Contratados | B7: Octubre | C7: 4951.2246 | D7: Puente Alto
A8: Contratados | B8: Noviembre | C8: 2984.0684 | D8: Puente Alto
A9: Contratados | B9: Diciembre | C9: 2999.7045 | D9: Puente Alto
A10: Contratados | B10: Enero | C10: 522.38855 | D10: Puente Alto
A11: Contratados | B11: Febrero | C11: 1978.6718 | D11: Puente Alto
A12: Contratados | B12: Marzo | C12: 2422.1948 | D12: Puente Alto
A13: Contratados | B13: Abril | C13: 808.99269 | D13: Puente Alto
... A25: Combustible y Lubricantes | B25: Abril | C25: 411.24224 | D25: Puente Alto

Sheet Visualización Jornales LCH (2)
A1: Detalle | B1: MES | C1: Valor | D1: Finca
A2: Contratados | B2: Mayo | C2: 3785.7037 | D2: La Chimbera
A3: Contratados | B3: Junio | C3: 5446.9104 | D3: La Chimbera
A4: Contratados | B4: Julio | C4: 3802.7777 | D4: La Chimbera
A5: Contratados | B5: Agosto | C5: 4577.028 | D5: La Chimbera
A6: Contratados | B6: Septiembre | C6: 1278.1208 | D6: La Chimbera
A7: Contratados | B7: Octubre | C7: 3243.9384 | D7: La Chimbera
A8: Contratados | B8: Noviembre | C8: 930.3802 | D8: La Chimbera
A9: Contratados | B9: Diciembre | C9: 2468.7886 | D9: La Chimbera
A10: Contratados | B10: Enero | C10: 1347.7149 | D10: La Chimbera
A11: Contratados | B11: Febrero | C11: 5416.165 | D11: La Chimbera
A12: Contratados | B12: Marzo | C12: 5443.211 | D12: La Chimbera
A13: Contratados | B13: Abril | C13: 1549.8074 | D13: La Chimbera
... A25: Combustible y Lubricantes | B25: Abril | C25: 72.421926 | D25: La Chimbera

Sheet Visualización Jornales CT
A1: Jornal Presupuestado | B1: $ | C1: =+INDEX(Tabla2[Precio Jornal],MATCH(C$19,Tabla2[Mes],0)) -> 19319.2 | D1: =+INDEX(Tabla2[Precio Jornal],MATCH(D$19,Tabla2[Mes],0)) -> 19646 | E1: =+INDEX(Tabla2[Precio Jornal],MATCH(E$19,Tabla2[Mes],0)) -> 19976.6 | F1: =+INDEX(Tabla2[Precio Jornal],MATCH(F$19,Tabla2[Mes],0)) -> 20312.9 | G1: =+INDEX(Tabla2[Precio Jornal],MATCH(G$19,Tabla2[Mes],0)) -> 20654.9 | H1: =+INDEX(Tabla2[Precio Jornal],MATCH(H$19,Tabla2[Mes],0)) -> 21002.6 | I1: =+INDEX(Tabla2[Precio Jornal],MATCH(I$19,Tabla2[Mes],0)) -> 21357.9 | J1: =+INDEX(Tabla2[Precio Jornal],MATCH(J$19,Tabla2[Mes],0)) -> 21717 | ... N1: =+INDEX(Tabla2[Precio Jornal],MATCH(N$19,Tabla2[Mes],0)) -> 23218
A2: Días Laborales | C2: 23.5 | D2: 20.5 | E2: 24 | F2: 24 | G2: 23 | H2: 24.5 | I2: 22.5 | J2: 23 | K2: 24 | L2: 20.5 | M2: 23 | N2: 22
A3: Jornales Disponibles CT | B3: 11 | C3: =+$B3*C2 -> 258.5 | D3: =+$B3*D2 -> 225.5 | E3: =+$B3*E2 -> 264 | F3: =+$B3*F2 -> 264 | G3: =+$B3*G2 -> 253 | H3: =+$B3*H2 -> 269.5 | I3: =+$B3*I2 -> 247.5 | J3: =+$B3*J2 -> 253 | ... N3: =+$B3*N2 -> 242 | O3: cosecha | P3: secado | Q3: gral | R3: Jorn/Has
A4: Jornales Cosecha | B4: =+SUMIF(TablaGeneral[Finca],$A$18,TablaGeneral[Resumen Jornales totales de Cosecha]) -> 417.99975 | K4: =+B4*0.2 -> 83.599949 | L4: =+B4*0.4 -> 167.1999 | M4: =+B4*0.4 -> 167.1999 | O4: =SUM(C4:N4) -> 417.99975 | P4: =SUM(C5:N5) -> 849.9303 | Q4: =+O114 -> 4446.4973 | R4: =+(O4+P4+Q4)/SUMIFS(TablaGeneral[Has],TablaGeneral[Finca],A18) -> 86.524812
A5: Jornales Secado | B5: =+SUMIFS(TablaGeneral[Resumen Jornales totales de Secado],TablaGeneral[Finca],"Camino truncado")*0.75 -> 850.03374 | C5: =+$B5*C18 -> 116.97328 | D5: =+$B5*D18 -> 100.70988 | E5: =+$B5*E18 -> 0 | F5: =+$B5*F18 -> 0 | G5: =+$B5*G18 -> 8.1317003 | H5: =+$B5*H18 -> 0 | I5: =+$B5*I18 -> 0 | J5: =+$B5*J18 -> 2.7105668 | ... N5: =+$B5*N18 -> 127.81555 | Q5: =+Q4/65 -> 68.407651
A6: Jornales a contratar | B6: =SUM(C6:N6) -> 2694.9274 | C6: =+(C114+C4+C5)-C3 -> 165.52657 | D6: =+D114+D4+D5-D3 -> 464.34616 | E6: =+E114+E4+E5-E3 -> 322.53808 | F6: =+F114+F4+F5-F3 -> 461.67684 | G6: =+G114+G4+G5-G3 -> 111.58305 | H6: =+H114+H4+H5-H3 -> 119.34185 | I6: =+I114+I4+I5-I3 -> 151.51738 | J6: =+J114+J4+J5-J3 -> 98.338568 | K6: =+K114+K4+K5-K3 -> 69.297822 | ... N6: =+N114+N4+N5-N3 -> 110.78363
A7: Contratados CT $ | B7: =SUM(C7:N7) -> 56460377 | C7: =+C6*C1 -> 3197841 | D7: =+D6*D1 -> 9122544.7 | E7: =+E6*E1 -> 6443214.2 | F7: =+F6*F1 -> 9377995.5 | G7: =+G6*G1 -> 2304736.8 | H7: =+H6*H1 -> 2506489.2 | I7: =+I6*I1 -> 3236093.1 | J7: =+J6*J1 -> 2135618.7 | ... N7: =+N6*N1 -> 2572174.4 | P7: USD/Has
A8: Contratados CT USD | B8: =SUM(C8:N8) -> 47717.446 | C8: =+C7/INDEX(Tabla2[TC],MATCH(C19,Tabla2[Mes],0)) -> 2837.4809 | D8: =+D7/INDEX(Tabla2[TC],MATCH(D19,Tabla2[Mes],0)) -> 8014.3944 | E8: =+E7/INDEX(Tabla2[TC],MATCH(E19,Tabla2[Mes],0)) -> 5604.4875 | F8: =+F7/INDEX(Tabla2[TC],MATCH(F19,Tabla2[Mes],0)) -> 8076.4774 | G8: =+G7/INDEX(Tabla2[TC],MATCH(G19,Tabla2[Mes],0)) -> 1965.2234 | H8: =+H7/INDEX(Tabla2[TC],MATCH(H19,Tabla2[Mes],0)) -> 2116.0945 | I8: =+I7/INDEX(Tabla2[TC],MATCH(I19,Tabla2[Mes],0)) -> 2705.0098 | J8: =+J7/INDEX(Tabla2[TC],MATCH(J19,Tabla2[Mes],0)) -> 1767.4624 | ... N8: =+N7/INDEX(Tabla2[TC],MATCH(N19,Tabla2[Mes],0)) -> 2045.6973 | P8: =+B8/SUMIFS(TablaGeneral[Has],TablaGeneral[Finca],A18) -> 722.51213
A9: Combustible Litros Gen | B9: =SUM(C9:N9) -> 3758.3181 | C9: =+(SUM(C20:C25,C34:C39,C48:C53,C62:C67,C76:C81,C106)*11.5) -> 57.5 | D9: =+(SUM(D20:D25,D34:D39,D48:D53,D62:D67,D76:D81,D106)*11.5) -> 57.5 | E9: =+(SUM(E20:E25,E34:E39,E48:E53,E62:E67,E76:E81,E106)*11.5) -> 57.5 | F9: =+(SUM(F20:F25,F34:F39,F48:F53,F62:F67,F76:F81,F106)*11.5) -> 882.62509 | G9: =+(SUM(G20:G25,G34:G39,G48:G53,G62:G67,G76:G81,G106)*11.5) -> 710.36805 | H9: =+(SUM(H20:H25,H34:H39,H48:H53,H62:H67,H76:H81,H106)*11.5) -> 285.83255 | I9: =+(SUM(I20:I25,I34:I39,I48:I53,I62:I67,I76:I81,I106)*11.5) -> 512.86606 | J9: =+(SUM(J20:J25,J34:J39,J48:J53,J62:J67,J76:J81,J106)*11.5) -> 250.12478 | ... N9: =+(SUM(N20:N25,N34:N39,N48:N53,N62:N67,N76:N81,N106)*11.5) -> 316.13555
A10: Combustible Litros Sec | B10: =SUM(C10:N10) -> 8159.3309 | C10: =+(SUMIFS(TablaGeneral[Resumen Jornales totales de Secado],TablaGeneral[Finca],"Camino truncado"))*0.72*C18*10 -> 1122.9435 | D10: =+(SUMIFS(TablaGeneral[Resumen Jornales totales de Secado],TablaGeneral[Finca],"Camino truncado"))*0.72*D18*10 -> 966.81486 | E10: =+(SUMIFS(TablaGeneral[Resumen Jornales totales de Secado],TablaGeneral[Finca],"Camino truncado"))*0.72*E18*10 -> 0 | F10: =+(SUMIFS(TablaGeneral[Resumen Jornales totales de Secado],TablaGeneral[Finca],"Camino truncado"))*0.72*F18*10 -> 0 | G10: =+(SUMIFS(TablaGeneral[Resumen Jornales totales de Secado],TablaGeneral[Finca],"Camino truncado"))*0.72*G18*10 -> 78.064323 | H10: =+(SUMIFS(TablaGeneral[Resumen Jornales totales de Secado],TablaGeneral[Finca],"Camino truncado"))*0.72*H18*10 -> 0 | I10: =+(SUMIFS(TablaGeneral[Resumen Jornales totales de Secado],TablaGeneral[Finca],"Camino truncado"))*0.72*I18*10 -> 0 | J10: =+(SUMIFS(TablaGeneral[Resumen Jornales totales de Secado],TablaGeneral[Finca],"Camino truncado"))*0.72*J18*10 -> 26.021441 | ... N10: =+(SUMIFS(TablaGeneral[Resumen Jornales totales de Secado],TablaGeneral[Finca],"Camino truncado"))*0.72*N18*10 -> 1227.0293
A11: Combustible Litros Cos | B11: =SUM(C11:N11) -> 4179.9975 | K11: =+SUMIFS(TablaGeneral[Resumen Jornales totales de Cosecha],TablaGeneral[Finca],$A$18)*0.2*10 -> 835.99949 | L11: =+SUMIFS(TablaGeneral[Resumen Jornales totales de Cosecha],TablaGeneral[Finca],$A$18)*0.4*10 -> 1671.999 | M11: =+SUMIFS(TablaGeneral[Resumen Jornales totales de Cosecha],TablaGeneral[Finca],$A$18)*0.4*10 -> 1671.999
A12: Combustible Litros Tot | B12: =SUM(C12:N12) -> 16097.647 | C12: =SUM(C9:C11) -> 1180.4435 | D12: =SUM(D9:D11) -> 1024.3149 | E12: =SUM(E9:E11) -> 57.5 | F12: =SUM(F9:F11) -> 882.62509 | G12: =SUM(G9:G11) -> 788.43238 | H12: =SUM(H9:H11) -> 285.83255 | I12: =SUM(I9:I11) -> 512.86606 | J12: =SUM(J9:J11) -> 276.14622 | ... N12: =SUM(N9:N11) -> 1543.1648
A13: Lubricantes Litros Totales | B13: =SUM(C13:N13) -> 348.78234 | C13: =+(C12/100)+(C12/150)+(C12/200) -> 25.576276 | D13: =+(D12/100)+(D12/150)+(D12/200) -> 22.193489 | E13: =+(E12/100)+(E12/150)+(E12/200) -> 1.2458333 | F13: =+(F12/100)+(F12/150)+(F12/200) -> 19.123544 | G13: =+(G12/100)+(G12/150)+(G12/200) -> 17.082701 | H13: =+(H12/100)+(H12/150)+(H12/200) -> 6.1930387 | I13: =+(I12/100)+(I12/150)+(I12/200) -> 11.112098 | J13: =+(J12/100)+(J12/150)+(J12/200) -> 5.983168 | ... N13: =+(N12/100)+(N12/150)+(N12/200) -> 33.435238
A14: Combustible USD | B14: =SUM(C14:N14) -> 20019786 | C14: =+(INDEX(Tabla2[Combustible],MATCH(C19,Tabla2[Mes],0))*C12) -> 1363618.8 | D14: =+(INDEX(Tabla2[Combustible],MATCH(D19,Tabla2[Mes],0))*D12) -> 1195095.6 | E14: =+(INDEX(Tabla2[Combustible],MATCH(E19,Tabla2[Mes],0))*E12) -> 67757.656 | F14: =+(INDEX(Tabla2[Combustible],MATCH(F19,Tabla2[Mes],0))*F12) -> 1050480.9 | G14: =+(INDEX(Tabla2[Combustible],MATCH(G19,Tabla2[Mes],0))*G12) -> 947758.58 | H14: =+(INDEX(Tabla2[Combustible],MATCH(H19,Tabla2[Mes],0))*H12) -> 347029.46 | I14: =+(INDEX(Tabla2[Combustible],MATCH(I19,Tabla2[Mes],0))*I12) -> 628897.66 | J14: =+(INDEX(Tabla2[Combustible],MATCH(J19,Tabla2[Mes],0))*J12) -> 342008.18 | ... N14: =+(INDEX(Tabla2[Combustible],MATCH(N19,Tabla2[Mes],0))*N12) -> 1988818.8
A15: Lubricantes USD | B15: =SUM(C15:N15) -> 2390981 | C15: =+(INDEX(Tabla2[Lubricantes],MATCH(C19,Tabla2[Mes],0))*C13) -> 162858.22 | D15: =+(INDEX(Tabla2[Lubricantes],MATCH(D19,Tabla2[Mes],0))*D13) -> 142731.33 | E15: =+(INDEX(Tabla2[Lubricantes],MATCH(E19,Tabla2[Mes],0))*E13) -> 8092.3575 | F15: =+(INDEX(Tabla2[Lubricantes],MATCH(F19,Tabla2[Mes],0))*F13) -> 125459.88 | G15: =+(INDEX(Tabla2[Lubricantes],MATCH(G19,Tabla2[Mes],0))*G13) -> 113191.66 | H15: =+(INDEX(Tabla2[Lubricantes],MATCH(H19,Tabla2[Mes],0))*H13) -> 41446.038 | I15: =+(INDEX(Tabla2[Lubricantes],MATCH(I19,Tabla2[Mes],0))*I13) -> 75109.81 | J15: =+(INDEX(Tabla2[Lubricantes],MATCH(J19,Tabla2[Mes],0))*J13) -> 40846.343 | ... N15: =+(INDEX(Tabla2[Lubricantes],MATCH(N19,Tabla2[Mes],0))*N13) -> 237526.4
A16: Combustible Pesos | B16: =SUM(C16:N16) -> 6983040.5 | C16: =+(C9*INDEX(Tabla2[Combustible],MATCH(C19,Tabla2[Mes],0)))+(C13*INDEX(Tabla2[Lubricantes],MATCH(C19,Tabla2[Mes],0))) -> 229280.78 | D16: =+(D9*INDEX(Tabla2[Combustible],MATCH(D19,Tabla2[Mes],0)))+(D13*INDEX(Tabla2[Lubricantes],MATCH(D19,Tabla2[Mes],0))) -> 209818.12 | E16: =+(E9*INDEX(Tabla2[Combustible],MATCH(E19,Tabla2[Mes],0)))+(E13*INDEX(Tabla2[Lubricantes],MATCH(E19,Tabla2[Mes],0))) -> 75850.013 | F16: =+(F9*INDEX(Tabla2[Combustible],MATCH(F19,Tabla2[Mes],0)))+(F13*INDEX(Tabla2[Lubricantes],MATCH(F19,Tabla2[Mes],0))) -> 1175940.8 | G16: =+(G9*INDEX(Tabla2[Combustible],MATCH(G19,Tabla2[Mes],0)))+(G13*INDEX(Tabla2[Lubricantes],MATCH(G19,Tabla2[Mes],0))) -> 967110.7 | H16: =+(H9*INDEX(Tabla2[Combustible],MATCH(H19,Tabla2[Mes],0)))+(H13*INDEX(Tabla2[Lubricantes],MATCH(H19,Tabla2[Mes],0))) -> 388475.5 | I16: =+(I9*INDEX(Tabla2[Combustible],MATCH(I19,Tabla2[Mes],0)))+(I13*INDEX(Tabla2[Lubricantes],MATCH(I19,Tabla2[Mes],0))) -> 704007.47 | J16: =+(J9*INDEX(Tabla2[Combustible],MATCH(J19,Tabla2[Mes],0)))+(J13*INDEX(Tabla2[Lubricantes],MATCH(J19,Tabla2[Mes],0))) -> 350626.87 | ... N16: =+(N9*INDEX(Tabla2[Combustible],MATCH(N19,Tabla2[Mes],0)))+(N13*INDEX(Tabla2[Lubricantes],MATCH(N19,Tabla2[Mes],0))) -> 644959.43
A17: Combustibles USD | B17: =SUM(C17:N17) -> 14293.181 | C17: =+INDEX(Tabla2[TC],MATCH(C19,Tabla2[Mes],0)) -> 1127 | D17: =+INDEX(Tabla2[TC],MATCH(D19,Tabla2[Mes],0)) -> 1138.27 | E17: =+INDEX(Tabla2[TC],MATCH(E19,Tabla2[Mes],0)) -> 1149.6527 | F17: =+INDEX(Tabla2[TC],MATCH(F19,Tabla2[Mes],0)) -> 1161.1492 | G17: =+INDEX(Tabla2[TC],MATCH(G19,Tabla2[Mes],0)) -> 1172.7607 | H17: =+INDEX(Tabla2[TC],MATCH(H19,Tabla2[Mes],0)) -> 1184.4883 | I17: =+INDEX(Tabla2[TC],MATCH(I19,Tabla2[Mes],0)) -> 1196.3332 | J17: =+INDEX(Tabla2[TC],MATCH(J19,Tabla2[Mes],0)) -> 1208.2965 | ... N17: =+INDEX(Tabla2[TC],MATCH(N19,Tabla2[Mes],0)) -> 1257.3582 | O17: =SUM(C17:N17)/SUMIFS(TablaGeneral[Has],TablaGeneral[Finca],A18) -> 216.41972
A18: Camino Truncado | B18: Jorn | C18: 0.13761016 | D18: 0.11847751 | E18: 0 | F18: 0 | G18: 0.0095663265 | H18: 0 | I18: 0 | J18: 0.0031887755 | K18: 0.07903824 | L18: 0.25998661 | M18: 0.24164543 | N18: 0.15036527
A19: Flame | B19: 715.20669 | C19: Mayo | D19: Junio | E19: Julio | F19: Agosto | G19: Septiembre | H19: Octubre | I19: Noviembre | J19: Diciembre | K19: Enero | L19: Febrero | M19: Marzo | N19: Abril
A20: Tractorista Subsolado | B20: 10 | F20: =+B20 -> 10
A21: Tractorista Triturado de sarmiento | B21: 6.4999952 | F21: =+B21 -> 6.4999952
A22: Tractorista Cincelado | B22: 4.8800037 | F22: =+B22 -> 4.8800037
A23: Tractorista Rastra | B23: 12.990034 | G23: =+B23/2 -> 6.4950172 | N23: =+B23/2 -> 6.4950172
A24: Tractor Atomizadora | B24: 27.320085 | G24: =+B24*0.45 -> 12.294038 | I24: =+B24*0.275 -> 7.5130235 | L24: =+B24*0.275 -> 7.5130235
A25: Tractor Herbicida | B25: 20 | H25: =+B25/4 -> 5 | I25: =+B25/4 -> 5 | J25: =+B25/4 -> 5 | L25: =+B25/4 -> 5
A26: Poda | B26: 270.4452 | D26: =+B26/3 -> 90.148401 | E26: =+B26/3 -> 90.148401 | F26: =+B26/3 -> 90.148401
A27: Atada | B27: 180.2968 | D27: =+B27/3 -> 60.098934 | E27: =+B27/3 -> 60.098934 | F27: =+B27/3 -> 60.098934
A28: Acomodo de brotes | B28: 0 | I28: =+B28 -> 0
A29: Desbrote de troncos | B29: 67.338 | H29: =+B29/2 -> 33.669 | J29: =+B29/2 -> 33.669
A30: Raleo de Racimos | B30: 67.338 | I30: =+B30 -> 67.338
A31: Desniete Deshoje | B31: 0
A32: Desbrote con criterio de Poda | B32: 48.098571 | H32: =+B32 -> 48.098571
A33: Fiesta | B33: 637.1396 | C33: =+SUM(C20:C32) -> 0 | D33: =+SUM(D20:D32) -> 150.24733 | E33: =+SUM(E20:E32) -> 150.24733 | F33: =+SUM(F20:F32) -> 171.62733 | G33: =+SUM(G20:G32) -> 18.789056 | H33: =+SUM(H20:H32) -> 86.767571 | I33: =+SUM(I20:I32) -> 79.851023 | J33: =+SUM(J20:J32) -> 38.669 | ... N33: =+SUM(N20:N32) -> 6.4950172
A34: Tractorista Subsolado | B34: 7.9000004 | F34: =+B34 -> 7.9000004
A35: Tractorista Triturado de sarmiento | B35: 5.299995 | F35: =+B35 -> 5.299995
A36: Tractorista Cincelado | B36: 3.9600031 | F36: =+B36 -> 3.9600031
A37: Tractorista Rastra | B37: 5.2800042 | G37: =+B37/2 -> 2.6400021 | N37: =+B37/2 -> 2.6400021
A38: Tractor Atomizadora | B38: 19.000093 | G38: =+B38*0.45 -> 8.550042 | I38: =+B38*0.275 -> 5.2250257 | L38: =+B38*0.275 -> 5.2250257
A39: Tractor Herbicida | B39: 15.999976 | H39: =+B39/4 -> 3.9999939 | I39: =+B39/4 -> 3.9999939 | J39: =+B39/4 -> 3.9999939 | L39: =+B39/4 -> 3.9999939
A40: Poda | B40: 223.53909 | D40: =+B40/3 -> 74.51303 | E40: =+B40/3 -> 74.51303 | F40: =+B40/3 -> 74.51303
A41: Atada | B41: 149.02606 | D41: =+B41/3 -> 49.675354 | E41: =+B41/3 -> 49.675354 | F41: =+B41/3 -> 49.675354
A42: Acomodo de brotes | B42: 44.071667 | I42: =+B42 -> 44.071667
A43: Desbrote de troncos | B43: 52.886 | H43: =+B43/2 -> 26.443 | J43: =+B43/2 -> 26.443
A44: Raleo de Racimos | B44: 33.086 | I44: =+B44 -> 33.086
A45: Desniete Deshoje | B45: 39.315 | J45: =+B45 -> 39.315
A46: Desbrote con criterio de Poda | B46: 37.775714 | H46: =+B46 -> 37.775714
A47: Sultanina | B47: 182.07331 | C47: =+SUM(C34:C46) -> 0 | D47: =+SUM(D34:D46) -> 124.18838 | E47: =+SUM(E34:E46) -> 124.18838 | F47: =+SUM(F34:F46) -> 141.34838 | G47: =+SUM(G34:G46) -> 11.190044 | H47: =+SUM(H34:H46) -> 68.218708 | I47: =+SUM(I34:I46) -> 86.382686 | J47: =+SUM(J34:J46) -> 69.757994 | ... N47: =+SUM(N34:N46) -> 2.6400021
A48: Tractorista Subsolado | B48: 2.8999996 | F48: =+B48 -> 2.8999996
A49: Tractorista Triturado de sarmiento | B49: 1.9000009 | F49: =+B49 -> 1.9000009
A50: Tractorista Cincelado | B50: 1.440002 | F50: =+B50 -> 1.440002
A51: Tractorista Rastra | B51: 3.8500084 | G51: =+B51/2 -> 1.9250042 | N51: =+B51/2 -> 1.9250042
A52: Tractor Atomizadora | B52: 6.9000537 | H52: =+B52*0.45 -> 3.1050242 | I52: =+B52*0.275 -> 1.8975148 | L52: =+B52*0.275 -> 1.8975148
A53: Tractor Herbicida | B53: 5.9999854 | H53: =+B53/4 -> 1.4999964 | I53: =+B53/4 -> 1.4999964 | J53: =+B53/4 -> 1.4999964 | L53: =+B53/4 -> 1.4999964
A54: Poda | B54: 78.538182 | D54: =+B54/3 -> 26.179394 | E54: =+B54/3 -> 26.179394 | F54: =+B54/3 -> 26.179394
A55: Atada | B55: 52.358788 | D55: =+B55/3 -> 17.452929 | E55: =+B55/3 -> 17.452929 | F55: =+B55/3 -> 17.452929
A56: Acomodo de brotes | B56: 0 | I56: =+B56 -> 0
A57: Desbrote de troncos | B57: 16.442 | H57: =+B57/2 -> 8.221 | J57: =+B57/2 -> 8.221
A58: Raleo de Racimos | B58: 0 | I58: =+B58 -> 0
A59: Desniete Deshoje | B59: 0 | J59: =+B59 -> 0
A60: Desbrote con criterio de Poda | B60: 11.744286 | H60: =+B60 -> 11.744286
A61: Superior | B61: 93.230286 | C61: =+SUM(C48:C60) -> 0 | D61: =+SUM(D48:D60) -> 43.632323 | E61: =+SUM(E48:E60) -> 43.632323 | F61: =+SUM(F48:F60) -> 49.872326 | G61: =+SUM(G48:G60) -> 1.9250042 | H61: =+SUM(H48:H60) -> 24.570306 | I61: =+SUM(I48:I60) -> 3.3975111 | J61: =+SUM(J48:J60) -> 9.7209964 | ... N61: =+SUM(N48:N60) -> 1.9250042
A62: Tractorista Subsolado | B62: 1 | F62: =+B62 -> 1
A63: Tractorista Triturado de sarmiento | B63: 1 | F63: =+B63 -> 1
A64: Tractorista Cincelado | B64: 1.3 | F64: =+B64 -> 1.3
A65: Tractorista Rastra | B65: 1 | G65: =+B65/2 -> 0.5 | N65: =+B65/2 -> 0.5
A66: Tractor Atomizadora | B66: 3.58 | G66: =+B66*0.45 -> 1.611 | I66: =+B66*0.275 -> 0.9845 | L66: =+B66*0.275 -> 0.9845
A67: Tractor Herbicida | B67: 3 | H67: =+B67/4 -> 0.75 | I67: =+B67/4 -> 0.75 | J67: =+B67/4 -> 0.75 | L67: =+B67/4 -> 0.75
A68: Poda | B68: 40.98 | D68: =+B68/3 -> 13.66 | E68: =+B68/3 -> 13.66 | F68: =+B68/3 -> 13.66
A69: Atada | B69: 27.32 | D69: =+B69/3 -> 9.1066667 | E69: =+B69/3 -> 9.1066667 | F69: =+B69/3 -> 9.1066667
A70: Acomodo de brotes | B70: 0 | I70: =+B70 -> 0
A71: Desbrote de troncos | B71: 8.196 | H71: =+B71/2 -> 4.098 | J71: =+B71/2 -> 4.098
A72: Raleo de Racimos | B72: 0 | I72: =+B72 -> 0
A73: Desniete Deshoje | B73: 0 | J73: =+B73 -> 0
A74: Desbrote con criterio de Poda | B74: 5.8542857 | H74: =+B74 -> 5.8542857
A75: Arizul | B75: 817.03782 | C75: =+SUM(C62:C74) -> 0 | D75: =+SUM(D62:D74) -> 22.766667 | E75: =+SUM(E62:E74) -> 22.766667 | F75: =+SUM(F62:F74) -> 26.066667 | G75: =+SUM(G62:G74) -> 2.111 | H75: =+SUM(H62:H74) -> 10.702286 | I75: =+SUM(I62:I74) -> 1.7345 | J75: =+SUM(J62:J74) -> 4.848 | ... N75: =+SUM(N62:N74) -> 0.5
A76: Tractorista Subsolado | B76: 10.9 | F76: =+B76 -> 10.9
A77: Tractorista Triturado de sarmiento | B77: 7.3000063 | F77: =+B77 -> 7.3000063
A78: Tractorista Cincelado | B78: 5.4700018 | F78: =+B78 -> 5.4700018
A79: Tractorista Rastra | B79: 21.860049 | G79: =+B79/2 -> 10.930025 | N79: =+B79/2 -> 10.930025
A80: Tractor Atomizadora | B80: 26.280014 | G80: =+B80*0.45 -> 11.826006 | I80: =+B80*0.275 -> 7.2270039 | L80: =+B80*0.275 -> 7.2270039
A81: Tractor Herbicida | B81: 21.999961 | H81: =+B81/4 -> 5.4999903 | I81: =+B81/4 -> 5.4999903 | J81: =+B81/4 -> 5.4999903 | L81: =+B81/4 -> 5.4999903
A82: Poda | B82: 295.64682 | D82: =+B82/3 -> 98.548939 | E82: =+B82/3 -> 98.548939 | F82: =+B82/3 -> 98.548939
A83: Atada | B83: 197.09788 | D83: =+B83/3 -> 65.699293 | E83: =+B83/3 -> 65.699293 | F83: =+B83/3 -> 65.699293
A84: Acomodo de brotes | B84: 75.391667 | I84: =+B84 -> 75.391667
A85: Desbrote de troncos | B85: 90.47 | H85: =+B85/2 -> 45.235 | J85: =+B85/2 -> 45.235
A86: Raleo de Racimos | B86: 0 | I86: =+B86 -> 0
A87: Desniete Deshoje | B87: 0 | J87: =+B87 -> 0
A88: Desbrote con criterio de Poda | B88: 64.621429 | H88: =+B88 -> 64.621429
A89: Total general | B89: 2444.6877 | C89: =+SUM(C76:C88) -> 0 | D89: =+SUM(D76:D88) -> 164.24823 | E89: =+SUM(E76:E88) -> 164.24823 | F89: =+SUM(F76:F88) -> 187.91824 | G89: =+SUM(G76:G88) -> 22.756031 | H89: =+SUM(H76:H88) -> 115.35642 | I89: =+SUM(I76:I88) -> 88.118661 | J89: =+SUM(J76:J88) -> 50.73499 | ... N89: =+SUM(N76:N88) -> 10.930025
A91: Total de Jornales Específicos | C91: =+C33+C47+C61+C75+C89 -> 0 | D91: =+D33+D47+D61+D75+D89 -> 505.08294 | E91: =+E33+E47+E61+E75+E89 -> 505.08294 | F91: =+F33+F47+F61+F75+F89 -> 576.83295 | G91: =+G33+G47+G61+G75+G89 -> 56.771135 | H91: =+H33+H47+H61+H75+H89 -> 305.61529 | I91: =+I33+I47+I61+I75+I89 -> 259.48438 | J91: =+J33+J47+J61+J75+J89 -> 173.73098 | ... N91: =+N33+N47+N61+N75+N89 -> 22.490048 | O91: =SUM(C91:N91) -> 2444.6877
A93: Etiquetas de fila | B93: Jorn
A94: Riego | B94: 543.99445 | C94: =+$B94*0.03 -> 16.319834 | D94: =+$B94*0.03 -> 16.319834 | E94: =+$B94*0.03 -> 16.319834 | F94: =+$B94*0.04 -> 21.759778 | G94: =+$B94*0.12 -> 65.279334 | H94: =+$B94*0.06 -> 32.639667 | I94: =+$B94*0.12 -> 65.279334 | J94: =+$B94*0.12 -> 65.279334 | K94: =+$B94*0.12 -> 65.279334 | L94: =+$B94*0.12 -> 65.279334 | M94: =+$B94*0.12 -> 65.279334 | N94: =+$B94*0.09 -> 48.959501
A95: Mantenimiento | B95: 40 | C95: =+B95/2 -> 20 | G95: =+B95/2 -> 20
A96: Mangueras | B96: 120 | G96: =+B96/2/2 -> 30 | J96: =+B96/2/2 -> 30 | N96: =+B96/2 -> 60
A97: Calicatas | B97: 12.000612 | C97: =+$B97/6 -> 2.000102 | E97: =+$B97/6 -> 2.000102 | G97: =+$B97/6 -> 2.000102 | I97: =+$B97/6 -> 2.000102 | K97: =+$B97/6 -> 2.000102 | M97: =+$B97/6 -> 2.000102
A98: Malezas Mochila | B98: 255.79565 | F98: =+$B98/2/2 -> 63.948913 | G98: =+$B98/2/2 -> 63.948913 | K98: =+$B98/2/2 -> 63.948913 | M98: =+$B98/2/2 -> 63.948913
A99: Desmalezar manual | B99: 100 | G99: =+$B99/3/2 -> 16.666667 | I99: =+$B99/3/2 -> 16.666667 | J99: =+$B99/3 -> 33.333333 | N99: =+$B99/3 -> 33.333333
A100: Jardinería | B100: 10 | G100: =+$B100/8 -> 1.25 | H100: =+$B100/8 -> 1.25 | I100: =+$B100/8 -> 1.25 | J100: =+$B100/8 -> 1.25 | K100: =+$B100/8 -> 1.25 | L100: =+$B100/8 -> 1.25 | M100: =+$B100/8 -> 1.25 | N100: =+$B100/8 -> 1.25
A101: Hormigas | B101: 62.01695 | E101: =+$B101*0.2/2 -> 6.201695 | F101: =+$B101*0.1 -> 6.201695 | G101: =+$B101*0.2/2 -> 6.201695 | H101: =+$B101*0.2 -> 12.40339 | I101: =+$B101*0.2 -> 12.40339 | J101: =+$B101*0.05 -> 3.1008475 | K101: =+$B101*0.05 -> 3.1008475 | L101: =+$B101*0.05 -> 3.1008475 | M101: =+$B101*0.05 -> 3.1008475 | N101: =+$B101*0.1 -> 6.201695
A102: Limpieza | B102: 32.999966 | D102: =+$B102/11 -> 2.9999969 | E102: =+$B102/11 -> 2.9999969 | F102: =+$B102/11 -> 2.9999969 | G102: =+$B102/11 -> 2.9999969 | H102: =+$B102/11 -> 2.9999969 | I102: =+$B102/11 -> 2.9999969 | J102: =+$B102/11 -> 2.9999969 | K102: =+$B102/11 -> 2.9999969 | ... N102: =+$B102/11 -> 2.9999969
...

Sheet Hoja1
A3: Suma de Jornales | B3: Etiquetas de columna
A4: Etiquetas de fila | B4: Camino Truncado | C4: El Espejo I | D4: El Espejo II | E4: El Espejo III | F4: La Chimbera | G4: Puente Alto | H4: Total general
A5: Camino Truncado | B5: 1233.3781 | H5: 1233.3781
A6: Colocación de malla | B6: 86.736597 | H6: 86.736597
A7: Dar vuelta la pasa | B7: 108.42095 | H7: 108.42095
A8: Descarga y carga de bines con Autoelevador | B8: 63.606681 | H8: 63.606681
A9: Desparramado de uva | B9: 140.94674 | H9: 140.94674
A10: Levantar pasa | B10: 165.54326 | H10: 165.54326
A11: Limpieza de secadero | B11: 10.842095 | H11: 10.842095
A12: Recolección de malla | B12: 86.736597 | H12: 86.736597
A13: Sereno | B13: 325.26164 | H13: 325.26164
A14: Tractor Cincelado de piedras | B14: 7.2280409 | H14: 7.2280409
A15: Tractor con acoplado | B15: 99.999823 | H15: 99.999823
A16: Tractor Descarga y carga de bines con tracto elevador | B16: 67.220813 | H16: 67.220813
A17: Tractor Volcado de bins | B17: 70.834914 | H17: 70.834914
A18: Grupo1 | C18: 279.95253 | D18: 44.811986 | H18: 324.76451
A19: Colocación de malla | C19: 12.023134 | H19: 12.023134
A20: Dar vuelta la pasa | C20: 24.254997 | H20: 24.254997
A21: Descarga y carga de bines con Autoelevador | C21: 6.2188557 | H21: 6.2188557
A22: Desparramado de uva | C22: 40.423975 | H22: 40.423975
A23: Levantar pasa | C23: 30.265184 | H23: 30.265184
A24: Limpieza de secadero | C24: 4.5604924 | H24: 4.5604924
A25: Recolección de malla | C25: 12.023134 | H25: 12.023134
A26: Sereno | C26: 80.24226 | H26: 80.24226
A27: Tractor con acoplado | C27: 43.188017 | D27: 44.811986 | H27: 88.000002
A28: Tractor Descarga y carga de bines con tracto elevador | C28: 6.6335363 | H28: 6.6335363
A29: Tractor Volcado de bins | C29: 20.118945 | H29: 20.118945
A30: El Espejo III | E30: 945.39835 | H30: 945.39835
A31: Colocación de malla | E31: 45.976964 | H31: 45.976964
A32: Dar vuelta la pasa | E32: 92.75212 | H32: 92.75212
A33: Descarga y carga de bines con Autoelevador | E33: 23.781164 | H33: 23.781164
A34: Desparramado de uva | E34: 154.58297 | H34: 154.58297
A35: Levantar pasa | E35: 115.73533 | H35: 115.73533
A36: Limpieza de secadero | E36: 17.439513 | H36: 17.439513
A37: Recolección de malla | E37: 45.976964 | H37: 45.976964
A38: Sereno | E38: 306.84975 | H38: 306.84975
A39: Tractor con acoplado | E39: 40.00098 | H39: 40.00098
A40: Tractor Descarga y carga de bines con tracto elevador | E40: 25.366919 | H40: 25.366919
A41: Tractor Volcado de bins | E41: 76.935685 | H41: 76.935685
A42: La Chimbera | F42: 315.0478 | H42: 315.0478
A43: Colocación de malla | F43: 18.000834 | H43: 18.000834
A44: Dar vuelta la pasa | F44: 35 | H44: 35
A45: Descarga y carga de bines con Autoelevador | F45: 8.0001235 | H45: 8.0001235
A46: Desparramado de uva | F46: 53.015548 | H46: 53.015548
A47: Levantar pasa | F47: 44.011549 | H47: 44.011549
A48: Limpieza de secadero | F48: 6.0002779 | H48: 6.0002779
A49: Recolección de malla | F49: 18.000834 | H49: 18.000834
A50: Sereno | F50: 98.01059 | H50: 98.01059
A51: Tractor Descarga y carga de bines con tracto elevador | F51: 9.0004168 | H51: 9.0004168
A52: Tractor Volcado de bins | F52: 26.007627 | H52: 26.007627
A53: Puente Alto | G53: 115.77873 | H53: 115.77873
A54: Colocación de malla | G54: 9.3214212 | H54: 9.3214212
A55: Dar vuelta la pasa | G55: 11.000731 | H55: 11.000731
A56: Descarga y carga de bines con Autoelevador | G56: 6.4900043 | H56: 6.4900043
A57: Desparramado de uva | G57: 15.001662 | H57: 15.001662
A58: Levantar pasa | G58: 17.002638 | H58: 17.002638
A59: Limpieza de secadero | G59: 1.1692989 | H59: 1.1692989
A60: Recolección de malla | G60: 9.0015959 | H60: 9.0015959
A61: Sereno | G61: 33.010241 | H61: 33.010241
A62: Tractor Cincelado de piedras | G62: 0.78000761 | H62: 0.78000761
A63: Tractor Descarga y carga de bines con tracto elevador | G63: 6.0006649 | H63: 6.0006649
A64: Tractor Volcado de bins | G64: 7.0004654 | H64: 7.0004654
A65: Total general | B65: 1233.3781 | C65: 279.95253 | D65: 44.811986 | E65: 945.39835 | F65: 315.0478 | G65: 115.77873 | H65: 2934.3675

Sheet Visualización Jornales PA
A1: Jornal Presupuestado | B1: $ | C1: =+INDEX(Tabla2[Precio Jornal],MATCH(C$19,Tabla2[Mes],0)) -> 19319.2 | D1: =+INDEX(Tabla2[Precio Jornal],MATCH(D$19,Tabla2[Mes],0)) -> 19646 | E1: =+INDEX(Tabla2[Precio Jornal],MATCH(E$19,Tabla2[Mes],0)) -> 19976.6 | F1: =+INDEX(Tabla2[Precio Jornal],MATCH(F$19,Tabla2[Mes],0)) -> 20312.9 | G1: =+INDEX(Tabla2[Precio Jornal],MATCH(G$19,Tabla2[Mes],0)) -> 20654.9 | H1: =+INDEX(Tabla2[Precio Jornal],MATCH(H$19,Tabla2[Mes],0)) -> 21002.6 | I1: =+INDEX(Tabla2[Precio Jornal],MATCH(I$19,Tabla2[Mes],0)) -> 21357.9 | J1: =+INDEX(Tabla2[Precio Jornal],MATCH(J$19,Tabla2[Mes],0)) -> 21717 | ... N1: =+INDEX(Tabla2[Precio Jornal],MATCH(N$19,Tabla2[Mes],0)) -> 23218
A2: Días Laborales | C2: 23.5 | D2: 20.5 | E2: 24 | F2: 24 | G2: 23 | H2: 24.5 | I2: 22.5 | J2: 23 | K2: 24 | L2: 20.5 | M2: 23 | N2: 22
A3: Jornales Disponibles PA | B3: 2 | C3: =+$B3*C2 -> 47 | D3: =+$B3*D2 -> 41 | E3: =+$B3*E2 -> 48 | F3: =+$B3*F2 -> 48 | G3: =+$B3*G2 -> 46 | H3: =+$B3*H2 -> 49 | I3: =+$B3*I2 -> 45 | J3: =+$B3*J2 -> 46 | ... N3: =+$B3*N2 -> 44 | O3: cosecha | P3: secado | Q3: gral | R3: Jorn/Has
A4: Jornales Cosecha | B4: =+SUMIFS(TablaGeneral[Anotador],TablaGeneral[Finca],A18)+SUMIFS(TablaGeneral[Tracto elevador],TablaGeneral[Finca],A18)+SUMIFS(TablaGeneral[Tractor con uñas],TablaGeneral[Finca],A18)+SUMIFS(TablaGeneral[Lavar Bines],TablaGeneral[Finca],A18)+SUMIFS(TablaGeneral[Tractor con acoplado],TablaGeneral[Finca],A18) -> 165.00433 | K4: =+B4*0.2 -> 33.000866 | L4: =+B4*0.4 -> 66.001732 | M4: =+B4*0.4 -> 66.001732 | O4: =SUM(C4:N4) -> 165.00433 | P4: =SUM(C5:N5) -> 32.4141 | Q4: =+O84 -> 1968.1007 | R4: =+(O4+P4+Q4)/SUMIFS(TablaGeneral[Has],TablaGeneral[Finca],A18) -> 80.863299 | S4: =+Q4/SUMIFS(TablaGeneral[Has],TablaGeneral[Finca],A18) -> 73.491439
A5: Jornales Secado | B5: =+SUMIFS(TablaGeneral[Resumen Jornales totales de Secado],TablaGeneral[Finca],"Puente Alto")*0.28 -> 32.418045 | C5: =+$B5*C18 -> 4.4610524 | D5: =+$B5*D18 -> 3.8408092 | E5: =+$B5*E18 -> 0 | F5: =+$B5*F18 -> 0 | G5: =+$B5*G18 -> 0.3101216 | H5: =+$B5*H18 -> 0 | I5: =+$B5*I18 -> 0 | J5: =+$B5*J18 -> 0.10337387 | ... N5: =+$B5*N18 -> 4.8745479 | Q5: =+Q4/27 -> 72.892619
A6: Jornales a contratar | B6: =SUM(C6:N6) -> 1616.5192 | C6: =+(C5+C4+C84)-C3 -> 152.94445 | D6: =+(D5+D4+D84)-D3 -> 170.43756 | E6: =+(E5+E4+E84)-E3 -> 158.96342 | F6: =+(F5+F4+F84)-F3 -> 236.42461 | G6: =+(G5+G4+G84)-G3 -> 36.690161 | H6: =+(H5+H4+H84)-H3 -> 279.23532 | I6: =+(I5+I4+I84)-I3 -> 167.14846 | J6: =+(J5+J4+J84)-J3 -> 166.61369 | ... N6: =+(N5+N4+N84)-N3 -> 30.385295
A7: Contratados PA $ | B7: =SUM(C7:N7) -> 33719119 | C7: =+C6*C1 -> 2954764.3 | D7: =+D6*D1 -> 3348416.3 | E7: =+E6*E1 -> 3175548.7 | F7: =+F6*F1 -> 4802469.4 | G7: =+G6*G1 -> 757831.61 | H7: =+H6*H1 -> 5864667.7 | I7: =+I6*I1 -> 3569940.1 | J7: =+J6*J1 -> 3618349.5 | ... N7: =+N6*N1 -> 705485.77 | P7: USD/Has
A8: Contratados PA USD | B8: =SUM(C8:N8) -> 28575.367 | C8: =+C7/INDEX(Tabla2[TC],MATCH(C19,Tabla2[Mes],0)) -> 2621.7962 | D8: =+D7/INDEX(Tabla2[TC],MATCH(D19,Tabla2[Mes],0)) -> 2941.6714 | E8: =+E7/INDEX(Tabla2[TC],MATCH(E19,Tabla2[Mes],0)) -> 2762.1809 | F8: =+F7/INDEX(Tabla2[TC],MATCH(F19,Tabla2[Mes],0)) -> 4135.9623 | G8: =+G7/INDEX(Tabla2[TC],MATCH(G19,Tabla2[Mes],0)) -> 646.19458 | H8: =+H7/INDEX(Tabla2[TC],MATCH(H19,Tabla2[Mes],0)) -> 4951.2246 | I8: =+I7/INDEX(Tabla2[TC],MATCH(I19,Tabla2[Mes],0)) -> 2984.0684 | J8: =+J7/INDEX(Tabla2[TC],MATCH(J19,Tabla2[Mes],0)) -> 2994.5873 | ... N8: =+N7/INDEX(Tabla2[TC],MATCH(N19,Tabla2[Mes],0)) -> 561.08574 | P8: =+B8/SUMIFS(TablaGeneral[Has],TablaGeneral[Finca],A18) -> 1067.0413
A9: Combustible Litros Gen | B9: =SUM(C9:N9) -> 1535.0073 | C9: =+(SUM(C20:C25,C34:C39,C48:C53,C74)*7.5) -> 30.000005 | D9: =+(SUM(D20:D25,D34:D39,D48:D53,D74)*7.5) -> 30.000005 | E9: =+(SUM(E20:E25,E34:E39,E48:E53,E74)*7.5) -> 30.000005 | F9: =+(SUM(F20:F25,F34:F39,F48:F53,F74)*7.5) -> 225.001 | G9: =+(SUM(G20:G25,G34:G39,G48:G53,G74)*7.5) -> 266.25001 | H9: =+(SUM(H20:H25,H34:H39,H48:H53,H74)*7.5) -> 247.12656 | I9: =+(SUM(I20:I25,I34:I39,I48:I53,I74)*7.5) -> 168.15781 | J9: =+(SUM(J20:J25,J34:J39,J48:J53,J74)*7.5) -> 44.064064 | ... N9: =+(SUM(N20:N25,N34:N39,N48:N53,N74)*7.5) -> 266.25001
A10: Combustible Litros Sec | B10: =SUM(C10:N10) -> 324.141 | C10: =+(SUMIFS(TablaGeneral[Resumen Jornales totales de Secado],TablaGeneral[Finca],"Puente alto"))*0.28*C18*10 -> 44.610524 | D10: =+(SUMIFS(TablaGeneral[Resumen Jornales totales de Secado],TablaGeneral[Finca],"Puente alto"))*0.28*D18*10 -> 38.408092 | E10: =+(SUMIFS(TablaGeneral[Resumen Jornales totales de Secado],TablaGeneral[Finca],"Puente alto"))*0.28*E18*10 -> 0 | F10: =+(SUMIFS(TablaGeneral[Resumen Jornales totales de Secado],TablaGeneral[Finca],"Puente alto"))*0.28*F18*10 -> 0 | G10: =+(SUMIFS(TablaGeneral[Resumen Jornales totales de Secado],TablaGeneral[Finca],"Puente alto"))*0.28*G18*10 -> 3.101216 | H10: =+(SUMIFS(TablaGeneral[Resumen Jornales totales de Secado],TablaGeneral[Finca],"Puente alto"))*0.28*H18*10 -> 0 | I10: =+(SUMIFS(TablaGeneral[Resumen Jornales totales de Secado],TablaGeneral[Finca],"Puente alto"))*0.28*I18*10 -> 0 | J10: =+(SUMIFS(TablaGeneral[Resumen Jornales totales de Secado],TablaGeneral[Finca],"Puente alto"))*0.28*J18*10 -> 1.0337387 | ... N10: =+(SUMIFS(TablaGeneral[Resumen Jornales totales de Secado],TablaGeneral[Finca],"Puente alto"))*0.28*N18*10 -> 48.745479
A11: Combustible Litros Cos | B11: =SUM(C11:N11) -> 960.10638 | K11: =+(SUMIFS(TablaGeneral[Tracto elevador],TablaGeneral[Finca],A18)+SUMIFS(TablaGeneral[Tractor con uñas],TablaGeneral[Finca],A18)+SUMIFS(TablaGeneral[Tractor con acoplado],TablaGeneral[Finca],A18))*0.2*10 -> 192.02128 | L11: =+(SUMIFS(TablaGeneral[Tracto elevador],TablaGeneral[Finca],A18)+SUMIFS(TablaGeneral[Tractor con uñas],TablaGeneral[Finca],A18)+SUMIFS(TablaGeneral[Tractor con acoplado],TablaGeneral[Finca],A18))*0.4*10 -> 384.04255 | M11: =+(SUMIFS(TablaGeneral[Tracto elevador],TablaGeneral[Finca],A18)+SUMIFS(TablaGeneral[Tractor con uñas],TablaGeneral[Finca],A18)+SUMIFS(TablaGeneral[Tractor con acoplado],TablaGeneral[Finca],A18))*0.4*10 -> 384.04255
A12: Combustible Litros Tot | B12: =SUM(C12:N12) -> 2819.2547 | C12: =SUM(C9:C11) -> 74.61053 | D12: =SUM(D9:D11) -> 68.408098 | E12: =SUM(E9:E11) -> 30.000005 | F12: =SUM(F9:F11) -> 225.001 | G12: =SUM(G9:G11) -> 269.35122 | H12: =SUM(H9:H11) -> 247.12656 | I12: =SUM(I9:I11) -> 168.15781 | J12: =SUM(J9:J11) -> 45.097802 | ... N12: =SUM(N9:N11) -> 314.99548
A13: Lubricantes Litros Totales | B13: =SUM(C13:N13) -> 61.083851 | C13: =+(C12/100)+(C12/150)+(C12/200) -> 1.6165615 | D13: =+(D12/100)+(D12/150)+(D12/200) -> 1.4821754 | E13: =+(E12/100)+(E12/150)+(E12/200) -> 0.65000012 | F13: =+(F12/100)+(F12/150)+(F12/200) -> 4.8750217 | G13: =+(G12/100)+(G12/150)+(G12/200) -> 5.8359431 | H13: =+(H12/100)+(H12/150)+(H12/200) -> 5.3544089 | I13: =+(I12/100)+(I12/150)+(I12/200) -> 3.6434193 | J13: =+(J12/100)+(J12/150)+(J12/200) -> 0.97711905 | ... N13: =+(N12/100)+(N12/150)+(N12/200) -> 6.8249022
A14: Combustible USD | B14: =SUM(C14:N14) -> 3503180.5 | C14: =+(INDEX(Tabla2[Combustible],MATCH(C19,Tabla2[Mes],0))*C12) -> 86188.218 | D14: =+(INDEX(Tabla2[Combustible],MATCH(D19,Tabla2[Mes],0))*D12) -> 79813.557 | E14: =+(INDEX(Tabla2[Combustible],MATCH(E19,Tabla2[Mes],0))*E12) -> 35351.827 | F14: =+(INDEX(Tabla2[Combustible],MATCH(F19,Tabla2[Mes],0))*F12) -> 267791.23 | G14: =+(INDEX(Tabla2[Combustible],MATCH(G19,Tabla2[Mes],0))*G12) -> 323781.65 | H14: =+(INDEX(Tabla2[Combustible],MATCH(H19,Tabla2[Mes],0))*H12) -> 300036.49 | I14: =+(INDEX(Tabla2[Combustible],MATCH(I19,Tabla2[Mes],0))*I12) -> 206202.1 | J14: =+(INDEX(Tabla2[Combustible],MATCH(J19,Tabla2[Mes],0))*J12) -> 55853.807 | ... N14: =+(INDEX(Tabla2[Combustible],MATCH(N19,Tabla2[Mes],0))*N12) -> 405963.72 | P14: =+(B14+B15)/SUMIFS(TablaGeneral[Has],TablaGeneral[Finca],A18) -> 146436.46
A15: Lubricantes USD | B15: =SUM(C15:N15) -> 418387.98 | C15: =+(INDEX(Tabla2[Lubricantes],MATCH(C19,Tabla2[Mes],0))*C13) -> 10293.536 | D15: =+(INDEX(Tabla2[Lubricantes],MATCH(D19,Tabla2[Mes],0))*D13) -> 9532.2045 | E15: =+(INDEX(Tabla2[Lubricantes],MATCH(E19,Tabla2[Mes],0))*E13) -> 4222.1003 | F15: =+(INDEX(Tabla2[Lubricantes],MATCH(F19,Tabla2[Mes],0))*F13) -> 31982.547 | G15: =+(INDEX(Tabla2[Lubricantes],MATCH(G19,Tabla2[Mes],0))*G13) -> 38669.531 | H15: =+(INDEX(Tabla2[Lubricantes],MATCH(H19,Tabla2[Mes],0))*H13) -> 35833.627 | I15: =+(INDEX(Tabla2[Lubricantes],MATCH(I19,Tabla2[Mes],0))*I13) -> 24626.901 | J15: =+(INDEX(Tabla2[Lubricantes],MATCH(J19,Tabla2[Mes],0))*J13) -> 6670.6701 | ... N15: =+(INDEX(Tabla2[Lubricantes],MATCH(N19,Tabla2[Mes],0))*N13) -> 48484.61
A16: Combustible Pesos | B16: =SUM(C16:N16) -> 2303452.7 | C16: =+(C9*INDEX(Tabla2[Combustible],MATCH(C19,Tabla2[Mes],0)))+(C13*INDEX(Tabla2[Lubricantes],MATCH(C19,Tabla2[Mes],0))) -> 44948.792 | D16: =+(D9*INDEX(Tabla2[Combustible],MATCH(D19,Tabla2[Mes],0)))+(D13*INDEX(Tabla2[Lubricantes],MATCH(D19,Tabla2[Mes],0))) -> 44534.013 | E16: =+(E9*INDEX(Tabla2[Combustible],MATCH(E19,Tabla2[Mes],0)))+(E13*INDEX(Tabla2[Lubricantes],MATCH(E19,Tabla2[Mes],0))) -> 39573.927 | F16: =+(F9*INDEX(Tabla2[Combustible],MATCH(F19,Tabla2[Mes],0)))+(F13*INDEX(Tabla2[Lubricantes],MATCH(F19,Tabla2[Mes],0))) -> 299773.78 | G16: =+(G9*INDEX(Tabla2[Combustible],MATCH(G19,Tabla2[Mes],0)))+(G13*INDEX(Tabla2[Lubricantes],MATCH(G19,Tabla2[Mes],0))) -> 358723.27 | H16: =+(H9*INDEX(Tabla2[Combustible],MATCH(H19,Tabla2[Mes],0)))+(H13*INDEX(Tabla2[Lubricantes],MATCH(H19,Tabla2[Mes],0))) -> 335870.12 | I16: =+(I9*INDEX(Tabla2[Combustible],MATCH(I19,Tabla2[Mes],0)))+(I13*INDEX(Tabla2[Lubricantes],MATCH(I19,Tabla2[Mes],0))) -> 230829 | J16: =+(J9*INDEX(Tabla2[Combustible],MATCH(J19,Tabla2[Mes],0)))+(J13*INDEX(Tabla2[Lubricantes],MATCH(J19,Tabla2[Mes],0))) -> 61244.187 | ... N16: =+(N9*INDEX(Tabla2[Combustible],MATCH(N19,Tabla2[Mes],0)))+(N13*INDEX(Tabla2[Lubricantes],MATCH(N19,Tabla2[Mes],0))) -> 391625.54
A17: Combustibles USD | B17: =SUM(C17:N17) -> 1918.5062 | C17: =+C16/INDEX(Tabla2[TC],MATCH(C19,Tabla2[Mes],0)) -> 39.883578 | D17: =+D16/INDEX(Tabla2[TC],MATCH(D19,Tabla2[Mes],0)) -> 39.124297 | E17: =+E16/INDEX(Tabla2[TC],MATCH(E19,Tabla2[Mes],0)) -> 34.422506 | F17: =+F16/INDEX(Tabla2[TC],MATCH(F19,Tabla2[Mes],0)) -> 258.1699 | G17: =+G16/INDEX(Tabla2[TC],MATCH(G19,Tabla2[Mes],0)) -> 305.87933 | H17: =+H16/INDEX(Tabla2[TC],MATCH(H19,Tabla2[Mes],0)) -> 283.55714 | I17: =+I16/INDEX(Tabla2[TC],MATCH(I19,Tabla2[Mes],0)) -> 192.94708 | J17: =+J16/INDEX(Tabla2[TC],MATCH(J19,Tabla2[Mes],0)) -> 50.686388 | ... N17: =+N16/INDEX(Tabla2[TC],MATCH(N19,Tabla2[Mes],0)) -> 311.46695 | P17: =SUM(C17:N17)/SUMIFS(TablaGeneral[Has],TablaGeneral[Finca],A18) -> 71.639516
A18: Puente Alto | B18: Jorn | C18: 0.13761016 | D18: 0.11847751 | E18: 0 | F18: 0 | G18: 0.0095663265 | H18: 0 | I18: 0 | J18: 0.0031887755 | K18: 0.07903824 | L18: 0.25998661 | M18: 0.24164543 | N18: 0.15036527
A19: Flame | B19: 707.19489 | C19: Mayo | D19: Junio | E19: Julio | F19: Agosto | G19: Septiembre | H19: Octubre | I19: Noviembre | J19: Diciembre | K19: Enero | L19: Febrero | M19: Marzo | N19: Abril
A20: Tractorista Subsolado | B20: 8.6508144 | F20: =+B20 -> 8.6508144
A21: Tractorista Triturado de sarmiento | B21: 3.7847313 | F21: =+B21 -> 3.7847313
A22: Tractorista Cincelado | B22: 1.6220996 | F22: =+B22 -> 1.6220996
A23: Tractorista Rastra | B23: 34.062582 | G23: =+B23/2 -> 17.031291 | N23: =+B23/2 -> 17.031291
A24: Tractor Atomizadora | B24: 32.530667 | H24: =+B24*0.45 -> 14.6388 | I24: =+B24*0.275 -> 8.9459333 | L24: =+B24*0.275 -> 8.9459333
A25: Tractor Herbicida | B25: 4.0555186 | H25: =+B25/4 -> 1.0138797 | I25: =+B25/4 -> 1.0138797 | J25: =+B25/4 -> 1.0138797 | L25: =+B25/4 -> 1.0138797
A26: Poda | B26: 182.81333 | D26: =+B26/3 -> 60.937778 | E26: =+B26/3 -> 60.937778 | F26: =+B26/3 -> 60.937778
A27: Atada | B27: 121.87556 | D27: =+B27/3 -> 40.625185 | E27: =+B27/3 -> 40.625185 | F27: =+B27/3 -> 40.625185
A28: Acomodo de brotes | B28: 81.326667 | I28: =+B28 -> 81.326667
A29: Desbrote de troncos | B29: 187.67692 | H29: =+B29/2 -> 93.838462 | J29: =+B29/2 -> 93.838462
A30: Raleo de Racimos | B30: 0 | I30: =+B30 -> 0
A31: Desniete Deshoje | B31: 0
A32: Desbrote con criterio de Poda | B32: 48.796 | H32: =+B32 -> 48.796
A33: Arizul | B33: 293.85887 | C33: =+SUM(C20:C32) -> 0 | D33: =+SUM(D20:D32) -> 101.56296 | E33: =+SUM(E20:E32) -> 101.56296 | F33: =+SUM(F20:F32) -> 115.62061 | G33: =+SUM(G20:G32) -> 17.031291 | H33: =+SUM(H20:H32) -> 158.28714 | I33: =+SUM(I20:I32) -> 91.28648 | J33: =+SUM(J20:J32) -> 94.852341 | ... N33: =+SUM(N20:N32) -> 17.031291
A34: Tractorista Subsolado | B34: 4.0452964 | F34: =+B34 -> 4.0452964
A35: Tractorista Triturado de sarmiento | B35: 1.7698172 | F35: =+B35 -> 1.7698172
A36: Tractorista Cincelado | B36: 0.75852669 | F36: =+B36 -> 0.75852669
A37: Tractorista Rastra | B37: 15.928355 | G37: =+B37/2 -> 7.9641773 | N37: =+B37/2 -> 7.9641773
A38: Tractor Atomizadora | B38: 15.212 | H38: =+B38*0.45 -> 6.8454 | I38: =+B38*0.275 -> 4.1833 | L38: =+B38*0.275 -> 4.1833
A39: Tractor Herbicida | B39: 1.8964428 | H39: =+B39/4 -> 0.4741107 | I39: =+B39/4 -> 0.4741107 | J39: =+B39/4 -> 0.4741107 | L39: =+B39/4 -> 0.4741107
A40: Poda | B40: 63.383333 | D40: =+B40/3 -> 21.127778 | E40: =+B40/3 -> 21.127778 | F40: =+B40/3 -> 21.127778
A41: Atada | B41: 42.255556 | D41: =+B41/3 -> 14.085185 | E41: =+B41/3 -> 14.085185 | F41: =+B41/3 -> 14.085185
A42: Acomodo de brotes | B42: 38.03 | I42: =+B42 -> 38.03
A43: Desbrote de troncos | B43: 87.761538 | H43: =+B43/2 -> 43.880769 | J43: =+B43/2 -> 43.880769
A44: Raleo de Racimos | B44: 0 | I44: =+B44 -> 0
A45: Desniete Deshoje | B45: 0 | J45: =+B45 -> 0
A46: Desbrote con criterio de Poda | B46: 22.818 | H46: =+B46 -> 22.818
A47: Selma | B47: 266.95401 | C47: =+SUM(C34:C46) -> 0 | D47: =+SUM(D34:D46) -> 35.212963 | E47: =+SUM(E34:E46) -> 35.212963 | F47: =+SUM(F34:F46) -> 41.786603 | G47: =+SUM(G34:G46) -> 7.9641773 | H47: =+SUM(H34:H46) -> 74.01828 | I47: =+SUM(I34:I46) -> 42.687411 | J47: =+SUM(J34:J46) -> 44.35488 | ... N47: =+SUM(N34:N46) -> 7.9641773
A48: Tractorista Subsolado | B48: 3.3038892 | F48: =+B48 -> 3.3038892
A49: Tractorista Triturado de sarmiento | B49: 1.4454515 | F49: =+B49 -> 1.4454515
A50: Tractorista Cincelado | B50: 0.61950668 | F50: =+B50 -> 0.61950668
A51: Tractorista Rastra | B51: 13.009064 | G51: =+B51/2 -> 6.5045319 | N51: =+B51/2 -> 6.5045319
A52: Tractor Atomizadora | B52: 12.424 | H52: =+B52*0.45 -> 5.5908 | I52: =+B52*0.275 -> 3.4166 | L52: =+B52*0.275 -> 3.4166
A53: Tractor Herbicida | B53: 1.5488697 | H53: =+B53/4 -> 0.38721742 | I53: =+B53/4 -> 0.38721742 | J53: =+B53/4 -> 0.38721742 | L53: =+B53/4 -> 0.38721742
A54: Poda | B54: 67.938182 | D54: =+B54/3 -> 22.646061 | E54: =+B54/3 -> 22.646061 | F54: =+B54/3 -> 22.646061
A55: Atada | B55: 45.292121 | D55: =+B55/3 -> 15.097374 | E55: =+B55/3 -> 15.097374 | F55: =+B55/3 -> 15.097374
A56: Acomodo de brotes | B56: 31.06 | I56: =+B56 -> 31.06
A57: Desbrote de troncos | B57: 71.676923 | H57: =+B57/2 -> 35.838462 | J57: =+B57/2 -> 35.838462
A58: Raleo de Racimos | B58: 0 | I58: =+B58 -> 0
A59: Desniete Deshoje | B59: 0 | J59: =+B59 -> 0
A60: Desbrote con criterio de Poda | B60: 18.636 | H60: =+B60 -> 18.636
A61: Total general | B61: 1268.0078 | C61: =+SUM(C48:C60) -> 0 | D61: =+SUM(D48:D60) -> 37.743434 | E61: =+SUM(E48:E60) -> 37.743434 | F61: =+SUM(F48:F60) -> 43.112282 | G61: =+SUM(G48:G60) -> 6.5045319 | H61: =+SUM(H48:H60) -> 60.452479 | I61: =+SUM(I48:I60) -> 34.863817 | J61: =+SUM(J48:J60) -> 36.225679 | ... N61: =+SUM(N48:N60) -> 6.5045319
A63: Total de Jornales Específicos | C63: =+C33+C47+C61 -> 0 | D63: =+D33+D47+D61 -> 174.51936 | E63: =+E33+E47+E61 -> 174.51936 | F63: =+F33+F47+F61 -> 200.51949 | G63: =+G33+G47+G61 -> 31.5 | H63: =+H33+H47+H61 -> 292.7579 | I63: =+I33+I47+I61 -> 168.83771 | J63: =+J33+J47+J61 -> 175.4329 | ... N63: =+N33+N47+N61 -> 31.5 | O63: =SUM(C63:N63) -> 1268.0078
A65: Etiquetas de fila | B65: Jorn
A66: Riego | B66: 100 | C66: =+$B66*0.03 -> 3 | D66: =+$B66*0.03 -> 3 | E66: =+$B66*0.03 -> 3 | F66: =+$B66*0.04 -> 4 | G66: =+$B66*0.06 -> 6 | H66: =+$B66*0.12 -> 12 | I66: =+$B66*0.12 -> 12 | J66: =+$B66*0.12 -> 12 | K66: =+$B66*0.12 -> 12 | L66: =+$B66*0.12 -> 12 | M66: =+$B66*0.12 -> 12 | N66: =+$B66*0.09 -> 9
A67: Calicatas | B67: 7 | C67: =+$B67/6 -> 1.1666667 | E67: =+$B67/6 -> 1.1666667 | G67: =+$B67/6 -> 1.1666667 | I67: =+$B67/6 -> 1.1666667 | K67: =+$B67/6 -> 1.1666667 | M67: =+$B67/6 -> 1.1666667
A68: Malezas Mochila | B68: 100.05543 | F68: =+$B68/2 -> 50.027716 | M68: =+$B68/2 -> 50.027716
A69: Desmalezar manual | B69: 20 | I69: =+$B69/3 -> 6.6666667 | J69: =+$B69/3 -> 6.6666667 | N69: =+$B69/3 -> 6.6666667
A70: Hormigas | B70: 16.000014 | F70: =+$B70*0.1 -> 1.6000014 | G70: =+$B70*0.2 -> 3.2000028 | H70: =+$B70*0.2 -> 3.2000028 | I70: =+$B70*0.2 -> 3.2000028 | J70: =+$B70*0.05 -> 0.80000071 | K70: =+$B70*0.05 -> 0.80000071 | L70: =+$B70*0.05 -> 0.80000071 | M70: =+$B70*0.05 -> 0.80000071 | N70: =+$B70*0.1 -> 1.6000014
A71: Limpieza | B71: 45.03493 | D71: =+$B71/11 -> 4.0940846 | E71: =+$B71/11 -> 4.0940846 | F71: =+$B71/11 -> 4.0940846 | G71: =+$B71/11 -> 4.0940846 | H71: =+$B71/11 -> 4.0940846 | I71: =+$B71/11 -> 4.0940846 | J71: =+$B71/11 -> 4.0940846 | K71: =+$B71/11 -> 4.0940846 | ... N71: =+$B71/11 -> 4.0940846
A72: Datos | B72: 20 | D72: =+$B72/7.5 -> 2.6666667 | E72: =+$B72/7.5 -> 2.6666667 | F72: =+$B72/7.5 -> 2.6666667 | H72: =+$B72/7.5 -> 2.6666667 | I72: =+$B72/7.5 -> 2.6666667 | K72: =+$B72/7.5 -> 2.6666667 | L72: =+$B72/7.5/2 -> 1.3333333 | M72: =+$B72/7.5/2 -> 1.3333333 | N72: =+$B72/7.5/2 -> 1.3333333
A73: Reparar Estructura | B73: 31.999915 | D73: =+$B73/4 -> 7.9999787 | E73: =+$B73/4 -> 7.9999787 | F73: =+$B73/4 -> 7.9999787 | G73: =+$B73/4 -> 7.9999787
A74: Tractorista Generales | B74: 48.000009 | C74: =+$B74/12 -> 4.0000007 | D74: =+$B74/12 -> 4.0000007 | E74: =+$B74/12 -> 4.0000007 | F74: =+$B74/12 -> 4.0000007 | G74: =+$B74/12 -> 4.0000007 | H74: =+$B74/12 -> 4.0000007 | I74: =+$B74/12 -> 4.0000007 | J74: =+$B74/12 -> 4.0000007 | ... N74: =+$B74/12 -> 4.0000007
A75: Hoyar y Replantar | B75: 17.002638 | G75: =+B75 -> 17.002638
A76: Varios | B76: 58.000018 | C76: =+$B76/12 -> 4.8333348 | D76: =+$B76/12 -> 4.8333348 | E76: =+$B76/12 -> 4.8333348 | F76: =+$B76/12 -> 4.8333348 | G76: =+$B76/12 -> 4.8333348 | H76: =+$B76/12 -> 4.8333348 | I76: =+$B76/12 -> 4.8333348 | J76: =+$B76/12 -> 4.8333348 | ... N76: =+$B76/12 -> 4.8333348
A77: P/ Medico | B77: 11.000007 | C77: =+$B77/12 -> 0.91666728 | D77: =+$B77/12 -> 0.91666728 | E77: =+$B77/12 -> 0.91666728 | F77: =+$B77/12 -> 0.91666728 | G77: =+$B77/12 -> 0.91666728 | H77: =+$B77/12 -> 0.91666728 | I77: =+$B77/12 -> 0.91666728 | J77: =+$B77/12 -> 0.91666728 | ... N77: =+$B77/12 -> 0.91666728
A78: Vacaciones | B78: 62.999986 | C78: =+B78 -> 62.999986
A79: Feriados | B79: 29.999934 | C79: =+$B79*0.13 -> 3.8999914 | D79: =+$B79*0.13 -> 3.8999914 | E79: =+$B79*0.07 -> 2.0999953 | F79: =+$B79*0.07 -> 2.0999953 | H79: =+$B79*0.07 -> 2.0999953 | I79: =+$B79*0.07 -> 2.0999953 | J79: =+$B79*0.07 -> 2.0999953 | K79: =+$B79*0.07 -> 2.0999953 | L79: =+$B79*0.13 -> 3.8999914 | M79: =+$B79*0.06 -> 1.799996 | N79: =+$B79*0.13 -> 3.8999914
A80: Mugrones | B80: 113.00008 | C80: =+B80 -> 113.00008
A81: Seguridad | B81: 20 | C81: =+$B81/12 -> 1.6666667 | D81: =+$B81/12 -> 1.6666667 | E81: =+$B81/12 -> 1.6666667 | F81: =+$B81/12 -> 1.6666667 | G81: =+$B81/12 -> 1.6666667 | H81: =+$B81/12 -> 1.6666667 | I81: =+$B81/12 -> 1.6666667 | J81: =+$B81/12 -> 1.6666667 | ... N81: =+$B81/12 -> 1.6666667
A82: Total Jornales Generales | B82: 700.09296 | C82: =SUM(C66:C81) -> 195.48339 | D82: =SUM(D66:D81) -> 33.077391 | E82: =SUM(E66:E81) -> 32.444061 | F82: =SUM(F66:F81) -> 83.905112 | G82: =SUM(G66:G81) -> 50.88004 | H82: =SUM(H66:H81) -> 35.477419 | I82: =SUM(I66:I81) -> 43.310752 | J82: =SUM(J66:J81) -> 37.077417 | ... N82: =SUM(N66:N81) -> 38.010747 | O82: =SUM(C82:N82) -> 700.09296
A83: Demanda de Jornales totales por mes
A84: Total Jornales | C84: =+C63+C82 -> 195.48339 | D84: =+D63+D82 -> 207.59675 | E84: =+E63+E82 -> 206.96342 | F84: =+F63+F82 -> 284.42461 | G84: =+G63+G82 -> 82.38004 | H84: =+H63+H82 -> 328.23532 | I84: =+I63+I82 -> 212.14846 | J84: =+J63+J82 -> 212.51032 | ... N84: =+N63+N82 -> 69.510747 | O84: =SUM(C84:N84) -> 1968.1007

Sheet Visualización Jornales LCH
A1: Jornal Presupuestado | B1: $ | C1: =+INDEX(Tabla2[Precio Jornal],MATCH(C$19,Tabla2[Mes],0)) -> 19319.2 | D1: =+INDEX(Tabla2[Precio Jornal],MATCH(D$19,Tabla2[Mes],0)) -> 19646 | E1: =+INDEX(Tabla2[Precio Jornal],MATCH(E$19,Tabla2[Mes],0)) -> 19976.6 | F1: =+INDEX(Tabla2[Precio Jornal],MATCH(F$19,Tabla2[Mes],0)) -> 20312.9 | G1: =+INDEX(Tabla2[Precio Jornal],MATCH(G$19,Tabla2[Mes],0)) -> 20654.9 | H1: =+INDEX(Tabla2[Precio Jornal],MATCH(H$19,Tabla2[Mes],0)) -> 21002.6 | I1: =+INDEX(Tabla2[Precio Jornal],MATCH(I$19,Tabla2[Mes],0)) -> 21357.9 | J1: =+INDEX(Tabla2[Precio Jornal],MATCH(J$19,Tabla2[Mes],0)) -> 21717 | ... N1: =+INDEX(Tabla2[Precio Jornal],MATCH(N$19,Tabla2[Mes],0)) -> 23218
A2: Días Laborales | C2: 23.5 | D2: 20.5 | E2: 24 | F2: 24 | G2: 23 | H2: 24.5 | I2: 22.5 | J2: 23 | K2: 24 | L2: 20.5 | M2: 23 | N2: 22
A3: Jornales Disponibles PA | B3: 3 | C3: =+$B3*C2 -> 70.5 | D3: =+$B3*D2 -> 61.5 | E3: =+$B3*E2 -> 72 | F3: =+$B3*F2 -> 72 | G3: =+$B3*G2 -> 69 | H3: =+$B3*H2 -> 73.5 | I3: =+$B3*I2 -> 67.5 | J3: =+$B3*J2 -> 69 | ... N3: =+$B3*N2 -> 66 | O3: cosecha | P3: secado | Q3: gral | R3: Jorn/Has
A4: Jornales Cosecha | B4: =+SUMIF(TablaGeneral[Finca],"La Chimbera",TablaGeneral[Resumen Jornales totales de Cosecha]) -> 283.04332 | K4: =+B4*0.2 -> 56.608664 | L4: =+B4*0.4 -> 113.21733 | M4: =+B4*0.4 -> 113.21733 | O4: =SUM(C4:N4) -> 283.04332 | P4: =SUM(C5:N5) -> 315.00946 | Q4: =+O85 -> 2516.6226 | R4: =+(O4+P4+Q4)/SUMIFS(TablaGeneral[Has],TablaGeneral[Finca],A18) -> 77.287231
A5: Jornales Secado | B5: =+SUMIFS(TablaGeneral[Resumen Jornales totales de Secado],TablaGeneral[Finca],"La Chimbera") -> 315.0478 | C5: =+$B5*C18 -> 43.353779 | D5: =+$B5*D18 -> 37.326079 | E5: =+$B5*E18 -> 0 | F5: =+$B5*F18 -> 0 | G5: =+$B5*G18 -> 3.0138501 | H5: =+$B5*H18 -> 0 | I5: =+$B5*I18 -> 0 | J5: =+$B5*J18 -> 1.0046167 | ... N5: =+$B5*N18 -> 47.372246 | Q5: =+Q4/40 -> 62.915566
A6: Jornales a contratar | B6: =SUM(C6:N6) -> 2291.1754 | C6: =+(C5+C4+C85)-C3 -> 165.54062 | D6: =+(D5+D4+D85)-D3 -> 267.97623 | E6: =+(E5+E4+E85)-E3 -> 218.84974 | F6: =+(F5+F4+F85)-F3 -> 261.63731 | G6: =+(G5+G4+G85)-G3 -> 68.725773 | H6: =+(H5+H4+H85)-H3 -> 236.30147 | I6: =+(I5+I4+I85)-I3 -> 347.79934 | J6: =+(J5+J4+J85)-J3 -> 265.64768 | ... N6: =+(N5+N4+N85)-N3 -> 23.501866
A7: Contratados LCH $ | B7: =SUM(C7:N7) -> 48106736 | C7: =+C6*C1 -> 3198112.4 | D7: =+D6*D1 -> 5264661.1 | E7: =+E6*E1 -> 4371873.7 | F7: =+F6*F1 -> 5314612.5 | G7: =+G6*G1 -> 1419524 | H7: =+H6*H1 -> 4962945.3 | I7: =+I6*I1 -> 7428263.6 | J7: =+J6*J1 -> 5769070.8 | ... N7: =+N6*N1 -> 545666.33 | P7: USD/Has
A8: Contratados LCH USD | B8: =SUM(C8:N8) -> 40608.532 | C8: =+C7/INDEX(Tabla2[TC],MATCH(C19,Tabla2[Mes],0)) -> 2837.7218 | D8: =+D7/INDEX(Tabla2[TC],MATCH(D19,Tabla2[Mes],0)) -> 4625.1426 | E8: =+E7/INDEX(Tabla2[TC],MATCH(E19,Tabla2[Mes],0)) -> 3802.7777 | F8: =+F7/INDEX(Tabla2[TC],MATCH(F19,Tabla2[Mes],0)) -> 4577.028 | G8: =+G7/INDEX(Tabla2[TC],MATCH(G19,Tabla2[Mes],0)) -> 1210.4123 | H8: =+H7/INDEX(Tabla2[TC],MATCH(H19,Tabla2[Mes],0)) -> 4189.9487 | I8: =+I7/INDEX(Tabla2[TC],MATCH(I19,Tabla2[Mes],0)) -> 6209.1928 | J8: =+J7/INDEX(Tabla2[TC],MATCH(J19,Tabla2[Mes],0)) -> 4774.5488 | ... N8: =+N7/INDEX(Tabla2[TC],MATCH(N19,Tabla2[Mes],0)) -> 433.97841 | P8: =+B8/SUMIFS(TablaGeneral[Has],TablaGeneral[Finca],A18) -> 1007.6559
A9: Combustible Litros Gen | B9: =SUM(C9:N9) -> 2262.2738 | C9: =+(SUM(C20:C25,C34:C39,C48:C53,C74)*13) -> 48.772585 | D9: =+(SUM(D20:D25,D34:D39,D48:D53,D74)*13) -> 48.772585 | E9: =+(SUM(E20:E25,E34:E39,E48:E53,E74)*13) -> 48.772585 | F9: =+(SUM(F20:F25,F34:F39,F48:F53,F74)*13) -> 295.61348 | G9: =+(SUM(G20:G25,G34:G39,G48:G53,G74)*13) -> 398.23732 | H9: =+(SUM(H20:H25,H34:H39,H48:H53,H74)*13) -> 348.16874 | I9: =+(SUM(I20:I25,I34:I39,I48:I53,I74)*13) -> 384.17306 | J9: =+(SUM(J20:J25,J34:J39,J48:J53,J74)*13) -> 126.77259 | ... N9: =+(SUM(N20:N25,N34:N39,N48:N53,N74)*13) -> 81.272585
A10: Combustible Litros Sec | B10: =SUM(C10:N10) -> 1207.2827 | C10: =+SUM(TablaGeneral[Tractor Volcado de bins],TablaGeneral[Tractor Cincelado de piedras],TablaGeneral[Tractor Carga de pasa],TablaGeneral[Tractor Descarga y carga de bines con tracto elevador],TablaGeneral[Descarga y carga de bines con Autoelevador])*10*C18*0.28 -> 166.15459 | D10: =+SUM(TablaGeneral[Tractor Volcado de bins],TablaGeneral[Tractor Cincelado de piedras],TablaGeneral[Tractor Carga de pasa],TablaGeneral[Tractor Descarga y carga de bines con tracto elevador],TablaGeneral[Descarga y carga de bines con Autoelevador])*10*D18*0.28 -> 143.05326 | E10: =+SUM(TablaGeneral[Tractor Volcado de bins],TablaGeneral[Tractor Cincelado de piedras],TablaGeneral[Tractor Carga de pasa],TablaGeneral[Tractor Descarga y carga de bines con tracto elevador],TablaGeneral[Descarga y carga de bines con Autoelevador])*10*E18*0.28 -> 0 | F10: =+SUM(TablaGeneral[Tractor Volcado de bins],TablaGeneral[Tractor Cincelado de piedras],TablaGeneral[Tractor Carga de pasa],TablaGeneral[Tractor Descarga y carga de bines con tracto elevador],TablaGeneral[Descarga y carga de bines con Autoelevador])*10*F18*0.28 -> 0 | G10: =+SUM(TablaGeneral[Tractor Volcado de bins],TablaGeneral[Tractor Cincelado de piedras],TablaGeneral[Tractor Carga de pasa],TablaGeneral[Tractor Descarga y carga de bines con tracto elevador],TablaGeneral[Descarga y carga de bines con Autoelevador])*10*G18*0.28 -> 11.550666 | H10: =+SUM(TablaGeneral[Tractor Volcado de bins],TablaGeneral[Tractor Cincelado de piedras],TablaGeneral[Tractor Carga de pasa],TablaGeneral[Tractor Descarga y carga de bines con tracto elevador],TablaGeneral[Descarga y carga de bines con Autoelevador])*10*H18*0.28 -> 0 | I10: =+SUM(TablaGeneral[Tractor Volcado de bins],TablaGeneral[Tractor Cincelado de piedras],TablaGeneral[Tractor Carga de pasa],TablaGeneral[Tractor Descarga y carga de bines con tracto elevador],TablaGeneral[Descarga y carga de bines con Autoelevador])*10*I18*0.28 -> 0 | J10: =+SUM(TablaGeneral[Tractor Volcado de bins],TablaGeneral[Tractor Cincelado de piedras],TablaGeneral[Tractor Carga de pasa],TablaGeneral[Tractor Descarga y carga de bines con tracto elevador],TablaGeneral[Descarga y carga de bines con Autoelevador])*10*J18*0.28 -> 3.850222 | ... N10: =+SUM(TablaGeneral[Tractor Volcado de bins],TablaGeneral[Tractor Cincelado de piedras],TablaGeneral[Tractor Carga de pasa],TablaGeneral[Tractor Descarga y carga de bines con tracto elevador],TablaGeneral[Descarga y carga de bines con Autoelevador])*10*N18*0.28 -> 181.55548
A11: Combustible Litros Cos | B11: =SUM(C11:N11) -> 2150.1046 | K11: =+(SUMIFS(TablaGeneral[Tracto elevador],TablaGeneral[Finca],A18)+SUMIFS(TablaGeneral[Tractor con uñas],TablaGeneral[Finca],A18)+SUMIFS(TablaGeneral[Tractor con acoplado],TablaGeneral[Finca],A18))*0.2*10 -> 430.02092 | L11: =+(SUMIFS(TablaGeneral[Tracto elevador],TablaGeneral[Finca],A18)+SUMIFS(TablaGeneral[Tractor con uñas],TablaGeneral[Finca],A18)+SUMIFS(TablaGeneral[Tractor con acoplado],TablaGeneral[Finca],A18))*0.4*10 -> 860.04183 | M11: =+(SUMIFS(TablaGeneral[Tracto elevador],TablaGeneral[Finca],A18)+SUMIFS(TablaGeneral[Tractor con uñas],TablaGeneral[Finca],A18)+SUMIFS(TablaGeneral[Tractor con acoplado],TablaGeneral[Finca],A18))*0.4*10 -> 860.04183
A12: Combustible Litros Tot | B12: =SUM(C12:N12) -> 5619.661 | C12: =SUM(C9:C11) -> 214.92717 | D12: =SUM(D9:D11) -> 191.82584 | E12: =SUM(E9:E11) -> 48.772585 | F12: =SUM(F9:F11) -> 295.61348 | G12: =SUM(G9:G11) -> 409.78799 | H12: =SUM(H9:H11) -> 348.16874 | I12: =SUM(I9:I11) -> 384.17306 | J12: =SUM(J9:J11) -> 130.62281 | ... N12: =SUM(N9:N11) -> 262.82806
A13: Lubricantes Litros Totales | B13: =SUM(C13:N13) -> 121.75932 | C13: =+(C12/100)+(C12/150)+(C12/200) -> 4.6567554 | D13: =+(D12/100)+(D12/150)+(D12/200) -> 4.1562265 | E13: =+(E12/100)+(E12/150)+(E12/200) -> 1.0567393 | F13: =+(F12/100)+(F12/150)+(F12/200) -> 6.4049587 | G13: =+(G12/100)+(G12/150)+(G12/200) -> 8.8787398 | H13: =+(H12/100)+(H12/150)+(H12/200) -> 7.5436561 | I13: =+(I12/100)+(I12/150)+(I12/200) -> 8.3237497 | J13: =+(J12/100)+(J12/150)+(J12/200) -> 2.8301608 | ... N13: =+(N12/100)+(N12/150)+(N12/200) -> 5.694608
A14: Combustible USD | B14: =SUM(C14:N14) -> 6987115.3 | C14: =+(INDEX(Tabla2[Combustible],MATCH(C19,Tabla2[Mes],0))*C12) -> 248278.5 | D14: =+(INDEX(Tabla2[Combustible],MATCH(D19,Tabla2[Mes],0))*D12) -> 223808.34 | E14: =+(INDEX(Tabla2[Combustible],MATCH(E19,Tabla2[Mes],0))*E12) -> 57473.323 | F14: =+(INDEX(Tabla2[Combustible],MATCH(F19,Tabla2[Mes],0))*F12) -> 351832.65 | G14: =+(INDEX(Tabla2[Combustible],MATCH(G19,Tabla2[Mes],0))*G12) -> 492597.84 | H14: =+(INDEX(Tabla2[Combustible],MATCH(H19,Tabla2[Mes],0))*H12) -> 422711.86 | I14: =+(INDEX(Tabla2[Combustible],MATCH(I19,Tabla2[Mes],0))*I12) -> 471088.97 | J14: =+(INDEX(Tabla2[Combustible],MATCH(J19,Tabla2[Mes],0))*J12) -> 161776.86 | ... N14: =+(INDEX(Tabla2[Combustible],MATCH(N19,Tabla2[Mes],0))*N12) -> 338730.75
A15: Lubricantes USD | B15: =SUM(C15:N15) -> 834477.43 | C15: =+(INDEX(Tabla2[Lubricantes],MATCH(C19,Tabla2[Mes],0))*C13) -> 29652.123 | D15: =+(INDEX(Tabla2[Lubricantes],MATCH(D19,Tabla2[Mes],0))*D13) -> 26729.63 | E15: =+(INDEX(Tabla2[Lubricantes],MATCH(E19,Tabla2[Mes],0))*E13) -> 6864.0903 | F15: =+(INDEX(Tabla2[Lubricantes],MATCH(F19,Tabla2[Mes],0))*F13) -> 42019.688 | G15: =+(INDEX(Tabla2[Lubricantes],MATCH(G19,Tabla2[Mes],0))*G13) -> 58831.4 | H15: =+(INDEX(Tabla2[Lubricantes],MATCH(H19,Tabla2[Mes],0))*H13) -> 50484.855 | I15: =+(INDEX(Tabla2[Lubricantes],MATCH(I19,Tabla2[Mes],0))*I13) -> 56262.577 | J15: =+(INDEX(Tabla2[Lubricantes],MATCH(J19,Tabla2[Mes],0))*J13) -> 19321.155 | ... N15: =+(INDEX(Tabla2[Lubricantes],MATCH(N19,Tabla2[Mes],0))*N13) -> 40454.916
A16: Combustible Pesos | B16: =SUM(C16:N16) -> 3599902.1 | C16: =+(C9*INDEX(Tabla2[Combustible],MATCH(C19,Tabla2[Mes],0)))+(C13*INDEX(Tabla2[Lubricantes],MATCH(C19,Tabla2[Mes],0))) -> 85992.994 | D16: =+(D9*INDEX(Tabla2[Combustible],MATCH(D19,Tabla2[Mes],0)))+(D13*INDEX(Tabla2[Lubricantes],MATCH(D19,Tabla2[Mes],0))) -> 83633.91 | E16: =+(E9*INDEX(Tabla2[Combustible],MATCH(E19,Tabla2[Mes],0)))+(E13*INDEX(Tabla2[Lubricantes],MATCH(E19,Tabla2[Mes],0))) -> 64337.413 | F16: =+(F9*INDEX(Tabla2[Combustible],MATCH(F19,Tabla2[Mes],0)))+(F13*INDEX(Tabla2[Lubricantes],MATCH(F19,Tabla2[Mes],0))) -> 393852.34 | G16: =+(G9*INDEX(Tabla2[Combustible],MATCH(G19,Tabla2[Mes],0)))+(G13*INDEX(Tabla2[Lubricantes],MATCH(G19,Tabla2[Mes],0))) -> 537544.42 | H16: =+(H9*INDEX(Tabla2[Combustible],MATCH(H19,Tabla2[Mes],0)))+(H13*INDEX(Tabla2[Lubricantes],MATCH(H19,Tabla2[Mes],0))) -> 473196.71 | I16: =+(I9*INDEX(Tabla2[Combustible],MATCH(I19,Tabla2[Mes],0)))+(I13*INDEX(Tabla2[Lubricantes],MATCH(I19,Tabla2[Mes],0))) -> 527351.54 | J16: =+(J9*INDEX(Tabla2[Combustible],MATCH(J19,Tabla2[Mes],0)))+(J13*INDEX(Tabla2[Lubricantes],MATCH(J19,Tabla2[Mes],0))) -> 176329.5 | ... N16: =+(N9*INDEX(Tabla2[Combustible],MATCH(N19,Tabla2[Mes],0)))+(N13*INDEX(Tabla2[Lubricantes],MATCH(N19,Tabla2[Mes],0))) -> 145198.39
A17: Combustibles USD | B17: =SUM(C17:N17) -> 3006.7708 | C17: =+C16/INDEX(Tabla2[TC],MATCH(C19,Tabla2[Mes],0)) -> 76.302568 | D17: =+D16/INDEX(Tabla2[TC],MATCH(D19,Tabla2[Mes],0)) -> 73.47458 | E17: =+E16/INDEX(Tabla2[TC],MATCH(E19,Tabla2[Mes],0)) -> 55.962477 | F17: =+F16/INDEX(Tabla2[TC],MATCH(F19,Tabla2[Mes],0)) -> 339.19183 | G17: =+G16/INDEX(Tabla2[TC],MATCH(G19,Tabla2[Mes],0)) -> 458.35814 | H17: =+H16/INDEX(Tabla2[TC],MATCH(H19,Tabla2[Mes],0)) -> 399.49462 | I17: =+I16/INDEX(Tabla2[TC],MATCH(I19,Tabla2[Mes],0)) -> 440.80657 | J17: =+J16/INDEX(Tabla2[TC],MATCH(J19,Tabla2[Mes],0)) -> 145.93231 | ... N17: =+N16/INDEX(Tabla2[TC],MATCH(N19,Tabla2[Mes],0)) -> 115.47893 | P17: =SUM(C17:N17)/SUMIFS(TablaGeneral[Has],TablaGeneral[Finca],A18) -> 74.609697
A18: La Chimbera | B18: Jorn | C18: 0.13761016 | D18: 0.11847751 | E18: 0 | F18: 0 | G18: 0.0095663265 | H18: 0 | I18: 0 | J18: 0.0031887755 | K18: 0.07903824 | L18: 0.25998661 | M18: 0.24164543 | N18: 0.15036527
A19: Flame | B19: 893.41487 | C19: Mayo | D19: Junio | E19: Julio | F19: Agosto | G19: Septiembre | H19: Octubre | I19: Noviembre | J19: Diciembre | K19: Enero | L19: Febrero | M19: Marzo | N19: Abril
A20: Tractorista Subsolado | B20: 9.0123167 | G20: =+B20 -> 9.0123167
A21: Tractorista Triturado de sarmiento | B21: 2.3718453 | F21: =+B21 -> 2.3718453
A22: Tractorista Cincelado | B22: 1.8982088 | F22: =+B22 -> 1.8982088
A23: Tractorista Rastra | B23: 2.3718453 | G23: =+B23/2 -> 1.1859227 | N23: =+B23/2 -> 1.1859227
A24: Tractor Atomizadora | B24: 34.154636 | G24: =+B24*0.45 -> 15.369586 | I24: =+B24*0.275 -> 9.3925249 | L24: =+B24*0.275 -> 9.3925249
A25: Tractor Herbicida | B25: 11.384858 | H25: =+B25/4 -> 2.8462144 | I25: =+B25/4 -> 2.8462144 | J25: =+B25/4 -> 2.8462144 | L25: =+B25/4 -> 2.8462144
A26: Poda | B26: 236.4 | D26: =+B26/3 -> 78.8 | E26: =+B26/3 -> 78.8 | F26: =+B26/3 -> 78.8
A27: Atada | B27: 157.6 | D27: =+B27/3 -> 52.533333 | E27: =+B27/3 -> 52.533333 | F27: =+B27/3 -> 52.533333
A28: Acomodo de brotes | B28: 61.464 | I28: =+B28 -> 61.464
A29: Desbrote de troncos | B29: 151.38916 | G29: =+B29/2/2 -> 37.847291 | H29: =+B29/2/2 -> 37.847291 | J29: =+B29/2 -> 75.694581
A30: Raleo de Racimos | B30: 102.44 | I30: =+B30 -> 102.44
A31: Desniete Deshoje | B31: 61.464 | J31: =+B31 -> 61.464
A32: Desbrote con criterio de Poda | B32: 61.464 | H32: =+B32 -> 61.464
A33: Arizul | B33: 518.38423 | C33: =+SUM(C20:C32) -> 0 | D33: =+SUM(D20:D32) -> 131.33333 | E33: =+SUM(E20:E32) -> 131.33333 | F33: =+SUM(F20:F32) -> 135.60339 | G33: =+SUM(G20:G32) -> 63.415116 | H33: =+SUM(H20:H32) -> 102.15751 | I33: =+SUM(I20:I32) -> 176.14274 | J33: =+SUM(J20:J32) -> 140.0048 | ... N33: =+SUM(N20:N32) -> 1.1859227
A34: Tractorista Subsolado | B34: 5.3560117 | F34: =+B34 -> 5.3560117
A35: Tractorista Triturado de sarmiento | B35: 1.4095856 | F35: =+B35 -> 1.4095856
A36: Tractorista Cincelado | B36: 1.1281038 | F36: =+B36 -> 1.1281038
A37: Tractorista Rastra | B37: 1.4095856 | G37: =+B37/2 -> 0.70479278 | N37: =+B37/2 -> 0.70479278
A38: Tractor Atomizadora | B38: 20.29807 | H38: =+B38*0.45 -> 9.1341313 | I38: =+B38*0.275 -> 5.5819691 | L38: =+B38*0.275 -> 5.5819691
A39: Tractor Herbicida | B39: 6.7660107 | H39: =+B39/4 -> 1.6915027 | I39: =+B39/4 -> 1.6915027 | J39: =+B39/4 -> 1.6915027 | L39: =+B39/4 -> 1.6915027
A40: Poda | B40: 132.94945 | D40: =+B40/3 -> 44.316484 | E40: =+B40/3 -> 44.316484 | F40: =+B40/3 -> 44.316484
A41: Atada | B41: 88.632967 | D41: =+B41/3 -> 29.544322 | E41: =+B41/3 -> 29.544322 | F41: =+B41/3 -> 29.544322
A42: Acomodo de brotes | B42: 36.528 | I42: =+B42 -> 36.528
A43: Desbrote de troncos | B43: 89.970443 | H43: =+B43/2 -> 44.985222 | J43: =+B43/2 -> 44.985222
A44: Raleo de Racimos | B44: 60.88 | I44: =+B44 -> 60.88
A45: Desniete Deshoje | B45: 36.528 | J45: =+B45 -> 36.528
A46: Desbrote con criterio de Poda | B46: 36.528 | H46: =+B46 -> 36.528
A47: Fiesta | B47: 417.75098 | C47: =+SUM(C34:C46) -> 0 | D47: =+SUM(D34:D46) -> 73.860806 | E47: =+SUM(E34:E46) -> 73.860806 | F47: =+SUM(F34:F46) -> 81.754507 | G47: =+SUM(G34:G46) -> 0.70479278 | H47: =+SUM(H34:H46) -> 92.338856 | I47: =+SUM(I34:I46) -> 104.68147 | J47: =+SUM(J34:J46) -> 83.204724 | ... N47: =+SUM(N34:N46) -> 0.70479278
A48: Tractorista Subsolado | B48: 4.6302053 | F48: =+B48 -> 4.6302053
A49: Tractorista Triturado de sarmiento | B49: 1.2185691 | F49: =+B49 -> 1.2185691
A50: Tractorista Cincelado | B50: 0.97523162 | F50: =+B50 -> 0.97523162
A51: Tractorista Rastra | B51: 1.2185691 | G51: =+B51/2 -> 0.60928456 | N51: =+B51/2 -> 0.60928456
A52: Tractor Atomizadora | B52: 17.547428 | H52: =+B52*0.45 -> 7.8963425 | I52: =+B52*0.275 -> 4.8255426 | L52: =+B52*0.275 -> 4.8255426
A53: Tractor Herbicida | B53: 5.8491317 | H53: =+B53/4 -> 1.4622829 | I53: =+B53/4 -> 1.4622829 | J53: =+B53/4 -> 1.4622829 | L53: =+B53/4 -> 1.4622829
A54: Poda | B54: 96.701709 | D54: =+B54/3 -> 32.233903 | E54: =+B54/3 -> 32.233903 | F54: =+B54/3 -> 32.233903
A55: Atada | B55: 64.467806 | D55: =+B55/3 -> 21.489269 | E55: =+B55/3 -> 21.489269 | F55: =+B55/3 -> 21.489269
A56: Acomodo de brotes | B56: 31.578 | I56: =+B56 -> 31.578
A57: Desbrote de troncos | B57: 77.778325 | H57: =+B57/2 -> 38.889163 | J57: =+B57/2 -> 38.889163
A58: Raleo de Racimos | B58: 52.63 | I58: =+B58 -> 52.63
A59: Desniete Deshoje | B59: 31.578 | J59: =+B59 -> 31.578
A60: Desbrote con criterio de Poda | B60: 31.578 | H60: =+B60 -> 31.578
A61: Total general | B61: 1829.5501 | C61: =+SUM(C48:C60) -> 0 | D61: =+SUM(D48:D60) -> 53.723172 | E61: =+SUM(E48:E60) -> 53.723172 | F61: =+SUM(F48:F60) -> 60.547178 | G61: =+SUM(G48:G60) -> 0.60928456 | H61: =+SUM(H48:H60) -> 79.825788 | I61: =+SUM(I48:I60) -> 90.495826 | J61: =+SUM(J48:J60) -> 71.929445 | ... N61: =+SUM(N48:N60) -> 0.60928456
A63: Total de Jornales Específicos | C63: =+C33+C47+C61 -> 0 | D63: =+D33+D47+D61 -> 258.91731 | E63: =+E33+E47+E61 -> 258.91731 | F63: =+F33+F47+F61 -> 277.90507 | G63: =+G33+G47+G61 -> 64.729194 | H63: =+H33+H47+H61 -> 274.32215 | I63: =+I33+I47+I61 -> 371.32004 | J63: =+J33+J47+J61 -> 295.13897 | ... N63: =+N33+N47+N61 -> 2.5 | O63: =SUM(C63:N63) -> 1829.5501
A65: Etiquetas de fila | B65: Jorn
A66: Riego | B66: 90.000042 | C66: =+$B66*0.03 -> 2.7000013 | D66: =+$B66*0.03 -> 2.7000013 | E66: =+$B66*0.03 -> 2.7000013 | F66: =+$B66*0.04 -> 3.6000017 | G66: =+$B66*0.06 -> 5.4000025 | H66: =+$B66*0.12 -> 10.800005 | I66: =+$B66*0.12 -> 10.800005 | J66: =+$B66*0.12 -> 10.800005 | K66: =+$B66*0.12 -> 10.800005 | L66: =+$B66*0.12 -> 10.800005 | M66: =+$B66*0.12 -> 10.800005 | N66: =+$B66*0.09 -> 8.1000038
A67: Calicatas | B67: 3 | C67: =+$B67/6 -> 0.5 | E67: =+$B67/6 -> 0.5 | G67: =+$B67/6 -> 0.5 | I67: =+$B67/6 -> 0.5 | K67: =+$B67/6 -> 0.5 | M67: =+$B67/6 -> 0.5
A68: Malezas Mochila | B68: 95.000051 | F68: =+$B68/2/2 -> 23.750013 | G68: =+$B68/2/2 -> 23.750013 | M68: =+$B68/2 -> 47.500026
A69: Desmalezar manual | B69: 23.999956 | I69: =+$B69/3 -> 7.9999852 | J69: =+$B69/3 -> 7.9999852 | N69: =+$B69/3 -> 7.9999852
A70: Hormigas | B70: 18.50001 | F70: =+$B70*0.1 -> 1.850001 | G70: =+$B70*0.2 -> 3.700002 | H70: =+$B70*0.2 -> 3.700002 | I70: =+$B70*0.2 -> 3.700002 | J70: =+$B70*0.05 -> 0.9250005 | K70: =+$B70*0.05 -> 0.9250005 | L70: =+$B70*0.05 -> 0.9250005 | M70: =+$B70*0.05 -> 0.9250005 | N70: =+$B70*0.1 -> 1.850001
A71: Limpieza | B71: 45.020848 | D71: =+$B71/11 -> 4.0928043 | E71: =+$B71/11 -> 4.0928043 | F71: =+$B71/11 -> 4.0928043 | G71: =+$B71/11 -> 4.0928043 | H71: =+$B71/11 -> 4.0928043 | I71: =+$B71/11 -> 4.0928043 | J71: =+$B71/11 -> 4.0928043 | K71: =+$B71/11 -> 4.0928043 | ... N71: =+$B71/11 -> 4.0928043
A72: Datos | B72: 16.501528 | D72: =+$B72/7.5 -> 2.2002038 | E72: =+$B72/7.5 -> 2.2002038 | G72: =+$B72/7.5 -> 2.2002038 | H72: =+$B72/7.5 -> 2.2002038 | I72: =+$B72/7.5 -> 2.2002038 | K72: =+$B72/7.5 -> 2.2002038 | L72: =+$B72/7.5/2 -> 1.1001019 | M72: =+$B72/7.5/2 -> 1.1001019 | N72: =+$B72/7.5/2 -> 1.1001019
A73: Reparar Estructura | B73: 31.012446 | D73: =+$B73/4 -> 7.7531115 | E73: =+$B73/4 -> 7.7531115 | F73: =+$B73/4 -> 7.7531115 | G73: =+$B73/4 -> 7.7531115
A74: Tractorista Generales | B74: 45.020848 | C74: =+$B74/12 -> 3.7517373 | D74: =+$B74/12 -> 3.7517373 | E74: =+$B74/12 -> 3.7517373 | F74: =+$B74/12 -> 3.7517373 | G74: =+$B74/12 -> 3.7517373 | H74: =+$B74/12 -> 3.7517373 | I74: =+$B74/12 -> 3.7517373 | J74: =+$B74/12 -> 3.7517373 | ... N74: =+$B74/12 -> 3.7517373
A75: Hoyar y Replantar | B75: 10.000772 | G75: =+B75 -> 10.000772
A76: Varios | B76: 34.007874 | C76: =+$B76/12 -> 2.8339895 | D76: =+$B76/12 -> 2.8339895 | E76: =+$B76/12 -> 2.8339895 | F76: =+$B76/12 -> 2.8339895 | G76: =+$B76/12 -> 2.8339895 | H76: =+$B76/12 -> 2.8339895 | I76: =+$B76/12 -> 2.8339895 | J76: =+$B76/12 -> 2.8339895 | ... N76: =+$B76/12 -> 2.8339895
A77: P/ Medico | B77: 11.001019 | C77: =+$B77/12 -> 0.91675157 | D77: =+$B77/12 -> 0.91675157 | E77: =+$B77/12 -> 0.91675157 | F77: =+$B77/12 -> 0.91675157 | G77: =+$B77/12 -> 0.91675157 | H77: =+$B77/12 -> 0.91675157 | I77: =+$B77/12 -> 0.91675157 | J77: =+$B77/12 -> 0.91675157 | ... N77: =+$B77/12 -> 0.91675157
A78: Vacaciones | B78: 63.000204 | C78: =+B78 -> 63.000204
A79: Feriados | B79: 30.006948 | C79: =+$B79*0.13 -> 3.9009032 | D79: =+$B79*0.13 -> 3.9009032 | E79: =+$B79*0.07 -> 2.1004863 | F79: =+$B79*0.07 -> 2.1004863 | H79: =+$B79*0.07 -> 2.1004863 | I79: =+$B79*0.07 -> 2.1004863 | J79: =+$B79*0.07 -> 2.1004863 | K79: =+$B79*0.07 -> 2.1004863 | L79: =+$B79*0.13 -> 3.9009032 | M79: =+$B79*0.06 -> 1.8004169 | N79: =+$B79*0.13 -> 3.9009032
A80: Mugrones | B80: 109.99992 | C80: =+B80 -> 109.99992
A81: Seguridad | B81: 12 | C81: =+$B81/12 -> 1 | D81: =+$B81/12 -> 1 | E81: =+$B81/12 -> 1 | F81: =+$B81/12 -> 1 | G81: =+$B81/12 -> 1 | H81: =+$B81/12 -> 1 | I81: =+$B81/12 -> 1 | J81: =+$B81/12 -> 1 | ... N81: =+$B81/12 -> 1
A82: Mantenimiento | B82: 49.000106 | C82: =+$B82/12 -> 4.0833422 | D82: =+$B82/12 -> 4.0833422 | E82: =+$B82/12 -> 4.0833422 | F82: =+$B82/12 -> 4.0833422 | G82: =+$B82/12 -> 4.0833422 | H82: =+$B82/12 -> 4.0833422 | I82: =+$B82/12 -> 4.0833422 | J82: =+$B82/12 -> 4.0833422 | ... N82: =+$B82/12 -> 4.0833422
A83: Total Jornales Generales | B83: 687.07257 | C83: =SUM(C66:C82) -> 192.68684 | D83: =SUM(D66:D82) -> 33.232845 | E83: =SUM(E66:E82) -> 31.932428 | F83: =SUM(F66:F82) -> 55.732238 | G83: =SUM(G66:G82) -> 69.982729 | H83: =SUM(H66:H82) -> 35.479322 | I83: =SUM(I66:I82) -> 43.979307 | J83: =SUM(J66:J82) -> 38.504102 | ... N83: =SUM(N66:N82) -> 39.62962 | O83: =SUM(C83:N83) -> 687.07257
A84: Demanda de Jornales totales por mes
A85: Total Jornales | C85: =+C63+C83 -> 192.68684 | D85: =+D63+D83 -> 292.15016 | E85: =+E63+E83 -> 290.84974 | F85: =+F63+F83 -> 333.63731 | G85: =+G63+G83 -> 134.71192 | H85: =+H63+H83 -> 309.80147 | I85: =+I63+I83 -> 415.29934 | J85: =+J63+J83 -> 333.64307 | ... N85: =+N63+N83 -> 42.12962 | O85: =SUM(C85:N85) -> 2516.6226

Sheet Visualización Jornales EE
A1: Jornal Presupuestado | B1: $ | C1: =+INDEX(Tabla2[Precio Jornal],MATCH(C$25,Tabla2[Mes],0)) -> 19319.2 | D1: =+INDEX(Tabla2[Precio Jornal],MATCH(D$25,Tabla2[Mes],0)) -> 19646 | E1: =+INDEX(Tabla2[Precio Jornal],MATCH(E$25,Tabla2[Mes],0)) -> 19976.6 | F1: =+INDEX(Tabla2[Precio Jornal],MATCH(F$25,Tabla2[Mes],0)) -> 20312.9 | G1: =+INDEX(Tabla2[Precio Jornal],MATCH(G$25,Tabla2[Mes],0)) -> 20654.9 | H1: =+INDEX(Tabla2[Precio Jornal],MATCH(H$25,Tabla2[Mes],0)) -> 21002.6 | I1: =+INDEX(Tabla2[Precio Jornal],MATCH(I$25,Tabla2[Mes],0)) -> 21357.9 | J1: =+INDEX(Tabla2[Precio Jornal],MATCH(J$25,Tabla2[Mes],0)) -> 21717 | ... N1: =+INDEX(Tabla2[Precio Jornal],MATCH(N$25,Tabla2[Mes],0)) -> 23218
A2: Días Laborales | C2: 23.5 | D2: 20.5 | E2: 24 | F2: 24 | G2: 23 | H2: 24.5 | I2: 22.5 | J2: 23 | K2: 24 | L2: 20.5 | M2: 23 | N2: 22
A3: Jornales Disponibles EE | B3: =23 -> 23 | C3: =+$B3*C2 -> 540.5 | D3: =+$B3*D2 -> 471.5 | E3: =+$B3*E2 -> 552 | F3: =+$B3*F2 -> 552 | G3: =+$B3*G2 -> 529 | H3: =+$B3*H2 -> 563.5 | I3: =+$B3*I2 -> 517.5 | J3: =+$B3*J2 -> 529 | ... N3: =+$B3*N2 -> 506
A4: Jornales Cosecha | B4: =+SUMIF(TablaGeneral[Finca],"El Espejo I",TablaGeneral[Resumen Jornales totales de Cosecha])+SUMIF(TablaGeneral[Finca],"El Espejo II",TablaGeneral[Resumen Jornales totales de Cosecha])+SUMIF(TablaGeneral[Finca],"El Espejo III",TablaGeneral[Resumen Jornales totales de Cosecha]) -> 936.11198 | K4: =+B4*0.2 -> 187.2224 | L4: =+B4*0.4 -> 374.44479 | M4: =+B4*0.4 -> 374.44479
A5: Jornales Secado | B5: =+SUMIFS(TablaGeneral[Resumen Jornales totales de Secado],TablaGeneral[Finca],"Camino truncado")*0.75 -> 850.03374 | C5: =+$B5*C24 -> 116.97328 | D5: =+$B5*D24 -> 100.70988 | E5: =+$B5*E24 -> 0 | F5: =+$B5*F24 -> 0 | G5: =+$B5*G24 -> 8.1317003 | H5: =+$B5*H24 -> 0 | I5: =+$B5*I24 -> 0 | J5: =+$B5*J24 -> 2.7105668 | ... N5: =+$B5*N24 -> 127.81555
A6: Jornales a contratar | B6: =SUM(C6:N6) -> 19936.788 | C6: =+(C127+C4+C5)-C3 -> 268.40932 | D6: =+D127+D4+D5-D3 -> 1968.5862 | E6: =+E127+E4+E5-E3 -> 1914.8032 | F6: =+F127+F4+F5-F3 -> 2303.1977 | G6: =+G127+G4+G5-G3 -> 1662.911 | H6: =+H127+H4+H5-H3 -> 1862.7863 | I6: =+I127+I4+I5-I3 -> 2963.5331 | J6: =+J127+J4+J5-J3 -> 3129.1805 | K6: =+K127+K4+K5-K3 -> 405.26267 | ... N6: =+N127+N4+N5-N3 -> 615.97233
A7: Contratados EE $ | B7: =SUM(C7:N7) -> 4.2123719e+08 | C7: =+C6*C1 -> 5185453.4 | D7: =+D6*D1 -> 38674844 | E7: =+E6*E1 -> 38251258 | F7: =+F6*F1 -> 46784624 | G7: =+G6*G1 -> 34347259 | H7: =+H6*H1 -> 39123356 | I7: =+I6*I1 -> 63294844 | J7: =+J6*J1 -> 67956414 | ... N7: =+N6*N1 -> 14301646 | P7: USD/Has
A8: Contratados EE USD | B8: =SUM(C8:N8) -> 354272.23 | C8: =+C7/INDEX(Tabla2[TC],MATCH(C25,Tabla2[Mes],0)) -> 4601.1121 | D8: =+D7/INDEX(Tabla2[TC],MATCH(D25,Tabla2[Mes],0)) -> 33976.863 | E8: =+E7/INDEX(Tabla2[TC],MATCH(E25,Tabla2[Mes],0)) -> 33272.012 | F8: =+F7/INDEX(Tabla2[TC],MATCH(F25,Tabla2[Mes],0)) -> 40291.655 | G8: =+G7/INDEX(Tabla2[TC],MATCH(G25,Tabla2[Mes],0)) -> 29287.525 | H8: =+H7/INDEX(Tabla2[TC],MATCH(H25,Tabla2[Mes],0)) -> 33029.753 | I8: =+I7/INDEX(Tabla2[TC],MATCH(I25,Tabla2[Mes],0)) -> 52907.37 | J8: =+J7/INDEX(Tabla2[TC],MATCH(J25,Tabla2[Mes],0)) -> 56241.503 | ... N8: =+N7/INDEX(Tabla2[TC],MATCH(N25,Tabla2[Mes],0)) -> 11374.36 | P8: =+B8/(SUMIFS(TablaGeneral[Has],TablaGeneral[Finca],"El Espejo I")+SUMIFS(TablaGeneral[Has],TablaGeneral[Finca],"El Espejo II")+SUMIFS(TablaGeneral[Has],TablaGeneral[Finca],"El Espejo III")) -> 1422.4944
A9: Contratados EE I y II $ | B9: =SUM(C9:N9) -> 2.9149613e+08 | C9: =+C7*0.692 -> 3588333.7 | D9: =+D7*0.692 -> 26762992 | E9: =+E7*0.692 -> 26469870 | F9: =+F7*0.692 -> 32374960 | G9: =+G7*0.692 -> 23768304 | H9: =+H7*0.692 -> 27073363 | I9: =+I7*0.692 -> 43800032 | J9: =+J7*0.692 -> 47025838 | ... N9: =+N7*0.692 -> 9896738.7 | P9: USD/Has EE I y II
A10: Contratados EE I y II USD | B10: =SUM(C10:N10) -> 245156.38 | C10: =+C9/INDEX(Tabla2[TC],MATCH(C25,Tabla2[Mes],0)) -> 3183.9696 | D10: =+D9/INDEX(Tabla2[TC],MATCH(D25,Tabla2[Mes],0)) -> 23511.989 | E10: =+E9/INDEX(Tabla2[TC],MATCH(E25,Tabla2[Mes],0)) -> 23024.232 | F10: =+F9/INDEX(Tabla2[TC],MATCH(F25,Tabla2[Mes],0)) -> 27881.825 | G10: =+G9/INDEX(Tabla2[TC],MATCH(G25,Tabla2[Mes],0)) -> 20266.968 | H10: =+H9/INDEX(Tabla2[TC],MATCH(H25,Tabla2[Mes],0)) -> 22856.589 | I10: =+I9/INDEX(Tabla2[TC],MATCH(I25,Tabla2[Mes],0)) -> 36611.9 | J10: =+J9/INDEX(Tabla2[TC],MATCH(J25,Tabla2[Mes],0)) -> 38919.12 | ... N10: =+N9/INDEX(Tabla2[TC],MATCH(N25,Tabla2[Mes],0)) -> 7871.0573 | P10: =+B8/(SUMIFS(TablaGeneral[Has],TablaGeneral[Finca],"El Espejo I")+SUMIFS(TablaGeneral[Has],TablaGeneral[Finca],"El Espejo II")) -> 2361.8148
A11: Contratados EE III $ | B11: =SUM(C11:N11) -> 1.2249577e+08 | C11: =+C7*0.2908 -> 1507929.8 | D11: =+D7*0.2908 -> 11246645 | E11: =+E7*0.2908 -> 11123466 | F11: =+F7*0.2908 -> 13604969 | G11: =+G7*0.2908 -> 9988183 | H11: =+H7*0.2908 -> 11377072 | I11: =+I7*0.2908 -> 18406141 | J11: =+J7*0.2908 -> 19761725 | ... N11: =+N7*0.2908 -> 4158918.5 | P11: USD/Has EE III
A12: Contratados EE III USD | B12: =SUM(C12:N12) -> 103022.36 | C12: =+C11/INDEX(Tabla2[TC],MATCH(C25,Tabla2[Mes],0)) -> 1338.0034 | D12: =+D11/INDEX(Tabla2[TC],MATCH(D25,Tabla2[Mes],0)) -> 9880.4718 | E12: =+E11/INDEX(Tabla2[TC],MATCH(E25,Tabla2[Mes],0)) -> 9675.501 | F12: =+F11/INDEX(Tabla2[TC],MATCH(F25,Tabla2[Mes],0)) -> 11716.813 | G12: =+G11/INDEX(Tabla2[TC],MATCH(G25,Tabla2[Mes],0)) -> 8516.8124 | H12: =+H11/INDEX(Tabla2[TC],MATCH(H25,Tabla2[Mes],0)) -> 9605.052 | I12: =+I11/INDEX(Tabla2[TC],MATCH(I25,Tabla2[Mes],0)) -> 15385.463 | J12: =+J11/INDEX(Tabla2[TC],MATCH(J25,Tabla2[Mes],0)) -> 16355.029 | ... N12: =+N11/INDEX(Tabla2[TC],MATCH(N25,Tabla2[Mes],0)) -> 3307.664 | P12: =+B12/63.69 -> 1617.5595
A13: Combustible Litros Gen | B13: =SUM(C13:N13) -> 12070.88 | C13: =+(SUM(C26:C28,C37:C39,C48:C50,C59:C61,C70:C72,C118,C81:C83,C92:C94)*10) -> 0 | D13: =+(SUM(D26:D28,D37:D39,D48:D50,D59:D61,D70:D72,D118,D81:D83,D92:D94)*19.5) -> 1694.4646 | E13: =+(SUM(E26:E28,E37:E39,E48:E50,E59:E61,E70:E72,E118,E81:E83,E92:E94)*19.5) -> 1694.4646 | F13: =+(SUM(F26:F28,F37:F39,F48:F50,F59:F61,F70:F72,F118,F81:F83,F92:F94)*19.5) -> 2838.1614 | G13: =+(SUM(G26:G28,G37:G39,G48:G50,G59:G61,G70:G72,G118,G81:G83,G92:G94)*19.5) -> 1191.4786 | H13: =+(SUM(H26:H28,H37:H39,H48:H50,H59:H61,H70:H72,H118,H81:H83,H92:H94)*19.5) -> 1523.5248 | I13: =+(SUM(I26:I28,I37:I39,I48:I50,I59:I61,I70:I72,I118,I81:I83,I92:I94)*19.5) -> 1099.9087 | J13: =+(SUM(J26:J28,J37:J39,J48:J50,J59:J61,J70:J72,J118,J81:J83,J92:J94)*19.5) -> 676.2925 | K13: =+(SUM(K26:K28,K37:K39,K48:K50,K59:K61,K70:K72,K118,K81:K83,K92:K94)*19.5) -> 0 | ... N13: =+(SUM(N26:N28,N37:N39,N48:N50,N59:N61,N70:N72,N118,N81:N83,N92:N94)*19.5) -> 0
A14: Combustible Litros Sec | B14: =SUM(C14:N14) -> 8565.1717 | C14: =+SUMIFS(TablaGeneral[Resumen Jornales totales de Secado],TablaGeneral[Ref Fincas],"El Espejo")*10*C24*0.75 -> 1178.7981 | D14: =+SUMIFS(TablaGeneral[Resumen Jornales totales de Secado],TablaGeneral[Ref Fincas],"El Espejo")*10*D24*0.75 -> 1014.9037 | E14: =+SUMIFS(TablaGeneral[Resumen Jornales totales de Secado],TablaGeneral[Ref Fincas],"El Espejo")*10*E24*0.75 -> 0 | F14: =+SUMIFS(TablaGeneral[Resumen Jornales totales de Secado],TablaGeneral[Ref Fincas],"El Espejo")*10*F24*0.75 -> 0 | G14: =+SUMIFS(TablaGeneral[Resumen Jornales totales de Secado],TablaGeneral[Ref Fincas],"El Espejo")*10*G24*0.75 -> 81.947201 | H14: =+SUMIFS(TablaGeneral[Resumen Jornales totales de Secado],TablaGeneral[Ref Fincas],"El Espejo")*10*H24*0.75 -> 0 | I14: =+SUMIFS(TablaGeneral[Resumen Jornales totales de Secado],TablaGeneral[Ref Fincas],"El Espejo")*10*I24*0.75 -> 0 | J14: =+SUMIFS(TablaGeneral[Resumen Jornales totales de Secado],TablaGeneral[Ref Fincas],"El Espejo")*10*J24*0.75 -> 27.315734 | ... N14: =+SUMIFS(TablaGeneral[Resumen Jornales totales de Secado],TablaGeneral[Ref Fincas],"El Espejo")*10*N24*0.75 -> 1288.0611
A15: Combustible Litros Cos | B15: =SUM(C15:N15) -> 9361.1198 | K15: =+(SUMIFS(TablaGeneral[Resumen Jornales totales de Cosecha],TablaGeneral[Ref Fincas],"El Espejo")*0.2*10) -> 1872.224 | L15: =+(SUMIFS(TablaGeneral[Resumen Jornales totales de Cosecha],TablaGeneral[Ref Fincas],"El Espejo")*0.4*10) -> 3744.4479 | M15: =+(SUMIFS(TablaGeneral[Resumen Jornales totales de Cosecha],TablaGeneral[Ref Fincas],"El Espejo")*0.4*10) -> 3744.4479
A16: Combustible Litros Tot | B16: =SUM(C16:N16) -> 29997.172 | C16: =SUM(C13:C15) -> 1178.7981 | D16: =SUM(D13:D15) -> 2709.3684 | E16: =SUM(E13:E15) -> 1694.4646 | F16: =SUM(F13:F15) -> 2838.1614 | G16: =SUM(G13:G15) -> 1273.4258 | H16: =SUM(H13:H15) -> 1523.5248 | I16: =SUM(I13:I15) -> 1099.9087 | J16: =SUM(J13:J15) -> 703.60823 | ... N16: =SUM(N13:N15) -> 1288.0611
A17: Lubricantes Litros Totales | B17: =SUM(C17:N17) -> 649.93872 | C17: =+(C16/100)+(C16/150)+(C16/200) -> 25.540626 | D17: =+(D16/100)+(D16/150)+(D16/200) -> 58.702981 | E17: =+(E16/100)+(E16/150)+(E16/200) -> 36.7134 | F17: =+(F16/100)+(F16/150)+(F16/200) -> 61.493497 | G17: =+(G16/100)+(G16/150)+(G16/200) -> 27.590892 | H17: =+(H16/100)+(H16/150)+(H16/200) -> 33.009704 | I17: =+(I16/100)+(I16/150)+(I16/200) -> 23.831354 | J17: =+(J16/100)+(J16/150)+(J16/200) -> 15.244845 | ... N17: =+(N16/100)+(N16/150)+(N16/200) -> 27.90799
A18: Combustible USD | B18: =SUM(C18:N18) -> 37028277 | C18: =+(INDEX(Tabla2[Combustible],MATCH(C25,Tabla2[Mes],0))*C16) -> 1361718.1 | D18: =+(INDEX(Tabla2[Combustible],MATCH(D25,Tabla2[Mes],0))*D16) -> 3161092.5 | E18: =+(INDEX(Tabla2[Combustible],MATCH(E25,Tabla2[Mes],0))*E16) -> 1996747 | F18: =+(INDEX(Tabla2[Combustible],MATCH(F25,Tabla2[Mes],0))*F16) -> 3377917.1 | G18: =+(INDEX(Tabla2[Combustible],MATCH(G25,Tabla2[Mes],0))*G16) -> 1530759.4 | H18: =+(INDEX(Tabla2[Combustible],MATCH(H25,Tabla2[Mes],0))*H16) -> 1849712.3 | I18: =+(INDEX(Tabla2[Combustible],MATCH(I25,Tabla2[Mes],0))*I16) -> 1348753.7 | J18: =+(INDEX(Tabla2[Combustible],MATCH(J25,Tabla2[Mes],0))*J16) -> 871421.58 | ... N18: =+(INDEX(Tabla2[Combustible],MATCH(N25,Tabla2[Mes],0))*N16) -> 1660043
A19: Lubricantes USD | B19: =SUM(C19:N19) -> 4422320.2 | C19: =+(INDEX(Tabla2[Lubricantes],MATCH(C25,Tabla2[Mes],0))*C17) -> 162631.21 | D19: =+(INDEX(Tabla2[Lubricantes],MATCH(D25,Tabla2[Mes],0))*D17) -> 377532.11 | E19: =+(INDEX(Tabla2[Lubricantes],MATCH(E25,Tabla2[Mes],0))*E17) -> 238473.28 | F19: =+(INDEX(Tabla2[Lubricantes],MATCH(F25,Tabla2[Mes],0))*F17) -> 403427.66 | G19: =+(INDEX(Tabla2[Lubricantes],MATCH(G25,Tabla2[Mes],0))*G17) -> 182819.96 | H19: =+(INDEX(Tabla2[Lubricantes],MATCH(H25,Tabla2[Mes],0))*H17) -> 220912.79 | I19: =+(INDEX(Tabla2[Lubricantes],MATCH(I25,Tabla2[Mes],0))*I17) -> 161082.86 | J19: =+(INDEX(Tabla2[Lubricantes],MATCH(J25,Tabla2[Mes],0))*J17) -> 104074.66 | ... N19: =+(INDEX(Tabla2[Lubricantes],MATCH(N25,Tabla2[Mes],0))*N17) -> 198260.42
A20: Combustible Pesos | B20: =SUM(C20:N20) -> 18959668 | C20: =+(C13*INDEX(Tabla2[Combustible],MATCH(C25,Tabla2[Mes],0)))+(C17*INDEX(Tabla2[Lubricantes],MATCH(C25,Tabla2[Mes],0))) -> 162631.21 | D20: =+(D13*INDEX(Tabla2[Combustible],MATCH(D25,Tabla2[Mes],0)))+(D17*INDEX(Tabla2[Lubricantes],MATCH(D25,Tabla2[Mes],0))) -> 2354509.3 | E20: =+(E13*INDEX(Tabla2[Combustible],MATCH(E25,Tabla2[Mes],0)))+(E17*INDEX(Tabla2[Lubricantes],MATCH(E25,Tabla2[Mes],0))) -> 2235220.3 | F20: =+(F13*INDEX(Tabla2[Combustible],MATCH(F25,Tabla2[Mes],0)))+(F17*INDEX(Tabla2[Lubricantes],MATCH(F25,Tabla2[Mes],0))) -> 3781344.8 | G20: =+(G13*INDEX(Tabla2[Combustible],MATCH(G25,Tabla2[Mes],0)))+(G17*INDEX(Tabla2[Lubricantes],MATCH(G25,Tabla2[Mes],0))) -> 1615072.2 | H20: =+(H13*INDEX(Tabla2[Combustible],MATCH(H25,Tabla2[Mes],0)))+(H17*INDEX(Tabla2[Lubricantes],MATCH(H25,Tabla2[Mes],0))) -> 2070625.1 | I20: =+(I13*INDEX(Tabla2[Combustible],MATCH(I25,Tabla2[Mes],0)))+(I17*INDEX(Tabla2[Lubricantes],MATCH(I25,Tabla2[Mes],0))) -> 1509836.5 | J20: =+(J13*INDEX(Tabla2[Combustible],MATCH(J25,Tabla2[Mes],0)))+(J17*INDEX(Tabla2[Lubricantes],MATCH(J25,Tabla2[Mes],0))) -> 941665.59 | ... N20: =+(N13*INDEX(Tabla2[Combustible],MATCH(N25,Tabla2[Mes],0)))+(N17*INDEX(Tabla2[Lubricantes],MATCH(N25,Tabla2[Mes],0))) -> 198260.42
A21: Combustibles USD | B21: =SUM(C21:N21) -> 16044.806 | C21: =+C20/INDEX(Tabla2[TC],MATCH(C25,Tabla2[Mes],0)) -> 144.30454 | D21: =+D20/INDEX(Tabla2[TC],MATCH(D25,Tabla2[Mes],0)) -> 2068.4981 | E21: =+E20/INDEX(Tabla2[TC],MATCH(E25,Tabla2[Mes],0)) -> 1944.257 | F21: =+F20/INDEX(Tabla2[TC],MATCH(F25,Tabla2[Mes],0)) -> 3256.5537 | G21: =+G20/INDEX(Tabla2[TC],MATCH(G25,Tabla2[Mes],0)) -> 1377.1541 | H21: =+H20/INDEX(Tabla2[TC],MATCH(H25,Tabla2[Mes],0)) -> 1748.1178 | I21: =+I20/INDEX(Tabla2[TC],MATCH(I25,Tabla2[Mes],0)) -> 1262.0535 | J21: =+J20/INDEX(Tabla2[TC],MATCH(J25,Tabla2[Mes],0)) -> 779.33319 | ... N21: =+N20/INDEX(Tabla2[TC],MATCH(N25,Tabla2[Mes],0)) -> 157.68014
A22: Combustibles USD EE I y II | B22: =SUM(C22:N22) -> 11103.006 | C22: =+C21*0.692 -> 99.85874 | D22: =+D21*0.692 -> 1431.4007 | E22: =+E21*0.692 -> 1345.4258 | F22: =+F21*0.692 -> 2253.5351 | G22: =+G21*0.692 -> 952.99064 | H22: =+H21*0.692 -> 1209.6975 | I22: =+I21*0.692 -> 873.34104 | J22: =+J21*0.692 -> 539.29857 | ... N22: =+N21*0.692 -> 109.11466 | P22: =SUM(C22:N22)/(SUMIFS(TablaGeneral[Has],TablaGeneral[Finca],"El Espejo I")+SUMIFS(TablaGeneral[Has],TablaGeneral[Finca],"El Espejo II")) -> 74.020038
A23: Combustibles USD EE III | B23: =SUM(C23:N23) -> 4665.8296 | C23: =+C21*0.2908 -> 41.963759 | D23: =+D21*0.2908 -> 601.51924 | E23: =+E21*0.2908 -> 565.38992 | F23: =+F21*0.2908 -> 947.00581 | G23: =+G21*0.2908 -> 400.47641 | H23: =+H21*0.2908 -> 508.35265 | I23: =+I21*0.2908 -> 367.00517 | J23: =+J21*0.2908 -> 226.63009 | ... N23: =+N21*0.2908 -> 45.853385 | P23: =SUM(C23:N23)/63.69 -> 73.258433
A24: El Espejo | B24: Jorn | C24: 0.13761016 | D24: 0.11847751 | E24: 0 | F24: 0 | G24: 0.0095663265 | H24: 0 | I24: 0 | J24: 0.0031887755 | K24: 0.07903824 | L24: 0.25998661 | M24: 0.24164543 | N24: 0.15036527
A25: Fiesta 2020 | B25: 1963.1785 | C25: Mayo | D25: Junio | E25: Julio | F25: Agosto | G25: Septiembre | H25: Octubre | I25: Noviembre | J25: Diciembre | K25: Enero | L25: Febrero | M25: Marzo | N25: Abril
A26: Tractorista Subsolado | B26: 0.56410642 | F26: =+B26 -> 0.56410642
A27: Tractor Atomizadora | B27: 22.37777 | G27: =+$B27/6 -> 3.7296284 | H27: =+$B27/6 -> 3.7296284 | I27: =+$B27/6 -> 3.7296284 | J27: =+$B27/6 -> 3.7296284 | L27: =+$B27/6 -> 3.7296284 | M27: =+$B27/6 -> 3.7296284
A28: Tractor Herbicida | B28: 6.2466616 | F28: =+B28 -> 6.2466616
A29: Poda | B29: 393.71667 | D29: =+$B29/3 -> 131.23889 | E29: =+$B29/3 -> 131.23889 | F29: =+$B29/3 -> 131.23889
A30: Atada | B30: 393.71667 | D30: =+$B30/3 -> 131.23889 | E30: =+$B30/3 -> 131.23889 | F30: =+$B30/3 -> 131.23889
A31: Acomodo de brotes | B31: 168.92781 | G31: =+$B31/2 -> 84.463905 | H31: =+$B31/2 -> 84.463905
A32: Desbrote de troncos | B32: 363.43077 | G32: =+$B32/5/2 -> 36.343077 | H32: =+$B32/5/2 -> 36.343077 | I32: =+$B32/5 -> 72.686154 | J32: =+$B32/5 -> 72.686154 | L32: =+$B32/5 -> 72.686154 | M32: =+$B32/5 -> 72.686154
A33: Raleo de Racimos | B33: 472.46 | I33: =+B33/2 -> 236.23 | J33: =+B33/2 -> 236.23
A34: Desniete Deshoje | B34: 47.246 | J34: =+B34 -> 47.246
A35: Desbrote con criterio de Poda | B35: 94.492 | F35: =+B35/2 -> 47.246 | G35: =+B35/2 -> 47.246
A36: Fiesta 2021 | B36: 2447.449 | C36: =+SUM(C26:C35) -> 0 | D36: =+SUM(D26:D35) -> 262.47778 | E36: =+SUM(E26:E35) -> 262.47778 | F36: =+SUM(F26:F35) -> 316.53455 | G36: =+SUM(G26:G35) -> 171.78261 | H36: =+SUM(H26:H35) -> 124.53661 | I36: =+SUM(I26:I35) -> 312.64578 | J36: =+SUM(J26:J35) -> 359.89178 | ... N36: =+SUM(N26:N35) -> 0
A37: Tractorista Subsolado | B37: 0.90701597 | G37: =+B37 -> 0.90701597
A38: Tractor Atomizadora | B38: 35.662978 | G38: =+$B38/6 -> 5.9438296 | H38: =+$B38/6 -> 5.9438296 | I38: =+$B38/6 -> 5.9438296 | J38: =+$B38/6 -> 5.9438296 | L38: =+$B38/6 -> 5.9438296 | M38: =+$B38/6 -> 5.9438296
A39: Tractor Herbicida | B39: 9.954922 | F39: =+B39 -> 9.954922
A40: Poda | B40: 461.89333 | D40: =+$B40/3 -> 153.96444 | E40: =+$B40/3 -> 153.96444 | F40: =+$B40/3 -> 153.96444
A41: Atada | B41: 307.92889 | D41: =+$B41/3 -> 102.64296 | E41: =+$B41/3 -> 102.64296 | F41: =+$B41/3 -> 102.64296
A42: Acomodo de brotes | B42: 182.456 | G42: =+$B42/2 -> 91.228 | H42: =+$B42/2 -> 91.228
A43: Desbrote de troncos | B43: 701.75385 | H43: =+$B43/5 -> 140.35077 | I43: =+$B43/5 -> 140.35077 | J43: =+$B43/5 -> 140.35077 | L43: =+$B43/5 -> 140.35077 | M43: =+$B43/5 -> 140.35077
A44: Raleo de Racimos | B44: 552.464 | I44: =+$B44/2 -> 276.232 | J44: =+$B44/2 -> 276.232
A45: Desniete Deshoje | B45: 11.972 | J45: =+B45 -> 11.972
A46: Desbrote con criterio de Poda | B46: 182.456 | F46: =+$B46/2 -> 91.228 | G46: =+$B46/2 -> 91.228
A47: Flame 2019 | B47: 4253.1351 | C47: =+SUM(C37:C46) -> 0 | D47: =+SUM(D37:D46) -> 256.60741 | E47: =+SUM(E37:E46) -> 256.60741 | F47: =+SUM(F37:F46) -> 357.79033 | G47: =+SUM(G37:G46) -> 189.30685 | H47: =+SUM(H37:H46) -> 237.5226 | I47: =+SUM(I37:I46) -> 422.5266 | J47: =+SUM(J37:J46) -> 434.4986 | ... N47: =+SUM(N37:N46) -> 0
A48: Tractorista Subsolado | B48: 1.3520358 | G48: =+B48 -> 1.3520358
A49: Tractor Atomizadora | B49: 53.634465 | G49: =+$B49/6 -> 8.9390776 | H49: =+$B49/6 -> 8.9390776 | I49: =+$B49/6 -> 8.9390776 | J49: =+$B49/6 -> 8.9390776 | L49: =+$B49/6 -> 8.9390776 | M49: =+$B49/6 -> 8.9390776
A50: Tractor Herbicida | B50: 14.971838 | F50: =+B50 -> 14.971838
A51: Poda | B51: 943.65 | D51: =+$B51/3 -> 314.55 | E51: =+$B51/3 -> 314.55 | F51: =+$B51/3 -> 314.55
A52: Atada | B52: 943.65 | D52: =+$B52/3 -> 314.55 | E52: =+$B52/3 -> 314.55 | F52: =+$B52/3 -> 314.55
A53: Acomodo de brotes | B53: 322.892 | G53: =+$B53/2 -> 161.446 | H53: =+$B53/2/2 -> 80.723 | I53: =+$B53/2/2 -> 80.723
A54: Desbrote de troncos | B54: 500.89077 | H54: =+$B54/5 -> 100.17815 | I54: =+$B54/5 -> 100.17815 | J54: =+$B54/5 -> 100.17815 | L54: =+$B54/5 -> 100.17815 | M54: =+$B54/5 -> 100.17815
A55: Raleo de Racimos | B55: 1132.38 | I55: =+$B55/2 -> 566.19 | J55: =+$B55/2 -> 566.19
A56: Desniete Deshoje | B56: 113.238 | J56: =+B56 -> 113.238
A57: Desbrote con criterio de Poda | B57: 226.476 | G57: =+$B57/2 -> 113.238 | H57: =+$B57/2 -> 113.238
A58: Flame 2020 | B58: 1169.0907 | C58: =+SUM(C48:C57) -> 0 | D58: =+SUM(D48:D57) -> 629.1 | E58: =+SUM(E48:E57) -> 629.1 | F58: =+SUM(F48:F57) -> 644.07184 | G58: =+SUM(G48:G57) -> 284.97511 | H58: =+SUM(H48:H57) -> 303.07823 | I58: =+SUM(I48:I57) -> 756.03023 | J58: =+SUM(J48:J57) -> 788.54523 | ... N58: =+SUM(N48:N57) -> 0
A59: Tractorista Subsolado | B59: 0.56267365 | G59: =+B59 -> 0.56267365
A60: Tractor Atomizadora | B60: 22.320933 | G60: =+$B60/6 -> 3.7201555 | H60: =+$B60/6 -> 3.7201555 | I60: =+$B60/6 -> 3.7201555 | J60: =+$B60/6 -> 3.7201555 | L60: =+$B60/6 -> 3.7201555 | M60: =+$B60/6 -> 3.7201555
A61: Tractor Herbicida | B61: 6.2307957 | F61: =+B61 -> 6.2307957
A62: Poda | B62: 88.412522 | D62: =+$B62/3 -> 29.470841 | E62: =+$B62/3 -> 29.470841 | F62: =+$B62/3 -> 29.470841
A63: Atada | B63: 58.941682 | D63: =+$B63/3 -> 19.647227 | E63: =+$B63/3 -> 19.647227 | F63: =+$B63/3 -> 19.647227
A64: Acomodo de brotes | B64: 175.18959 | G64: =+$B64/2 -> 87.594796 | H64: =+$B64/2/2 -> 43.797398 | I64: =+$B64/2/2 -> 43.797398
A65: Desbrote de troncos | B65: 581.80247 | H65: =+$B65/5 -> 116.36049 | I65: =+$B65/5 -> 116.36049 | J65: =+$B65/5 -> 116.36049 | L65: =+$B65/5 -> 116.36049 | M65: =+$B65/5 -> 116.36049
A66: Raleo de Racimos | B66: 0 | I66: =+$B66/2 -> 0 | J66: =+$B66/2 -> 0
A67: Desniete Deshoje | B67: 0
A68: Desbrote con criterio de Poda | B68: 235.63 | G68: =+$B68/2 -> 117.815 | H68: =+$B68/2 -> 117.815
A69: Flame 2021 | B69: 1272.9051 | C69: =+SUM(C59:C68) -> 0 | D69: =+SUM(D59:D68) -> 49.118068 | E69: =+SUM(E59:E68) -> 49.118068 | F69: =+SUM(F59:F68) -> 55.348864 | G69: =+SUM(G59:G68) -> 209.69262 | H69: =+SUM(H59:H68) -> 281.69305 | I69: =+SUM(I59:I68) -> 163.87805 | J69: =+SUM(J59:J68) -> 120.08065 | ... N69: =+SUM(N59:N68) -> 0
A70: Tractorista Subsolado | B70: 0.51210789 | G70: =+B70 -> 0.51210789
A71: Tractor Atomizadora | B71: 20.13558 | G71: =+$B71/6 -> 3.3559299 | H71: =+$B71/6 -> 3.3559299 | I71: =+$B71/6 -> 3.3559299 | J71: =+$B71/6 -> 3.3559299 | L71: =+$B71/6 -> 3.3559299 | M71: =+$B71/6 -> 3.3559299
A72: Tractor Herbicida | B72: 5.6206222 | F72: =+B72 -> 5.6206222
A73: Poda | B73: 228.83167 | D73: =+$B73/3 -> 76.277222 | E73: =+$B73/3 -> 76.277222 | F73: =+$B73/3 -> 76.277222
A74: Atada | B74: 152.55444 | D74: =+$B74/3 -> 50.851481 | E74: =+$B74/3 -> 50.851481 | F74: =+$B74/3 -> 50.851481
A75: Acomodo de brotes | B75: 103.016 | G75: =+$B75/2 -> 51.508 | H75: =+$B75/2/2 -> 25.754 | I75: =+$B75/2/2 -> 25.754
A76: Desbrote de troncos | B76: 396.21538 | H76: =+$B76/5 -> 79.243077 | I76: =+$B76/5 -> 79.243077 | J76: =+$B76/5 -> 79.243077 | L76: =+$B76/5 -> 79.243077 | M76: =+$B76/5 -> 79.243077
A77: Raleo de Racimos | B77: 263.00333 | I77: =+$B77/2 -> 131.50167 | J77: =+$B77/2 -> 131.50167
A78: Desniete Deshoje | B78: 0
A79: Desbrote con criterio de Poda | B79: 103.016 | G79: =+$B79/2 -> 51.508 | H79: =+$B79/2 -> 51.508
A80: Selma 2019 | B80: 4047.2326 | C80: =+SUM(C70:C79) -> 0 | D80: =+SUM(D70:D79) -> 127.1287 | E80: =+SUM(E70:E79) -> 127.1287 | F80: =+SUM(F70:F79) -> 132.74933 | G80: =+SUM(G70:G79) -> 106.88404 | H80: =+SUM(H70:H79) -> 159.86101 | I80: =+SUM(I70:I79) -> 239.85467 | J80: =+SUM(J70:J79) -> 214.10067 | ... N80: =+SUM(N70:N79) -> 0
A81: Tractorista Subsolado | B81: 1.151185 | G81: =+B81 -> 1.151185
A82: Tractor Atomizadora | B82: 45.666831 | G82: =+$B82/6 -> 7.6111385 | H82: =+$B82/6 -> 7.6111385 | I82: =+$B82/6 -> 7.6111385 | J82: =+$B82/6 -> 7.6111385 | L82: =+$B82/6 -> 7.6111385 | M82: =+$B82/6 -> 7.6111385
A83: Tractor Herbicida | B83: 12.747706 | F83: =+B83 -> 12.747706
A84: Poda | B84: 803.46667 | D84: =+$B84/3 -> 267.82222 | E84: =+$B84/3 -> 267.82222 | F84: =+$B84/3 -> 267.82222
A85: Atada | B85: 803.46667 | D85: =+$B85/3 -> 267.82222 | E85: =+$B85/3 -> 267.82222 | F85: =+$B85/3 -> 267.82222
A86: Acomodo de brotes | B86: 385.664 | G86: =+$B86/2 -> 192.832 | H86: =+$B86/2/2 -> 96.416 | I86: =+$B86/2/2 -> 96.416
A87: Desbrote de troncos | B87: 741.66154 | H87: =+$B87/5 -> 148.33231 | I87: =+$B87/5 -> 148.33231 | J87: =+$B87/5 -> 148.33231 | L87: =+$B87/5 -> 148.33231 | M87: =+$B87/5 -> 148.33231
A88: Raleo de Racimos | B88: 964.16 | I88: =+$B88/2 -> 482.08 | J88: =+$B88/2 -> 482.08
A89: Desniete Deshoje | B89: 96.416 | J89: =+B89 -> 96.416
A90: Desbrote con criterio de Poda | B90: 192.832 | G90: =+$B90/2 -> 96.416 | H90: =+$B90/2 -> 96.416
A91: Selma 2021 | B91: 419.06396 | C91: =+SUM(C81:C90) -> 0 | D91: =+SUM(D81:D90) -> 535.64444 | E91: =+SUM(E81:E90) -> 535.64444 | F91: =+SUM(F81:F90) -> 548.39215 | G91: =+SUM(G81:G90) -> 298.01032 | H91: =+SUM(H81:H90) -> 348.77545 | I91: =+SUM(I81:I90) -> 734.43945 | J91: =+SUM(J81:J90) -> 734.43945 | ... N91: =+SUM(N81:N90) -> 0
A92: Tractorista Subsolado | B92: 0.21087614 | G92: =+B92 -> 0.21087614
A93: Tractor Atomizadora | B93: 8.2914429 | G93: =+$B93/6 -> 1.3819072 | H93: =+$B93/6 -> 1.3819072 | I93: =+$B93/6 -> 1.3819072 | J93: =+$B93/6 -> 1.3819072 | L93: =+$B93/6 -> 1.3819072 | M93: =+$B93/6 -> 1.3819072
A94: Tractor Herbicida | B94: 2.3144637 | F94: =+B94 -> 2.3144637
A95: Poda | B95: 70.7 | D95: =+$B95/3 -> 23.566667 | E95: =+$B95/3 -> 23.566667 | F95: =+$B95/3 -> 23.566667
A96: Atada | B96: 47.133333 | D96: =+$B96/3 -> 15.711111 | E96: =+$B96/3 -> 15.711111 | F96: =+$B96/3 -> 15.711111
A97: Acomodo de brotes | B97: 42.42 | G97: =+$B97/2 -> 21.21 | H97: =+$B97/2/2 -> 10.605 | I97: =+$B97/2/2 -> 10.605
A98: Desbrote de troncos | B98: 163.15385 | H98: =+$B98/5 -> 32.630769 | I98: =+$B98/5 -> 32.630769 | J98: =+$B98/5 -> 32.630769 | L98: =+$B98/5 -> 32.630769 | M98: =+$B98/5 -> 32.630769
A99: Raleo de Racimos | B99: 42.42 | I99: =+$B99/2 -> 21.21 | J99: =+$B99/2 -> 21.21
A100: Desniete Deshoje | B100: 0
...

Sheet Resumen de Jornales
A1: Jornales Tractoristas y consumo de combustible | C1: Puente Alto
C2: Jornal | D2: Combustible | E2: Lubricantes | F2: u$s Comb | G2: u$s Lubr | H2: Pres 25-26 | I2: Real 24-25
A3: Específicos | B3: Tractorista Subsolado | C3: =+SUMIFS(TablaGeneral[Tractorista Subsolado],TablaGeneral[Finca],C1) -> 16 | D3: =+C3*10 -> 160 | E3: =+(D3/100)+(D3/150)+(D3/200) -> 3.4666667 | F3: =+AVERAGE(Tabla2[Combustible])*D3*1.08 -> 210967.35 | G3: =+AVERAGE(Tabla2[Lubricantes])*E3*1.08 -> 25196.019 | H3: =+SUM(F3:G9) -> 3020937.5 | I3: 3448.47
B4: Tractorista Triturado de sarmiento | C4: =+SUMIFS(TablaGeneral[Tractorista Triturado de sarmiento],TablaGeneral[Finca],C1) -> 7 | D4: =+C4*10 -> 70 | E4: =+(D4/100)+(D4/150)+(D4/200) -> 1.5166667 | F4: =+AVERAGE(Tabla2[Combustible])*D4*1.08 -> 92298.216 | G4: =+AVERAGE(Tabla2[Lubricantes])*E4*1.08 -> 11023.259
B5: Tractorista Cincelado | C5: =+SUMIFS(TablaGeneral[Tractorista Cincelado],TablaGeneral[Finca],C1) -> 3.000133 | D5: =+C5*10 -> 30.00133 | E5: =+(D5/100)+(D5/150)+(D5/200) -> 0.65002881 | F5: =+AVERAGE(Tabla2[Combustible])*D5*1.08 -> 39558.131 | G5: =+AVERAGE(Tabla2[Lubricantes])*E5*1.08 -> 4724.463
B6: Tractorista Rastra | C6: =+SUMIFS(TablaGeneral[Tractorista Rastra],TablaGeneral[Finca],C1) -> 63 | D6: =+C6*10 -> 630 | E6: =+(D6/100)+(D6/150)+(D6/200) -> 13.65 | F6: =+AVERAGE(Tabla2[Combustible])*D6*1.08 -> 830683.94 | G6: =+AVERAGE(Tabla2[Lubricantes])*E6*1.08 -> 99209.326
B7: Tractor Herbicida | C7: =+SUMIFS(TablaGeneral[Tractor Herbicida],TablaGeneral[Finca],C1) -> 7.5008311 | D7: =+C7*10 -> 75.008311 | E7: =+(D7/100)+(D7/150)+(D7/200) -> 1.6251801 | F7: =+AVERAGE(Tabla2[Combustible])*D7*1.08 -> 98901.904 | G7: =+AVERAGE(Tabla2[Lubricantes])*E7*1.08 -> 11811.943
B8: Tractor Atomizadora | C8: =+SUMIFS(TablaGeneral[Tractor Atomizadora],TablaGeneral[Finca],C1) -> 60.166667 | D8: =+C8*10 -> 601.66667 | E8: =+(D8/100)+(D8/150)+(D8/200) -> 13.036111 | F8: =+AVERAGE(Tabla2[Combustible])*D8*1.08 -> 793325.14 | G8: =+AVERAGE(Tabla2[Lubricantes])*E8*1.08 -> 94747.531
A9: Generales | B9: Tractorista Generales | C9: =+SUMIFS(TablaGeneral[Tractorista Generales],TablaGeneral[Finca],C1) -> 48.000009 | D9: =+C9*10 -> 480.00009 | E9: =+(D9/100)+(D9/150)+(D9/200) -> 10.400002 | F9: =+AVERAGE(Tabla2[Combustible])*D9*1.08 -> 632902.16 | G9: =+AVERAGE(Tabla2[Lubricantes])*E9*1.08 -> 75588.071
A10: Cosecha | B10: Tracto elevador | C10: =+SUMIFS(TablaGeneral[Tracto elevador],TablaGeneral[Finca],C1) -> 48.005319 | D10: =+C10*10 -> 480.05319 | E10: =+(D10/100)+(D10/150)+(D10/200) -> 10.401152 | F10: =+AVERAGE(Tabla2[Combustible])*D10*1.08 -> 632972.19 | G10: =+AVERAGE(Tabla2[Lubricantes])*E10*1.08 -> 75596.434 | H10: =+SUM(F10:G12) -> 1417137.2 | I10: 1123.6
B11: Tractor con uñas | C11: =+SUMIFS(TablaGeneral[Tractor con uñas],TablaGeneral[Finca],C1) -> 48.005319 | D11: =+C11*10 -> 480.05319 | E11: =+(D11/100)+(D11/150)+(D11/200) -> 10.401152 | F11: =+AVERAGE(Tabla2[Combustible])*D11*1.08 -> 632972.19 | G11: =+AVERAGE(Tabla2[Lubricantes])*E11*1.08 -> 75596.434
B12: Tractor con acoplado | C12: =+SUMIFS(TablaGeneral[Tractor con acoplado],TablaGeneral[Finca],C1) -> 0 | D12: =+C12*10 -> 0 | E12: =+(D12/100)+(D12/150)+(D12/200) -> 0 | F12: =+AVERAGE(Tabla2[Combustible])*D12*1.08 -> 0 | G12: =+AVERAGE(Tabla2[Lubricantes])*E12*1.08 -> 0
A13: Secado | B13: Tractor Volcado de bins | C13: =+SUMIFS(TablaGeneral[Tractor Volcado de bins],TablaGeneral[Finca],C1) -> 7.0004654 | D13: =+C13*10 -> 70.004654 | E13: =+(D13/100)+(D13/150)+(D13/200) -> 1.5167675 | F13: =+AVERAGE(Tabla2[Combustible])*D13*1.08 -> 92304.352 | G13: =+AVERAGE(Tabla2[Lubricantes])*E13*1.08 -> 11023.991 | H13: =+SUM(F13:G17) -> 299206.33 | I13: 195.43
B14: Tractor Cincelado de piedras | C14: =+SUMIFS(TablaGeneral[Tractor Cincelado de piedras],TablaGeneral[Finca],C1) -> 0.78000761 | D14: =+C14*10 -> 7.8000761 | E14: =+(D14/100)+(D14/150)+(D14/200) -> 0.16900165 | F14: =+AVERAGE(Tabla2[Combustible])*D14*1.08 -> 10284.759 | G14: =+AVERAGE(Tabla2[Lubricantes])*E14*1.08 -> 1228.3179
B15: Tractor Carga de pasa | C15: =+SUMIFS(TablaGeneral[Tractor Carga de pasa],TablaGeneral[Finca],C1) -> 0 | D15: =+C15*10 -> 0 | E15: =+(D15/100)+(D15/150)+(D15/200) -> 0 | F15: =+AVERAGE(Tabla2[Combustible])*D15*1.08 -> 0 | G15: =+AVERAGE(Tabla2[Lubricantes])*E15*1.08 -> 0
B16: Tractor Descarga y carga de bines con tracto elevador | C16: =+SUMIFS(TablaGeneral[Tractor Descarga y carga de bines con tracto elevador],TablaGeneral[Finca],C1) -> 6.0006649 | D16: =+C16*10 -> 60.006649 | E16: =+(D16/100)+(D16/150)+(D16/200) -> 1.3001441 | F16: =+AVERAGE(Tabla2[Combustible])*D16*1.08 -> 79121.523 | G16: =+AVERAGE(Tabla2[Lubricantes])*E16*1.08 -> 9449.5543
B17: Descarga y carga de bines con Autoelevador | C17: =+SUMIFS(TablaGeneral[Descarga y carga de bines con Autoelevador],TablaGeneral[Finca],C1) -> 6.4900043 | D17: =+C17*10 -> 64.900043 | E17: =+(D17/100)+(D17/150)+(D17/200) -> 1.4061676 | F17: =+AVERAGE(Tabla2[Combustible])*D17*1.08 -> 85573.688 | G17: =+AVERAGE(Tabla2[Lubricantes])*E17*1.08 -> 10220.142
C18: =SUM(C3:C17) -> 320.94942 | D18: =SUM(D3:D17) -> 3209.4942 | E18: =SUM(E3:E17) -> 69.539041 | F18: =SUM(F3:F17) -> 4231865.5 | G18: =SUM(G3:G17) -> 505415.49 | H18: =SUM(H3:H17) -> 4737281 | I18: =SUM(I3:I17) -> 4767.5
C19: =+C18/SUMIF(TablaGeneral[Finca],C1,TablaGeneral[Has]) -> 11.984668 | D19: =+D18/SUMIF(TablaGeneral[Finca],C1,TablaGeneral[Has]) -> 119.84668 | E19: =+E18/SUMIF(TablaGeneral[Finca],C1,TablaGeneral[Has]) -> 2.5966782 | F19: =+F18/SUMIF(TablaGeneral[Finca],C1,TablaGeneral[Has]) -> 158023.36 | G19: =+G18/SUMIF(TablaGeneral[Finca],C1,TablaGeneral[Has]) -> 18872.871 | H19: =+H18/SUMIF(TablaGeneral[Finca],C1,TablaGeneral[Has]) -> 176896.23 | I19: =+I18/SUMIF(TablaGeneral[Finca],C1,TablaGeneral[Has]) -> 178.02465 | K19: 90
B20: Gen | C20: =+SUM(C3:C9)/SUMIF(TablaGeneral[Finca],C1,TablaGeneral[Has]) -> 7.6425556 | E20: Generales | H20: =+H3/SUMIF(TablaGeneral[Finca],C1,TablaGeneral[Has]) -> 112805.73 | I20: =+I3/SUMIF(TablaGeneral[Finca],C1,TablaGeneral[Has]) -> 128.77035
B21: Cosecha | C21: =+SUM(C10:C12)/SUMIF(TablaGeneral[Finca],C1,TablaGeneral[Has]) -> 3.585162 | E21: Cosecha | H21: =+H10/SUMIF(TablaGeneral[Finca],C1,TablaGeneral[Has]) -> 52917.746 | I21: =+I10/SUMIF(TablaGeneral[Finca],C1,TablaGeneral[Has]) -> 41.956684
B22: Secado | C22: =+SUM(C13:C17)/SUMIF(TablaGeneral[Finca],C1,TablaGeneral[Has]) -> 0.75695079 | E22: Secado | H22: =+H13/SUMIF(TablaGeneral[Finca],C1,TablaGeneral[Has]) -> 11172.753 | I22: =+I13/SUMIF(TablaGeneral[Finca],C1,TablaGeneral[Has]) -> 7.2976102
A24: Jornales Tractoristas y consumo de combustible | C24: Camino Truncado
C25: Jornal | D25: Combustible | E25: Lubricantes | F25: u$s Comb | G25: u$s Lubr | H25: Pres 25-26 | I25: Real 24-25
A26: Específicos | B26: Tractorista Subsolado | C26: =+SUMIFS(TablaGeneral[Tractorista Subsolado],TablaGeneral[Finca],C24) -> 32.7 | D26: =+C26*10 -> 327 | E26: =+(D26/100)+(D26/150)+(D26/200) -> 7.085 | F26: =+AVERAGE(Tabla2[Combustible])*D26*1.08 -> 431164.52 | G26: =+AVERAGE(Tabla2[Lubricantes])*E26*1.08 -> 51494.364 | H26: =+SUM(F26:G32) -> 4823788.5 | I26: 3448.47
B27: Tractorista Triturado de sarmiento | C27: =+SUMIFS(TablaGeneral[Tractorista Triturado de sarmiento],TablaGeneral[Finca],C24) -> 21.999997 | D27: =+C27*10 -> 219.99997 | E27: =+(D27/100)+(D27/150)+(D27/200) -> 4.7666661 | F27: =+AVERAGE(Tabla2[Combustible])*D27*1.08 -> 290080.07 | G27: =+AVERAGE(Tabla2[Lubricantes])*E27*1.08 -> 34644.522
B28: Tractorista Cincelado | C28: =+SUMIFS(TablaGeneral[Tractorista Cincelado],TablaGeneral[Finca],C24) -> 17.050011 | D28: =+C28*10 -> 170.50011 | E28: =+(D28/100)+(D28/150)+(D28/200) -> 3.694169 | F28: =+AVERAGE(Tabla2[Combustible])*D28*1.08 -> 224812.22 | G28: =+AVERAGE(Tabla2[Lubricantes])*E28*1.08 -> 26849.525
B29: Tractorista Rastra | C29: =+SUMIFS(TablaGeneral[Tractorista Rastra],TablaGeneral[Finca],C24) -> 44.980096 | D29: =+C29*10 -> 449.80096 | E29: =+(D29/100)+(D29/150)+(D29/200) -> 9.7456875 | F29: =+AVERAGE(Tabla2[Combustible])*D29*1.08 -> 593083.23 | G29: =+AVERAGE(Tabla2[Lubricantes])*E29*1.08 -> 70832.461
B30: Tractor Herbicida | C30: =+SUMIFS(TablaGeneral[Tractor Herbicida],TablaGeneral[Finca],C24) -> 66.999922 | D30: =+C30*10 -> 669.99922 | E30: =+(D30/100)+(D30/150)+(D30/200) -> 14.51665 | F30: =+AVERAGE(Tabla2[Combustible])*D30*1.08 -> 883424.75 | G30: =+AVERAGE(Tabla2[Lubricantes])*E30*1.08 -> 105508.21
B31: Tractor Atomizadora | C31: =+SUMIFS(TablaGeneral[Tractor Atomizadora],TablaGeneral[Finca],C24) -> 83.080247 | D31: =+C31*10 -> 830.80247 | E31: =+(D31/100)+(D31/150)+(D31/200) -> 18.00072 | F31: =+AVERAGE(Tabla2[Combustible])*D31*1.08 -> 1095451.2 | G31: =+AVERAGE(Tabla2[Lubricantes])*E31*1.08 -> 130830.72
A32: Generales | B32: Tractorista Generales | C32: =+SUMIFS(TablaGeneral[Tractorista Generales],TablaGeneral[Finca],C24) -> 60 | D32: =+C32*10 -> 600 | E32: =+(D32/100)+(D32/150)+(D32/200) -> 13 | F32: =+AVERAGE(Tabla2[Combustible])*D32*1.08 -> 791127.56 | G32: =+AVERAGE(Tabla2[Lubricantes])*E32*1.08 -> 94485.072
A33: Cosecha | B33: Tracto elevador | C33: =+SUMIFS(TablaGeneral[Tracto elevador],TablaGeneral[Finca],C24) -> 50 | D33: =+C33*10 -> 500 | E33: =+(D33/100)+(D33/150)+(D33/200) -> 10.833333 | F33: =+AVERAGE(Tabla2[Combustible])*D33*1.08 -> 659272.97 | G33: =+AVERAGE(Tabla2[Lubricantes])*E33*1.08 -> 78737.56 | H33: =+SUM(F33:G35) -> 5166070 | I33: 1123.6
B34: Tractor con uñas | C34: =+SUMIFS(TablaGeneral[Tractor con uñas],TablaGeneral[Finca],C24) -> 199.99993 | D34: =+C34*10 -> 1999.9993 | E34: =+(D34/100)+(D34/150)+(D34/200) -> 43.333318 | F34: =+AVERAGE(Tabla2[Combustible])*D34*1.08 -> 2637090.9 | G34: =+AVERAGE(Tabla2[Lubricantes])*E34*1.08 -> 314950.13
B35: Tractor con acoplado | C35: =+SUMIFS(TablaGeneral[Tractor con acoplado],TablaGeneral[Finca],C24) -> 99.999823 | D35: =+C35*10 -> 999.99823 | E35: =+(D35/100)+(D35/150)+(D35/200) -> 21.666628 | F35: =+AVERAGE(Tabla2[Combustible])*D35*1.08 -> 1318543.6 | G35: =+AVERAGE(Tabla2[Lubricantes])*E35*1.08 -> 157474.84
A36: Secado | B36: Tractor Volcado de bins | C36: =+SUMIFS(TablaGeneral[Tractor Volcado de bins],TablaGeneral[Finca],C24) -> 70.834914 | D36: =+C36*10 -> 708.34914 | E36: =+(D36/100)+(D36/150)+(D36/200) -> 15.347565 | F36: =+AVERAGE(Tabla2[Combustible])*D36*1.08 -> 933990.88 | G36: =+AVERAGE(Tabla2[Lubricantes])*E36*1.08 -> 111547.37 | H36: =+SUM(F36:G40) -> 3083267 | I36: 195.43
B37: Tractor Cincelado de piedras | C37: =+SUMIFS(TablaGeneral[Tractor Cincelado de piedras],TablaGeneral[Finca],C24) -> 7.2280409 | D37: =+C37*10 -> 72.280409 | E37: =+(D37/100)+(D37/150)+(D37/200) -> 1.5660755 | F37: =+AVERAGE(Tabla2[Combustible])*D37*1.08 -> 95305.039 | G37: =+AVERAGE(Tabla2[Lubricantes])*E37*1.08 -> 11382.366
B38: Tractor Carga de pasa | C38: =+SUMIFS(TablaGeneral[Tractor Carga de pasa],TablaGeneral[Finca],C24) -> 0 | D38: =+C38*10 -> 0 | E38: =+(D38/100)+(D38/150)+(D38/200) -> 0 | F38: =+AVERAGE(Tabla2[Combustible])*D38*1.08 -> 0 | G38: =+AVERAGE(Tabla2[Lubricantes])*E38*1.08 -> 0
B39: Tractor Descarga y carga de bines con tracto elevador | C39: =+SUMIFS(TablaGeneral[Tractor Descarga y carga de bines con tracto elevador],TablaGeneral[Finca],C24) -> 67.220813 | D39: =+C39*10 -> 672.20813 | E39: =+(D39/100)+(D39/150)+(D39/200) -> 14.564509 | F39: =+AVERAGE(Tabla2[Combustible])*D39*1.08 -> 886337.3 | G39: =+AVERAGE(Tabla2[Lubricantes])*E39*1.08 -> 105856.06
B40: Descarga y carga de bines con Autoelevador | C40: =+SUMIFS(TablaGeneral[Descarga y carga de bines con Autoelevador],TablaGeneral[Finca],C24) -> 63.606681 | D40: =+C40*10 -> 636.06681 | E40: =+(D40/100)+(D40/150)+(D40/200) -> 13.781448 | F40: =+AVERAGE(Tabla2[Combustible])*D40*1.08 -> 838683.31 | G40: =+AVERAGE(Tabla2[Lubricantes])*E40*1.08 -> 100164.7
C41: =SUM(C26:C40) -> 885.70047 | D41: =SUM(D26:D40) -> 8857.0047 | E41: =SUM(E26:E40) -> 191.90177 | F41: =SUM(F26:F40) -> 11678368 | G41: =SUM(G26:G40) -> 1394757.9 | H41: =SUM(H26:H40) -> 13073126 | I41: =SUM(I26:I40) -> 4767.5
C42: =+C41/SUMIF(TablaGeneral[Finca],C24,TablaGeneral[Has]) -> 13.410804 | D42: =+D41/SUMIF(TablaGeneral[Finca],C24,TablaGeneral[Has]) -> 134.10804 | E42: =+E41/SUMIF(TablaGeneral[Finca],C24,TablaGeneral[Has]) -> 2.9056743 | F42: =+F41/SUMIF(TablaGeneral[Finca],C24,TablaGeneral[Has]) -> 176827.61 | G42: =+G41/SUMIF(TablaGeneral[Finca],C24,TablaGeneral[Has]) -> 21118.68 | H42: =+H41/SUMIF(TablaGeneral[Finca],C24,TablaGeneral[Has]) -> 197946.29 | I42: =+I41/SUMIF(TablaGeneral[Finca],C24,TablaGeneral[Has]) -> 72.186943 | K42: 57
B43: Gen | C43: =+SUM(C26:C32)/SUMIF(TablaGeneral[Finca],C24,TablaGeneral[Has]) -> 4.9483869 | E43: Generales | H43: =+H26/SUMIF(TablaGeneral[Finca],C24,TablaGeneral[Has]) -> 73039.232 | I43: =+I26/SUMIF(TablaGeneral[Finca],C24,TablaGeneral[Has]) -> 52.214894
B44: Cosecha | C44: =+SUM(C33:C35)/SUMIF(TablaGeneral[Finca],C24,TablaGeneral[Has]) -> 5.2995096 | E44: Cosecha | H44: =+H33/SUMIF(TablaGeneral[Finca],C24,TablaGeneral[Has]) -> 78221.878 | I44: =+I33/SUMIF(TablaGeneral[Finca],C24,TablaGeneral[Has]) -> 17.012952
B45: Secado | C45: =+SUM(C36:C40)/SUMIF(TablaGeneral[Finca],C24,TablaGeneral[Has]) -> 3.1629078 | E45: Secado | H45: =+H36/SUMIF(TablaGeneral[Finca],C24,TablaGeneral[Has]) -> 46685.185 | I45: =+I36/SUMIF(TablaGeneral[Finca],C24,TablaGeneral[Has]) -> 2.9590968
A47: Jornales Tractoristas y consumo de combustible | C47: La Chimbera
C48: Jornal | D48: Combustible | E48: Lubricantes | F48: u$s Comb | G48: u$s Lubr | H48: Pres 25-26 | I48: Real 24-25
A49: Específicos | B49: Tractorista Subsolado | C49: =+SUMIFS(TablaGeneral[Tractorista Subsolado],TablaGeneral[Finca],C47) -> 18.998534 | D49: =+C49*10 -> 189.98534 | E49: =+(D49/100)+(D49/150)+(D49/200) -> 4.116349 | F49: =+AVERAGE(Tabla2[Combustible])*D49*1.08 -> 250504.39 | G49: =+AVERAGE(Tabla2[Lubricantes])*E49*1.08 -> 29917.964 | H49: =+SUM(F49:G55) -> 2568587.5 | I49: 3448.47
B50: Tractorista Triturado de sarmiento | C50: =+SUMIFS(TablaGeneral[Tractorista Triturado de sarmiento],TablaGeneral[Finca],C47) -> 5 | D50: =+C50*10 -> 50 | E50: =+(D50/100)+(D50/150)+(D50/200) -> 1.0833333 | F50: =+AVERAGE(Tabla2[Combustible])*D50*1.08 -> 65927.297 | G50: =+AVERAGE(Tabla2[Lubricantes])*E50*1.08 -> 7873.756
B51: Tractorista Cincelado | C51: =+SUMIFS(TablaGeneral[Tractorista Cincelado],TablaGeneral[Finca],C47) -> 4.0015442 | D51: =+C51*10 -> 40.015442 | E51: =+(D51/100)+(D51/150)+(D51/200) -> 0.86700124 | F51: =+AVERAGE(Tabla2[Combustible])*D51*1.08 -> 52762.198 | G51: =+AVERAGE(Tabla2[Lubricantes])*E51*1.08 -> 6301.4365
B52: Tractorista Rastra | C52: =+SUMIFS(TablaGeneral[Tractorista Rastra],TablaGeneral[Finca],C47) -> 5 | D52: =+C52*10 -> 50 | E52: =+(D52/100)+(D52/150)+(D52/200) -> 1.0833333 | F52: =+AVERAGE(Tabla2[Combustible])*D52*1.08 -> 65927.297 | G52: =+AVERAGE(Tabla2[Lubricantes])*E52*1.08 -> 7873.756
B53: Tractor Herbicida | C53: =+SUMIFS(TablaGeneral[Tractor Herbicida],TablaGeneral[Finca],C47) -> 24 | D53: =+C53*10 -> 240 | E53: =+(D53/100)+(D53/150)+(D53/200) -> 5.2 | F53: =+AVERAGE(Tabla2[Combustible])*D53*1.08 -> 316451.03 | G53: =+AVERAGE(Tabla2[Lubricantes])*E53*1.08 -> 37794.029
B54: Tractor Atomizadora | C54: =+SUMIFS(TablaGeneral[Tractor Atomizadora],TablaGeneral[Finca],C47) -> 72.000133 | D54: =+C54*10 -> 720.00133 | E54: =+(D54/100)+(D54/150)+(D54/200) -> 15.600029 | F54: =+AVERAGE(Tabla2[Combustible])*D54*1.08 -> 949354.83 | G54: =+AVERAGE(Tabla2[Lubricantes])*E54*1.08 -> 113382.3
A55: Generales | B55: Tractorista Generales | C55: =+SUMIFS(TablaGeneral[Tractorista Generales],TablaGeneral[Finca],C47) -> 45.020848 | D55: =+C55*10 -> 450.20848 | E55: =+(D55/100)+(D55/150)+(D55/200) -> 9.754517 | F55: =+AVERAGE(Tabla2[Combustible])*D55*1.08 -> 593620.56 | G55: =+AVERAGE(Tabla2[Lubricantes])*E55*1.08 -> 70896.634
A56: Cosecha | B56: Tracto elevador | C56: =+SUMIFS(TablaGeneral[Tracto elevador],TablaGeneral[Finca],C47) -> 65.045181 | D56: =+C56*10 -> 650.45181 | E56: =+(D56/100)+(D56/150)+(D56/200) -> 14.093122 | F56: =+AVERAGE(Tabla2[Combustible])*D56*1.08 -> 857650.59 | G56: =+AVERAGE(Tabla2[Lubricantes])*E56*1.08 -> 102429.98 | H56: =+SUM(F56:G58) -> 3173599.6 | I56: 1123.6
B57: Tractor con uñas | C57: =+SUMIFS(TablaGeneral[Tractor con uñas],TablaGeneral[Finca],C47) -> 149.96528 | D57: =+C57*10 -> 1499.6528 | E57: =+(D57/100)+(D57/150)+(D57/200) -> 32.492477 | F57: =+AVERAGE(Tabla2[Combustible])*D57*1.08 -> 1977361.1 | G57: =+AVERAGE(Tabla2[Lubricantes])*E57*1.08 -> 236158
B58: Tractor con acoplado | C58: =+SUMIFS(TablaGeneral[Tractor con acoplado],TablaGeneral[Finca],C47) -> 0 | D58: =+C58*10 -> 0 | E58: =+(D58/100)+(D58/150)+(D58/200) -> 0 | F58: =+AVERAGE(Tabla2[Combustible])*D58*1.08 -> 0 | G58: =+AVERAGE(Tabla2[Lubricantes])*E58*1.08 -> 0
A59: Secado | B59: Tractor Volcado de bins | C59: =+SUMIFS(TablaGeneral[Tractor Volcado de bins],TablaGeneral[Finca],C47) -> 26.007627 | D59: =+C59*10 -> 260.07627 | E59: =+(D59/100)+(D59/150)+(D59/200) -> 5.6349859 | F59: =+AVERAGE(Tabla2[Combustible])*D59*1.08 -> 342922.52 | G59: =+AVERAGE(Tabla2[Lubricantes])*E59*1.08 -> 40955.543 | H59: =+SUM(F59:G63) -> 634809.61 | I59: 195.43
B60: Tractor Cincelado de piedras | C60: =+SUMIFS(TablaGeneral[Tractor Cincelado de piedras],TablaGeneral[Finca],C47) -> 0 | D60: =+C60*10 -> 0 | E60: =+(D60/100)+(D60/150)+(D60/200) -> 0 | F60: =+AVERAGE(Tabla2[Combustible])*D60*1.08 -> 0 | G60: =+AVERAGE(Tabla2[Lubricantes])*E60*1.08 -> 0
B61: Tractor Carga de pasa | C61: =+SUMIFS(TablaGeneral[Tractor Carga de pasa],TablaGeneral[Finca],C47) -> 0 | D61: =+C61*10 -> 0 | E61: =+(D61/100)+(D61/150)+(D61/200) -> 0 | F61: =+AVERAGE(Tabla2[Combustible])*D61*1.08 -> 0 | G61: =+AVERAGE(Tabla2[Lubricantes])*E61*1.08 -> 0
B62: Tractor Descarga y carga de bines con tracto elevador | C62: =+SUMIFS(TablaGeneral[Tractor Descarga y carga de bines con tracto elevador],TablaGeneral[Finca],C47) -> 9.0004168 | D62: =+C62*10 -> 90.004168 | E62: =+(D62/100)+(D62/150)+(D62/200) -> 1.9500903 | F62: =+AVERAGE(Tabla2[Combustible])*D62*1.08 -> 118674.63 | G62: =+AVERAGE(Tabla2[Lubricantes])*E62*1.08 -> 14173.417
B63: Descarga y carga de bines con Autoelevador | C63: =+SUMIFS(TablaGeneral[Descarga y carga de bines con Autoelevador],TablaGeneral[Finca],C47) -> 8.0001235 | D63: =+C63*10 -> 80.001235 | E63: =+(D63/100)+(D63/150)+(D63/200) -> 1.7333601 | F63: =+AVERAGE(Tabla2[Combustible])*D63*1.08 -> 105485.3 | G63: =+AVERAGE(Tabla2[Lubricantes])*E63*1.08 -> 12598.204
C64: =SUM(C49:C63) -> 432.03969 | D64: =SUM(D49:D63) -> 4320.3969 | E64: =SUM(E49:E63) -> 93.608598 | F64: =SUM(F49:F63) -> 5696641.7 | G64: =SUM(G49:G63) -> 680355.02 | H64: =SUM(H49:H63) -> 6376996.7 | I64: =SUM(I49:I63) -> 4767.5
C65: =+C64/SUMIF(TablaGeneral[Finca],C47,TablaGeneral[Has]) -> 10.720588 | D65: =+D64/SUMIF(TablaGeneral[Finca],C47,TablaGeneral[Has]) -> 107.20588 | E65: =+E64/SUMIF(TablaGeneral[Finca],C47,TablaGeneral[Has]) -> 2.322794 | F65: =+F64/SUMIF(TablaGeneral[Finca],C47,TablaGeneral[Has]) -> 141355.87 | G65: =+G64/SUMIF(TablaGeneral[Finca],C47,TablaGeneral[Has]) -> 16882.258 | H65: =+H64/SUMIF(TablaGeneral[Finca],C47,TablaGeneral[Has]) -> 158238.13 | I65: =+I64/SUMIF(TablaGeneral[Finca],C47,TablaGeneral[Has]) -> 118.30025 | K65: 49
B66: Gen | C66: =+SUM(C49:C55)/SUMIF(TablaGeneral[Finca],C47,TablaGeneral[Has]) -> 4.3181404 | E66: Generales | H66: =+H49/SUMIF(TablaGeneral[Finca],C47,TablaGeneral[Has]) -> 63736.662 | I66: =+I49/SUMIF(TablaGeneral[Finca],C47,TablaGeneral[Has]) -> 85.569975
B67: Cosecha | C67: =+SUM(C56:C58)/SUMIF(TablaGeneral[Finca],C47,TablaGeneral[Has]) -> 5.3352471 | E67: Cosecha | H67: =+H56/SUMIF(TablaGeneral[Finca],C47,TablaGeneral[Has]) -> 78749.371 | I67: =+I56/SUMIF(TablaGeneral[Finca],C47,TablaGeneral[Has]) -> 27.880893
B68: Secado | C68: =+SUM(C59:C63)/SUMIF(TablaGeneral[Finca],C47,TablaGeneral[Has]) -> 1.0672002 | E68: Secado | H68: =+H59/SUMIF(TablaGeneral[Finca],C47,TablaGeneral[Has]) -> 15752.1 | I68: =+I59/SUMIF(TablaGeneral[Finca],C47,TablaGeneral[Has]) -> 4.8493797
A70: Jornales Tractoristas y consumo de combustible | C70: El Espejo I
C71: Jornal | D71: Combustible | E71: Lubricantes | F71: u$s Comb | G71: u$s Lubr | H71: Pres 25-26 | I71: Real 24-25
A72: Específicos | B72: Tractorista Subsolado | C72: =+SUMIFS(TablaGeneral[Tractorista Subsolado],TablaGeneral[Finca],C70) -> 1.339117 | D72: =+C72*10 -> 13.39117 | E72: =+(D72/100)+(D72/150)+(D72/200) -> 0.29014201 | F72: =+AVERAGE(Tabla2[Combustible])*D72*1.08 -> 17656.872 | G72: =+AVERAGE(Tabla2[Lubricantes])*E72*1.08 -> 2108.776 | H72: =+SUM(F72:G78) -> 2332421.7 | I72: 3448.47 | K72: =+C72-C3 -> -14.660883
B73: Tractorista Triturado de sarmiento | C73: =+SUMIFS(TablaGeneral[Tractorista Triturado de sarmiento],TablaGeneral[Finca],C70) -> 0 | D73: =+C73*10 -> 0 | E73: =+(D73/100)+(D73/150)+(D73/200) -> 0 | F73: =+AVERAGE(Tabla2[Combustible])*D73*1.08 -> 0 | G73: =+AVERAGE(Tabla2[Lubricantes])*E73*1.08 -> 0 | K73: =+C73-C4 -> -7
B74: Tractorista Cincelado | C74: =+SUMIFS(TablaGeneral[Tractorista Cincelado],TablaGeneral[Finca],C70) -> 0 | D74: =+C74*10 -> 0 | E74: =+(D74/100)+(D74/150)+(D74/200) -> 0 | F74: =+AVERAGE(Tabla2[Combustible])*D74*1.08 -> 0 | G74: =+AVERAGE(Tabla2[Lubricantes])*E74*1.08 -> 0 | K74: =+C74-C5 -> -3.000133
B75: Tractorista Rastra | C75: =+SUMIFS(TablaGeneral[Tractorista Rastra],TablaGeneral[Finca],C70) -> 0 | D75: =+C75*10 -> 0 | E75: =+(D75/100)+(D75/150)+(D75/200) -> 0 | F75: =+AVERAGE(Tabla2[Combustible])*D75*1.08 -> 0 | G75: =+AVERAGE(Tabla2[Lubricantes])*E75*1.08 -> 0 | K75: =+C75-C6 -> -63
B76: Tractor Herbicida | C76: =+SUMIFS(TablaGeneral[Tractor Herbicida],TablaGeneral[Finca],C70) -> 14.828781 | D76: =+C76*10 -> 148.28781 | E76: =+(D76/100)+(D76/150)+(D76/200) -> 3.2129025 | F76: =+AVERAGE(Tabla2[Combustible])*D76*1.08 -> 195524.29 | G76: =+AVERAGE(Tabla2[Lubricantes])*E76*1.08 -> 23351.64 | K76: =+C76-C7 -> 7.3279496
B77: Tractor Atomizadora | C77: =+SUMIFS(TablaGeneral[Tractor Atomizadora],TablaGeneral[Finca],C70) -> 53.121983 | D77: =+C77*10 -> 531.21983 | E77: =+(D77/100)+(D77/150)+(D77/200) -> 11.509763 | F77: =+AVERAGE(Tabla2[Combustible])*D77*1.08 -> 700437.75 | G77: =+AVERAGE(Tabla2[Lubricantes])*E77*1.08 -> 83653.907 | K77: =+C77-C8 -> -7.0446837
A78: Generales | B78: Tractorista Generales | C78: =+SUMIFS(TablaGeneral[Tractorista Generales],TablaGeneral[Finca],C70) -> 88.731013 | D78: =+C78*10 -> 887.31013 | E78: =+(D78/100)+(D78/150)+(D78/200) -> 19.225053 | F78: =+AVERAGE(Tabla2[Combustible])*D78*1.08 -> 1169959.2 | G78: =+AVERAGE(Tabla2[Lubricantes])*E78*1.08 -> 139729.27 | K78: =+C78-C9 -> 40.731004
A79: Cosecha | B79: Tracto elevador | C79: =+SUMIFS(TablaGeneral[Tracto elevador],TablaGeneral[Finca],C70) -> 48.250688 | D79: =+C79*10 -> 482.50688 | E79: =+(D79/100)+(D79/150)+(D79/200) -> 10.454316 | F79: =+AVERAGE(Tabla2[Combustible])*D79*1.08 -> 636207.49 | G79: =+AVERAGE(Tabla2[Lubricantes])*E79*1.08 -> 75982.83 | H79: =+SUM(F79:G81) -> 2489882.7 | I79: 1123.6 | K79: =+C79-C10 -> 0.24536918
B80: Tractor con uñas | C80: =+SUMIFS(TablaGeneral[Tractor con uñas],TablaGeneral[Finca],C70) -> 77.250125 | D80: =+C80*10 -> 772.50125 | E80: =+(D80/100)+(D80/150)+(D80/200) -> 16.737527 | F80: =+AVERAGE(Tabla2[Combustible])*D80*1.08 -> 1018578.4 | G80: =+AVERAGE(Tabla2[Lubricantes])*E80*1.08 -> 121649.73 | K80: =+C80-C11 -> 29.244806
B81: Tractor con acoplado | C81: =+SUMIFS(TablaGeneral[Tractor con acoplado],TablaGeneral[Finca],C70) -> 43.188017 | D81: =+C81*10 -> 431.88017 | E81: =+(D81/100)+(D81/150)+(D81/200) -> 9.3574037 | F81: =+AVERAGE(Tabla2[Combustible])*D81*1.08 -> 569453.84 | G81: =+AVERAGE(Tabla2[Lubricantes])*E81*1.08 -> 68010.382 | K81: =+C81-C12 -> 43.188017
A82: Secado | B82: Tractor Volcado de bins | C82: =+SUMIFS(TablaGeneral[Tractor Volcado de bins],TablaGeneral[Finca],C70) -> 20.118945 | D82: =+C82*10 -> 201.18945 | E82: =+(D82/100)+(D82/150)+(D82/200) -> 4.3591048 | F82: =+AVERAGE(Tabla2[Combustible])*D82*1.08 -> 265277.53 | G82: =+AVERAGE(Tabla2[Lubricantes])*E82*1.08 -> 31682.333 | H82: =+SUM(F82:G86) -> 486663.88 | I82: 195.43 | K82: =+C82-C13 -> 13.11848
B83: Tractor Cincelado de piedras | C83: =+SUMIFS(TablaGeneral[Tractor Cincelado de piedras],TablaGeneral[Finca],C70) -> 0 | D83: =+C83*10 -> 0 | E83: =+(D83/100)+(D83/150)+(D83/200) -> 0 | F83: =+AVERAGE(Tabla2[Combustible])*D83*1.08 -> 0 | G83: =+AVERAGE(Tabla2[Lubricantes])*E83*1.08 -> 0 | K83: =+C83-C14 -> -0.78000761
B84: Tractor Carga de pasa | C84: =+SUMIFS(TablaGeneral[Tractor Carga de pasa],TablaGeneral[Finca],C70) -> 0 | D84: =+C84*10 -> 0 | E84: =+(D84/100)+(D84/150)+(D84/200) -> 0 | F84: =+AVERAGE(Tabla2[Combustible])*D84*1.08 -> 0 | G84: =+AVERAGE(Tabla2[Lubricantes])*E84*1.08 -> 0 | K84: =+C84-C15 -> 0
B85: Tractor Descarga y carga de bines con tracto elevador | C85: =+SUMIFS(TablaGeneral[Tractor Descarga y carga de bines con tracto elevador],TablaGeneral[Finca],C70) -> 6.6335363 | D85: =+C85*10 -> 66.335363 | E85: =+(D85/100)+(D85/150)+(D85/200) -> 1.4372662 | F85: =+AVERAGE(Tabla2[Combustible])*D85*1.08 -> 87466.223 | G85: =+AVERAGE(Tabla2[Lubricantes])*E85*1.08 -> 10446.169 | K85: =+C85-C16 -> 0.63287136
B86: Descarga y carga de bines con Autoelevador | C86: =+SUMIFS(TablaGeneral[Descarga y carga de bines con Autoelevador],TablaGeneral[Finca],C70) -> 6.2188557 | D86: =+C86*10 -> 62.188557 | E86: =+(D86/100)+(D86/150)+(D86/200) -> 1.3474187 | F86: =+AVERAGE(Tabla2[Combustible])*D86*1.08 -> 81998.47 | G86: =+AVERAGE(Tabla2[Lubricantes])*E86*1.08 -> 9793.1506 | K86: =+C86-C17 -> -0.27114858
C87: =SUM(C72:C86) -> 359.68106 | D87: =SUM(D72:D86) -> 3596.8106 | E87: =SUM(E72:E86) -> 77.930896 | F87: =SUM(F72:F86) -> 4742560 | G87: =SUM(G72:G86) -> 566408.18 | H87: =SUM(H72:H86) -> 5308968.2 | I87: =SUM(I72:I86) -> 4767.5
C88: =+C87/SUMIF(TablaGeneral[Finca],C70,TablaGeneral[Has]) -> 6.4355173 | D88: =+D87/SUMIF(TablaGeneral[Finca],C70,TablaGeneral[Has]) -> 64.355173 | E88: =+E87/SUMIF(TablaGeneral[Finca],C70,TablaGeneral[Has]) -> 1.3943621 | F88: =+F87/SUMIF(TablaGeneral[Finca],C70,TablaGeneral[Has]) -> 84855.252 | G88: =+G87/SUMIF(TablaGeneral[Finca],C70,TablaGeneral[Has]) -> 10134.339 | H88: =+H87/SUMIF(TablaGeneral[Finca],C70,TablaGeneral[Has]) -> 94989.59 | I88: =+I87/SUMIF(TablaGeneral[Finca],C70,TablaGeneral[Has]) -> 85.301485
B89: Gen | C89: =+SUM(C72:C78)/SUMIF(TablaGeneral[Finca],C70,TablaGeneral[Has]) -> 2.8273554 | E89: Generales | H89: =+H72/SUMIF(TablaGeneral[Finca],C70,TablaGeneral[Has]) -> 41732.361 | I89: =+I72/SUMIF(TablaGeneral[Finca],C70,TablaGeneral[Has]) -> 61.70102
B90: Cosecha | C90: =+SUM(C79:C81)/SUMIF(TablaGeneral[Finca],C70,TablaGeneral[Has]) -> 3.0182292 | E90: Cosecha | H90: =+H79/SUMIF(TablaGeneral[Finca],C70,TablaGeneral[Has]) -> 44549.699 | I90: =+I79/SUMIF(TablaGeneral[Finca],C70,TablaGeneral[Has]) -> 20.103775
B91: Secado | C91: =+SUM(C82:C86)/SUMIF(TablaGeneral[Finca],C70,TablaGeneral[Has]) -> 0.58993267 | E91: Secado | H91: =+H82/SUMIF(TablaGeneral[Finca],C70,TablaGeneral[Has]) -> 8707.5305 | I91: =+I82/SUMIF(TablaGeneral[Finca],C70,TablaGeneral[Has]) -> 3.4966899
A93: Jornales Tractoristas y consumo de combustible | C93: El Espejo II
C94: Jornal | D94: Combustible | E94: Lubricantes | F94: u$s Comb | G94: u$s Lubr | H94: Pres 25-26 | I94: Real 24-25
A95: Específicos | B95: Tractorista Subsolado | C95: =+SUMIFS(TablaGeneral[Tractorista Subsolado],TablaGeneral[Finca],C93) -> 2.2908839 | D95: =+C95*10 -> 22.908839 | E95: =+(D95/100)+(D95/150)+(D95/200) -> 0.49635817 | F95: =+AVERAGE(Tabla2[Combustible])*D95*1.08 -> 30206.356 | G95: =+AVERAGE(Tabla2[Lubricantes])*E95*1.08 -> 3607.5721 | H95: =+SUM(F95:G101) -> 3990172.1 | I95: 3448.47
B96: Tractorista Triturado de sarmiento | C96: =+SUMIFS(TablaGeneral[Tractorista Triturado de sarmiento],TablaGeneral[Finca],C93) -> 0 | D96: =+C96*10 -> 0 | E96: =+(D96/100)+(D96/150)+(D96/200) -> 0 | F96: =+AVERAGE(Tabla2[Combustible])*D96*1.08 -> 0 | G96: =+AVERAGE(Tabla2[Lubricantes])*E96*1.08 -> 0
B97: Tractorista Cincelado | C97: =+SUMIFS(TablaGeneral[Tractorista Cincelado],TablaGeneral[Finca],C93) -> 0 | D97: =+C97*10 -> 0 | E97: =+(D97/100)+(D97/150)+(D97/200) -> 0 | F97: =+AVERAGE(Tabla2[Combustible])*D97*1.08 -> 0 | G97: =+AVERAGE(Tabla2[Lubricantes])*E97*1.08 -> 0
B98: Tractorista Rastra | C98: =+SUMIFS(TablaGeneral[Tractorista Rastra],TablaGeneral[Finca],C93) -> 0 | D98: =+C98*10 -> 0 | E98: =+(D98/100)+(D98/150)+(D98/200) -> 0 | F98: =+AVERAGE(Tabla2[Combustible])*D98*1.08 -> 0 | G98: =+AVERAGE(Tabla2[Lubricantes])*E98*1.08 -> 0
B99: Tractor Herbicida | C99: =+SUMIFS(TablaGeneral[Tractor Herbicida],TablaGeneral[Finca],C93) -> 25.368221 | D99: =+C99*10 -> 253.68221 | E99: =+(D99/100)+(D99/150)+(D99/200) -> 5.4964478 | F99: =+AVERAGE(Tabla2[Combustible])*D99*1.08 -> 334491.64 | G99: =+AVERAGE(Tabla2[Lubricantes])*E99*1.08 -> 39948.636
B100: Tractor Atomizadora | C100: =+SUMIFS(TablaGeneral[Tractor Atomizadora],TablaGeneral[Finca],C93) -> 90.878017 | D100: =+C100*10 -> 908.78017 | E100: =+(D100/100)+(D100/150)+(D100/200) -> 19.690237 | F100: =+AVERAGE(Tabla2[Combustible])*D100*1.08 -> 1198268.4 | G100: =+AVERAGE(Tabla2[Lubricantes])*E100*1.08 -> 143110.27
A101: Generales | B101: Tractorista Generales | C101: =+SUMIFS(TablaGeneral[Tractorista Generales],TablaGeneral[Finca],C93) -> 151.79589 | D101: =+C101*10 -> 1517.9589 | E101: =+(D101/100)+(D101/150)+(D101/200) -> 32.889109 | F101: =+AVERAGE(Tabla2[Combustible])*D101*1.08 -> 2001498.5 | G101: =+AVERAGE(Tabla2[Lubricantes])*E101*1.08 -> 239040.75
A102: Cosecha | B102: Tracto elevador | C102: =+SUMIFS(TablaGeneral[Tracto elevador],TablaGeneral[Finca],C93) -> 59.749319 | D102: =+C102*10 -> 597.49319 | E102: =+(D102/100)+(D102/150)+(D102/200) -> 12.945686 | F102: =+AVERAGE(Tabla2[Combustible])*D102*1.08 -> 787822.22 | G102: =+AVERAGE(Tabla2[Lubricantes])*E102*1.08 -> 94090.312 | H102: =+SUM(F102:G104) -> 2425259.4 | I102: 1123.6
B103: Tractor con uñas | C103: =+SUMIFS(TablaGeneral[Tractor con uñas],TablaGeneral[Finca],C93) -> 59.749319 | D103: =+C103*10 -> 597.49319 | E103: =+(D103/100)+(D103/150)+(D103/200) -> 12.945686 | F103: =+AVERAGE(Tabla2[Combustible])*D103*1.08 -> 787822.22 | G103: =+AVERAGE(Tabla2[Lubricantes])*E103*1.08 -> 94090.312
B104: Tractor con acoplado | C104: =+SUMIFS(TablaGeneral[Tractor con acoplado],TablaGeneral[Finca],C93) -> 44.811986 | D104: =+C104*10 -> 448.11986 | E104: =+(D104/100)+(D104/150)+(D104/200) -> 9.7092635 | F104: =+AVERAGE(Tabla2[Combustible])*D104*1.08 -> 590866.62 | G104: =+AVERAGE(Tabla2[Lubricantes])*E104*1.08 -> 70567.728
...

Sheet Personal Camino Truncado
A1: Finca | B1: Detalle | C1: MES | D1: Valor
A2: Camino Truncado | B2: Encargados | C2: Mayo | D2: 851.01124
A3: Camino Truncado | B3: Encargados | C3: Junio | D3: 1210.6493
A4: Camino Truncado | B4: Encargados | C4: Julio | D4: 866.89071
A5: Camino Truncado | B5: Encargados | C5: Agosto | D5: 884.40539
A6: Camino Truncado | B6: Encargados | C6: Septiembre | D6: 843.33838
A7: Camino Truncado | B7: Encargados | C7: Octubre | D7: 894.0715
A8: Camino Truncado | B8: Encargados | C8: Noviembre | D8: 852.67927
A9: Camino Truncado | B9: Encargados | C9: Diciembre | D9: 1294.0648
A10: Camino Truncado | B10: Encargados | C10: Enero | D10: 574.23635
A11: Camino Truncado | B11: Encargados | C11: Febrero | D11: 249.21215
A12: Camino Truncado | B12: Encargados | C12: Marzo | D12: 258.67504
A13: Camino Truncado | B13: Encargados | C13: Abril | D13: 258.65599
... A49: Camino Truncado | B49: Dirección Técnica | C49: Abril | D49: 673.81727

Sheet Fletes Varios
A1: Finca | B1: MES | C1: Valor | D1: Detalle
A2: Camino Truncado | B2: Mayo | C2: 21.186441 | D2: Fletes Varios
A3: Camino Truncado | B3: Junio | C3: 21.186441 | D3: Fletes Varios
A4: Camino Truncado | B4: Julio | C4: 21.186441 | D4: Fletes Varios
A5: Camino Truncado | B5: Agosto | C5: 21.186441 | D5: Fletes Varios
A6: Camino Truncado | B6: Septiembre | C6: 21.186441 | D6: Fletes Varios
A7: Camino Truncado | B7: Octubre | C7: 21.186441 | D7: Fletes Varios
A8: Camino Truncado | B8: Noviembre | C8: 21.186441 | D8: Fletes Varios
A9: Camino Truncado | B9: Diciembre | C9: 84.745763 | D9: Fletes Varios
A10: Camino Truncado | B10: Enero | C10: 84.745763 | D10: Fletes Varios
A11: Camino Truncado | B11: Febrero | C11: 84.745763 | D11: Fletes Varios
A12: Camino Truncado | B12: Marzo | C12: 21.186441 | D12: Fletes Varios
A13: Camino Truncado | B13: Abril | C13: 21.186441 | D13: Fletes Varios
... A61: El Espejo III | B61: Abril | C61: 32.037288 | D61: Fletes Varios

Sheet Visualización Jornales CT (2)
A1: Detalle | B1: MES | C1: Valor | D1: Finca
A2: Contratados | B2: Mayo | C2: 2837.4809 | D2: Camino Truncado
A3: Contratados | B3: Junio | C3: 8014.3944 | D3: Camino Truncado
A4: Contratados | B4: Julio | C4: 5604.4875 | D4: Camino Truncado
A5: Contratados | B5: Agosto | C5: 8076.4774 | D5: Camino Truncado
A6: Contratados | B6: Septiembre | C6: 1965.2234 | D6: Camino Truncado
A7: Contratados | B7: Octubre | C7: 2116.0945 | D7: Camino Truncado
A8: Contratados | B8: Noviembre | C8: 2705.0098 | D8: Camino Truncado
A9: Contratados | B9: Diciembre | C9: 1767.4624 | D9: Camino Truncado
A10: Contratados | B10: Enero | C10: 1253.9971 | D10: Camino Truncado
A11: Contratados | B11: Febrero | C11: 5914.3558 | D11: Camino Truncado
A12: Contratados | B12: Marzo | C12: 5416.766 | D12: Camino Truncado
A13: Contratados | B13: Abril | C13: 2045.6973 | D13: Camino Truncado
... A25: Combustible y Lubricantes | B25: Abril | C25: 318.45264 | D25: Camino Truncado

Sheet Personal La Chimbera
A1: Finca | B1: Detalle | C1: MES | D1: Valor
A2: La Chimbera | B2: Encargados | C2: Mayo | D2: 742.75924
A3: La Chimbera | B3: Encargados | C3: Junio | D3: 1049.879
A4: La Chimbera | B4: Encargados | C4: Julio | D4: 760.7717
A5: La Chimbera | B5: Encargados | C5: Agosto | D5: 780.54277
A6: La Chimbera | B6: Encargados | C6: Septiembre | D6: 740.5041
A7: La Chimbera | B7: Encargados | C7: Octubre | D7: 792.25538
A8: La Chimbera | B8: Encargados | C8: Noviembre | D8: 751.87124
A9: La Chimbera | B9: Encargados | C9: Diciembre | D9: 1144.3499
A10: La Chimbera | B10: Encargados | C10: Enero | D10: 588.83285
A11: La Chimbera | B11: Encargados | C11: Febrero | D11: 220.29727
A12: La Chimbera | B12: Encargados | C12: Marzo | D12: 230.05512
A13: La Chimbera | B13: Encargados | C13: Abril | D13: 767.76009
... A49: La Chimbera | B49: Dirección Técnica | C49: Abril | D49: 404.29036

Sheet Personal Puente Alto
A1: Finca | B1: Detalle | C1: MES | D1: Valor
A2: Puente Alto | B2: Encargados | C2: Mayo | D2: 711.62072
A3: Puente Alto | B3: Encargados | C3: Junio | D3: 1008.0255
A4: Puente Alto | B4: Encargados | C4: Julio | D4: 728.86405
A5: Puente Alto | B5: Encargados | C5: Agosto | D5: 745.76642
A6: Puente Alto | B6: Encargados | C6: Septiembre | D6: 708.3263
A7: Puente Alto | B7: Encargados | C7: Octubre | D7: 756.2741
A8: Puente Alto | B8: Encargados | C8: Noviembre | D8: 718.51644
A9: Puente Alto | B9: Encargados | C9: Diciembre | D9: 1092.8798
A10: Puente Alto | B10: Encargados | C10: Enero | D10: 561.4522
A11: Puente Alto | B11: Encargados | C11: Febrero | D11: 210.08203
A12: Puente Alto | B12: Encargados | C12: Marzo | D12: 219.09999
A13: Puente Alto | B13: Encargados | C13: Abril | D13: 730.98473
... A49: Puente Alto | B49: Dirección Técnica | C49: Abril | D49: 162.00458

Sheet Personal El Espejo III
A1: Finca | B1: Detalle | C1: MES | D1: Valor
A2: El Espejo III | B2: Encargados | C2: Mayo | D2: 333.98416
A3: El Espejo III | B3: Encargados | C3: Junio | D3: 481.3886
A4: El Espejo III | B4: Encargados | C4: Julio | D4: 336.62927
A5: El Espejo III | B5: Encargados | C5: Agosto | D5: 340.50188
A6: El Espejo III | B6: Encargados | C6: Septiembre | D6: 332.06919
A7: El Espejo III | B7: Encargados | C7: Octubre | D7: 349.83719
A8: El Espejo III | B8: Encargados | C8: Noviembre | D8: 340.5243
A9: El Espejo III | B9: Encargados | C9: Diciembre | D9: 519.71183
A10: El Espejo III | B10: Encargados | C10: Enero | D10: 355.63642
A11: El Espejo III | B11: Encargados | C11: Febrero | D11: 341.22759
A12: El Espejo III | B12: Encargados | C12: Marzo | D12: 353.92628
A13: El Espejo III | B13: Encargados | C13: Abril | D13: 356.56965
... A37: El Espejo III | B37: Cargas Sociales | C37: Abril | D37: 699.7674

Sheet Personal El Espejo I y II
A1: Finca | B1: Detalle | C1: MES | D1: Valor
A2: El Espejo I y II | B2: Encargados | C2: Mayo | D2: 795.3371
A3: El Espejo I y II | B3: Encargados | C3: Junio | D3: 1146.3604
A4: El Espejo I y II | B4: Encargados | C4: Julio | D4: 801.63607
A5: El Espejo I y II | B5: Encargados | C5: Agosto | D5: 810.85817
A6: El Espejo I y II | B6: Encargados | C6: Septiembre | D6: 790.77686
A7: El Espejo I y II | B7: Encargados | C7: Octubre | D7: 833.08891
A8: El Espejo I y II | B8: Encargados | C8: Noviembre | D8: 810.91155
A9: El Espejo I y II | B9: Encargados | C9: Diciembre | D9: 1237.6219
A10: El Espejo I y II | B10: Encargados | C10: Enero | D10: 846.89897
A11: El Espejo I y II | B11: Encargados | C11: Febrero | D11: 812.58633
A12: El Espejo I y II | B12: Encargados | C12: Marzo | D12: 842.82651
A13: El Espejo I y II | B13: Encargados | C13: Abril | D13: 849.12132
... A37: El Espejo I y II | B37: Cargas Sociales | C37: Abril | D37: 1666.3993

Sheet Fito CT
A1: Detalle | B1: Finca | C1: MES | D1: Valor
A2: Coadyuvantes | B2: Camino Truncado | C2: Octubre | D2: 66.416815
A3: Coadyuvantes | B3: Camino Truncado | C3: Noviembre | D3: 79.700178
A4: Coadyuvantes | B4: Camino Truncado | C4: Diciembre | D4: 66.416815
A5: Coadyuvantes | B5: Camino Truncado | C5: Febrero | D5: 119.55027
A6: Coadyuvantes | B6: Camino Truncado | C6: Octubre | D6: 101.82369
A7: Coadyuvantes | B7: Camino Truncado | C7: Noviembre | D7: 122.18843
A8: Coadyuvantes | B8: Camino Truncado | C8: Diciembre | D8: 101.82369
A9: Coadyuvantes | B9: Camino Truncado | C9: Febrero | D9: 183.28264
A10: Foliares | B10: Camino Truncado | C10: Octubre | D10: 19.714074
A11: Foliares | B11: Camino Truncado | C11: Noviembre | D11: 23.656889
A12: Foliares | B12: Camino Truncado | C12: Diciembre | D12: 19.714074
A13: Foliares | B13: Camino Truncado | C13: Febrero | D13: 35.485334
... A89: Insecticidas | B89: Camino Truncado | C89: Febrero | D89: 0

Sheet Fito PA
A1: Detalle | B1: Finca | C1: MES | D1: Valor
A2: Coadyuvantes | B2: Puente Alto | C2: Octubre | D2: 26.931253
A3: Coadyuvantes | B3: Puente Alto | C3: Noviembre | D3: 32.317504
A4: Coadyuvantes | B4: Puente Alto | C4: Diciembre | D4: 26.931253
A5: Coadyuvantes | B5: Puente Alto | C5: Febrero | D5: 48.476256
A6: Coadyuvantes | B6: Puente Alto | C6: Octubre | D6: 41.288333
A7: Coadyuvantes | B7: Puente Alto | C7: Noviembre | D7: 49.545999
A8: Coadyuvantes | B8: Puente Alto | C8: Diciembre | D8: 41.288333
A9: Coadyuvantes | B9: Puente Alto | C9: Febrero | D9: 74.318999
A10: Foliares | B10: Puente Alto | C10: Octubre | D10: 7.99383
A11: Foliares | B11: Puente Alto | C11: Noviembre | D11: 9.592596
A12: Foliares | B12: Puente Alto | C12: Diciembre | D12: 7.99383
A13: Foliares | B13: Puente Alto | C13: Febrero | D13: 14.388894
... A89: Insecticidas | B89: Puente Alto | C89: Febrero | D89: 0

Sheet Fito EE III
A1: Detalle | B1: Finca | C1: MES | D1: Valor
A2: Coadyuvantes | B2: El Espejo III | C2: Octubre | D2: 72.832789
A3: Coadyuvantes | B3: El Espejo III | C3: Noviembre | D3: 87.399347
A4: Coadyuvantes | B4: El Espejo III | C4: Diciembre | D4: 72.832789
A5: Coadyuvantes | B5: El Espejo III | C5: Febrero | D5: 131.09902
A6: Coadyuvantes | B6: El Espejo III | C6: Octubre | D6: 111.66003
A7: Coadyuvantes | B7: El Espejo III | C7: Noviembre | D7: 133.99203
A8: Coadyuvantes | B8: El Espejo III | C8: Diciembre | D8: 111.66003
A9: Coadyuvantes | B9: El Espejo III | C9: Febrero | D9: 200.98805
A10: Foliares | B10: El Espejo III | C10: Octubre | D10: 21.618486
A11: Foliares | B11: El Espejo III | C11: Noviembre | D11: 25.942184
A12: Foliares | B12: El Espejo III | C12: Diciembre | D12: 21.618486
A13: Foliares | B13: El Espejo III | C13: Febrero | D13: 38.913276
... A89: Insecticidas | B89: El Espejo III | C89: Febrero | D89: 0

Sheet Fito EE I y II
A1: Detalle | B1: Finca | C1: MES | D1: Valor
A2: Coadyuvantes | B2: El Espejo I y II | C2: Octubre | D2: 173.44122
A3: Coadyuvantes | B3: El Espejo I y II | C3: Noviembre | D3: 208.12946
A4: Coadyuvantes | B4: El Espejo I y II | C4: Diciembre | D4: 173.44122
A5: Coadyuvantes | B5: El Espejo I y II | C5: Febrero | D5: 312.19419
A6: Coadyuvantes | B6: El Espejo I y II | C6: Octubre | D6: 265.90291
A7: Coadyuvantes | B7: El Espejo I y II | C7: Noviembre | D7: 319.0835
A8: Coadyuvantes | B8: El Espejo I y II | C8: Diciembre | D8: 265.90291
A9: Coadyuvantes | B9: El Espejo I y II | C9: Febrero | D9: 478.62525
A10: Foliares | B10: El Espejo I y II | C10: Octubre | D10: 51.481437
A11: Foliares | B11: El Espejo I y II | C11: Noviembre | D11: 61.777724
A12: Foliares | B12: El Espejo I y II | C12: Diciembre | D12: 51.481437
A13: Foliares | B13: El Espejo I y II | C13: Febrero | D13: 92.666586
... A89: Insecticidas | B89: El Espejo I y II | C89: Febrero | D89: 0

Sheet Fito LCH
A1: Detalle | B1: Finca | C1: MES | D1: Valor
A2: Coadyuvantes | B2: La Chimbera | C2: Octubre | D2: 40.527614
A3: Coadyuvantes | B3: La Chimbera | C3: Noviembre | D3: 48.633137
A4: Coadyuvantes | B4: La Chimbera | C4: Diciembre | D4: 40.527614
A5: Coadyuvantes | B5: La Chimbera | C5: Febrero | D5: 72.949706
A6: Coadyuvantes | B6: La Chimbera | C6: Octubre | D6: 62.132928
A7: Coadyuvantes | B7: La Chimbera | C7: Noviembre | D7: 74.559514
A8: Coadyuvantes | B8: La Chimbera | C8: Diciembre | D8: 62.132928
A9: Coadyuvantes | B9: La Chimbera | C9: Febrero | D9: 111.83927
A10: Foliares | B10: La Chimbera | C10: Octubre | D10: 12.02955
A11: Foliares | B11: La Chimbera | C11: Noviembre | D11: 14.43546
A12: Foliares | B12: La Chimbera | C12: Diciembre | D12: 12.02955
A13: Foliares | B13: La Chimbera | C13: Febrero | D13: 21.65319
... A89: Insecticidas | B89: La Chimbera | C89: Febrero | D89: 0

Sheet Cosechas
A1: Finca | B1: Detalle | C1: MES | D1: Valor
A2: Camino Truncado | B2: Cosecha | C2: Enero | D2: 15291.575 | F2: Cosecha | G2: Camino truncado
A3: Camino Truncado | B3: Cosecha | C3: Febrero | D3: 17821.932
A4: Camino Truncado | B4: Cosecha | C4: Marzo | D4: 18262.831
A5: Camino Truncado | B5: Cosecha | C5: Abril | D5: 0
A6: Camino Truncado | B6: Combustible Cosecha | C6: Enero | D6: 835.47067
A7: Camino Truncado | B7: Combustible Cosecha | C7: Febrero | D7: 1654.3974
A8: Camino Truncado | B8: Combustible Cosecha | C8: Marzo | D8: 1638.0172
A9: Camino Truncado | B9: Combustible Cosecha | C9: Abril | D9: 0
A10: Camino Truncado | B10: Alquiler Maquinaria Cos | C10: Enero | D10: 1500
A11: Camino Truncado | B11: Alquiler Maquinaria Cos | C11: Febrero | D11: 1500
A12: Camino Truncado | B12: Alquiler Maquinaria Cos | C12: Marzo | D12: 1500
A13: Camino Truncado | B13: Alquiler Maquinaria Cos | C13: Abril | D13: 0
A14: Camino Truncado | B14: Flete Cosecha | C14: Enero | D14: 0
... A81: El Espejo III | B81: Flete Cosecha | C81: Abril | D81: 0

Sheet COSECHA
A1: Finca | B1: Variedad | C1: Faena | D1: Tipo de Cosecha | E1: KG uva | F1: Jornales | G1: Bins | H1: KG | I1: Días Hab | J1: Carros | K1: Mes | L1: Bins + Carros | M1: Jornales $ | N1: Cosecha | O1: PA | P1: CT | Q1: LCH | R1: EE I y II | S1: EE III | V1: TC | W1: 1220.3795 | X1: 1232.5833 | Y1: 1244.9091 | Z1: 1257.3582
A2: Puente Alto | B2: Selma | C2: Anotador | D2: Bins | E2: 99950 | F2: 9.912766 | G2: =+COSECHA[[#This Row],[KG]]/300 -> 83.291667 | H2: =+IFERROR(COSECHA[[#This Row],[KG uva]]/COUNTIFS(COSECHA[Finca],COSECHA[[#This Row],[Finca]],COSECHA[Variedad],COSECHA[[#This Row],[Variedad]],COSECHA[Tipo de Cosecha],COSECHA[[#This Row],[Tipo de Cosecha]]),0) -> 24987.5 | K2: Enero | L2: =+IFERROR(IF(COSECHA[[#This Row],[Bins]]="",COSECHA[[#This Row],[KG]]*INDEX(Tabla2[Precio Kg Uva Carro],MATCH(COSECHA[[#This Row],[Mes]],Tabla2[Mes],0)),COSECHA[[#This Row],[Bins]]*INDEX(Tabla2[Precio Bins],MATCH(COSECHA[[#This Row],[Mes]],Tabla2[Mes],0))),0) -> 409170.31 | M2: =+IFERROR(INDEX(Tabla2[Precio Jornal],MATCH(COSECHA[[#This Row],[Mes]],Tabla2[Mes],0))*COSECHA[[#This Row],[Jornales]],0) -> 218910.55 | N2: =+COSECHA[[#This Row],[Jornales $]]+SUM(COSECHA[[#This Row],[PA]:[EE III]]) -> 873583.05 | O2: =+IF(COSECHA[[#This Row],[Finca]]="Puente Alto",INDEX(Tabla2[kg pa],MATCH(COSECHA[[#This Row],[Mes]],Tabla2[Mes],0))*COSECHA[[#This Row],[KG]],"") -> 654672.5 | U2: Finca | V2: Detalle | W2: Enero | X2: Febrero | Y2: Marzo | Z2: Abril | AC2: =+SUM(W3:Z3,W11:Z11)/(66+25) -> 798.25756
A3: Puente Alto | B3: Selma | C3: Tracto elevador | D3: Bins | E3: 99950 | F3: 9.912766 | G3: =+COSECHA[[#This Row],[KG]]/300 -> 83.291667 | H3: =+IFERROR(COSECHA[[#This Row],[KG uva]]/COUNTIFS(COSECHA[Finca],COSECHA[[#This Row],[Finca]],COSECHA[Variedad],COSECHA[[#This Row],[Variedad]],COSECHA[Tipo de Cosecha],COSECHA[[#This Row],[Tipo de Cosecha]]),0) -> 24987.5 | K3: Enero | L3: =+IFERROR(IF(COSECHA[[#This Row],[Bins]]="",COSECHA[[#This Row],[KG]]*INDEX(Tabla2[Precio Kg Uva Carro],MATCH(COSECHA[[#This Row],[Mes]],Tabla2[Mes],0)),COSECHA[[#This Row],[Bins]]*INDEX(Tabla2[Precio Bins],MATCH(COSECHA[[#This Row],[Mes]],Tabla2[Mes],0))),0) -> 409170.31 | M3: =+IFERROR(INDEX(Tabla2[Precio Jornal],MATCH(COSECHA[[#This Row],[Mes]],Tabla2[Mes],0))*COSECHA[[#This Row],[Jornales]],0) -> 218910.55 | N3: =+COSECHA[[#This Row],[Jornales $]]+SUM(COSECHA[[#This Row],[PA]:[EE III]]) -> 873583.05 | O3: =+IF(COSECHA[[#This Row],[Finca]]="Puente Alto",INDEX(Tabla2[kg pa],MATCH(COSECHA[[#This Row],[Mes]],Tabla2[Mes],0))*COSECHA[[#This Row],[KG]],"") -> 654672.5 | U3: Camino Truncado | V3: Cosecha | W3: =+SUMIFS(COSECHA[Cosecha],COSECHA[Finca],$U$3,COSECHA[Mes],W$2)/W$1 -> 15291.575 | X3: =+SUMIFS(COSECHA[Cosecha],COSECHA[Finca],$U$3,COSECHA[Mes],X$2)/X$1 -> 17821.932 | Y3: =+SUMIFS(COSECHA[Cosecha],COSECHA[Finca],$U$3,COSECHA[Mes],Y$2)/Y$1 -> 18262.831 | Z3: =+SUMIFS(COSECHA[Cosecha],COSECHA[Finca],$U$3,COSECHA[Mes],Z$2)/Z$1 -> 0 | AB3: =+SUM(Cosechas[[#This Row],[Enero]:[Abril]])/66.04 -> 777.95787 | AC3: =+SUM(W3:Y3,W7:Y7,W11:Y11)/133.13 -> 810.23304
A4: Puente Alto | B4: Selma | C4: Tractor con uñas | D4: Bins | E4: 99950 | F4: 9.912766 | G4: =+COSECHA[[#This Row],[KG]]/300 -> 83.291667 | H4: =+IFERROR(COSECHA[[#This Row],[KG uva]]/COUNTIFS(COSECHA[Finca],COSECHA[[#This Row],[Finca]],COSECHA[Variedad],COSECHA[[#This Row],[Variedad]],COSECHA[Tipo de Cosecha],COSECHA[[#This Row],[Tipo de Cosecha]]),0) -> 24987.5 | K4: Enero | L4: =+IFERROR(IF(COSECHA[[#This Row],[Bins]]="",COSECHA[[#This Row],[KG]]*INDEX(Tabla2[Precio Kg Uva Carro],MATCH(COSECHA[[#This Row],[Mes]],Tabla2[Mes],0)),COSECHA[[#This Row],[Bins]]*INDEX(Tabla2[Precio Bins],MATCH(COSECHA[[#This Row],[Mes]],Tabla2[Mes],0))),0) -> 409170.31 | M4: =+IFERROR(INDEX(Tabla2[Precio Jornal],MATCH(COSECHA[[#This Row],[Mes]],Tabla2[Mes],0))*COSECHA[[#This Row],[Jornales]],0) -> 218910.55 | N4: =+COSECHA[[#This Row],[Jornales $]]+SUM(COSECHA[[#This Row],[PA]:[EE III]]) -> 873583.05 | O4: =+IF(COSECHA[[#This Row],[Finca]]="Puente Alto",INDEX(Tabla2[kg pa],MATCH(COSECHA[[#This Row],[Mes]],Tabla2[Mes],0))*COSECHA[[#This Row],[KG]],"") -> 654672.5 | U4: Camino Truncado | V4: Combustible Cosecha | W4: =+(SUMIFS(TablaGeneral[Resumen de Jornales tractoristas de Cosecha],TablaGeneral[Finca],$U$3)*10*INDEX(Tabla2[Combustible],MATCH(W$2,Tabla2[Mes],0))*0.2)/W1 -> 717.49949 | X4: =+(SUMIFS(TablaGeneral[Resumen de Jornales tractoristas de Cosecha],TablaGeneral[Finca],$U$3)*10*INDEX(Tabla2[Combustible],MATCH(X$2,Tabla2[Mes],0))*0.2)/X1 -> 717.49949 | Y4: =+(SUMIFS(TablaGeneral[Resumen de Jornales tractoristas de Cosecha],TablaGeneral[Finca],$U$3)*10*INDEX(Tabla2[Combustible],MATCH(Y$2,Tabla2[Mes],0))*0.2)/Y1 -> 717.49949 | Z4: 0 | AB4: =+SUM(Cosechas[[#This Row],[Enero]:[Abril]])/66.04 -> 32.593859 | AC4: =+AB15 -> 1117.6268
A5: Puente Alto | B5: Selma | C5: Lavar Bines | D5: Bins | E5: 99950 | F5: 4.3339535 | G5: =+COSECHA[[#This Row],[KG]]/300 -> 83.291667 | H5: =+IFERROR(COSECHA[[#This Row],[KG uva]]/COUNTIFS(COSECHA[Finca],COSECHA[[#This Row],[Finca]],COSECHA[Variedad],COSECHA[[#This Row],[Variedad]],COSECHA[Tipo de Cosecha],COSECHA[[#This Row],[Tipo de Cosecha]]),0) -> 24987.5 | K5: Enero | L5: =+IFERROR(IF(COSECHA[[#This Row],[Bins]]="",COSECHA[[#This Row],[KG]]*INDEX(Tabla2[Precio Kg Uva Carro],MATCH(COSECHA[[#This Row],[Mes]],Tabla2[Mes],0)),COSECHA[[#This Row],[Bins]]*INDEX(Tabla2[Precio Bins],MATCH(COSECHA[[#This Row],[Mes]],Tabla2[Mes],0))),0) -> 409170.31 | M5: =+IFERROR(INDEX(Tabla2[Precio Jornal],MATCH(COSECHA[[#This Row],[Mes]],Tabla2[Mes],0))*COSECHA[[#This Row],[Jornales]],0) -> 95709.729 | N5: =+COSECHA[[#This Row],[Jornales $]]+SUM(COSECHA[[#This Row],[PA]:[EE III]]) -> 750382.23 | O5: =+IF(COSECHA[[#This Row],[Finca]]="Puente Alto",INDEX(Tabla2[kg pa],MATCH(COSECHA[[#This Row],[Mes]],Tabla2[Mes],0))*COSECHA[[#This Row],[KG]],"") -> 654672.5 | U5: Camino Truncado | V5: Alquiler Maquinaria Cos | W5: 1500 | X5: 1500 | Y5: 1500 | Z5: 0 | AB5: =+SUM(Cosechas[[#This Row],[Enero]:[Abril]])/66.04 -> 68.140521
A6: Puente Alto | B6: Flame | C6: Anotador | D6: Bins | E6: 522280 | F6: 25.955319 | G6: =+COSECHA[[#This Row],[KG]]/300 -> 435.23333 | H6: =+IFERROR(COSECHA[[#This Row],[KG uva]]/COUNTIFS(COSECHA[Finca],COSECHA[[#This Row],[Finca]],COSECHA[Variedad],COSECHA[[#This Row],[Variedad]],COSECHA[Tipo de Cosecha],COSECHA[[#This Row],[Tipo de Cosecha]]),0) -> 130570 | K6: Febrero | L6: =+IFERROR(IF(COSECHA[[#This Row],[Bins]]="",COSECHA[[#This Row],[KG]]*INDEX(Tabla2[Precio Kg Uva Carro],MATCH(COSECHA[[#This Row],[Mes]],Tabla2[Mes],0)),COSECHA[[#This Row],[Bins]]*INDEX(Tabla2[Precio Bins],MATCH(COSECHA[[#This Row],[Mes]],Tabla2[Mes],0))),0) -> 2202125.2 | M6: =+IFERROR(INDEX(Tabla2[Precio Jornal],MATCH(COSECHA[[#This Row],[Mes]],Tabla2[Mes],0))*COSECHA[[#This Row],[Jornales]],0) -> 582805.93 | N6: =+COSECHA[[#This Row],[Jornales $]]+SUM(COSECHA[[#This Row],[PA]:[EE III]]) -> 4106206.3 | O6: =+IF(COSECHA[[#This Row],[Finca]]="Puente Alto",INDEX(Tabla2[kg pa],MATCH(COSECHA[[#This Row],[Mes]],Tabla2[Mes],0))*COSECHA[[#This Row],[KG]],"") -> 3523400.4 | U6: Camino Truncado | V6: Flete Cosecha | W6: 0 | X6: 0 | Y6: 0 | Z6: 0
A7: Puente Alto | B7: Flame | C7: Tracto elevador | D7: Bins | E7: 522280 | F7: 25.955319 | G7: =+COSECHA[[#This Row],[KG]]/300 -> 435.23333 | H7: =+IFERROR(COSECHA[[#This Row],[KG uva]]/COUNTIFS(COSECHA[Finca],COSECHA[[#This Row],[Finca]],COSECHA[Variedad],COSECHA[[#This Row],[Variedad]],COSECHA[Tipo de Cosecha],COSECHA[[#This Row],[Tipo de Cosecha]]),0) -> 130570 | K7: Febrero | L7: =+IFERROR(IF(COSECHA[[#This Row],[Bins]]="",COSECHA[[#This Row],[KG]]*INDEX(Tabla2[Precio Kg Uva Carro],MATCH(COSECHA[[#This Row],[Mes]],Tabla2[Mes],0)),COSECHA[[#This Row],[Bins]]*INDEX(Tabla2[Precio Bins],MATCH(COSECHA[[#This Row],[Mes]],Tabla2[Mes],0))),0) -> 2202125.2 | M7: =+IFERROR(INDEX(Tabla2[Precio Jornal],MATCH(COSECHA[[#This Row],[Mes]],Tabla2[Mes],0))*COSECHA[[#This Row],[Jornales]],0) -> 582805.93 | N7: =+COSECHA[[#This Row],[Jornales $]]+SUM(COSECHA[[#This Row],[PA]:[EE III]]) -> 4106206.3 | O7: =+IF(COSECHA[[#This Row],[Finca]]="Puente Alto",INDEX(Tabla2[kg pa],MATCH(COSECHA[[#This Row],[Mes]],Tabla2[Mes],0))*COSECHA[[#This Row],[KG]],"") -> 3523400.4 | U7: La Chimbera | V7: Cosecha | W7: =+SUMIFS(COSECHA[Cosecha],COSECHA[Finca],$U$7,COSECHA[Mes],W$2)/W$1 -> 8107.534 | X7: =+SUMIFS(COSECHA[Cosecha],COSECHA[Finca],$U$7,COSECHA[Mes],X$2)/X$1 -> 16199.056 | Y7: =+SUMIFS(COSECHA[Cosecha],COSECHA[Finca],$U$7,COSECHA[Mes],Y$2)/Y$1 -> 10918.297 | Z7: =+SUMIFS(COSECHA[Cosecha],COSECHA[Finca],$U$7,COSECHA[Mes],Z$2)/Z$1 -> 0 | AB7: =+SUM(Cosechas[[#This Row],[Enero]:[Abril]])/40.5 -> 869.75028
A8: Puente Alto | B8: Flame | C8: Tractor con uñas | D8: Bins | E8: 522280 | F8: 25.955319 | G8: =+COSECHA[[#This Row],[KG]]/300 -> 435.23333 | H8: =+IFERROR(COSECHA[[#This Row],[KG uva]]/COUNTIFS(COSECHA[Finca],COSECHA[[#This Row],[Finca]],COSECHA[Variedad],COSECHA[[#This Row],[Variedad]],COSECHA[Tipo de Cosecha],COSECHA[[#This Row],[Tipo de Cosecha]]),0) -> 130570 | K8: Febrero | L8: =+IFERROR(IF(COSECHA[[#This Row],[Bins]]="",COSECHA[[#This Row],[KG]]*INDEX(Tabla2[Precio Kg Uva Carro],MATCH(COSECHA[[#This Row],[Mes]],Tabla2[Mes],0)),COSECHA[[#This Row],[Bins]]*INDEX(Tabla2[Precio Bins],MATCH(COSECHA[[#This Row],[Mes]],Tabla2[Mes],0))),0) -> 2202125.2 | M8: =+IFERROR(INDEX(Tabla2[Precio Jornal],MATCH(COSECHA[[#This Row],[Mes]],Tabla2[Mes],0))*COSECHA[[#This Row],[Jornales]],0) -> 582805.93 | N8: =+COSECHA[[#This Row],[Jornales $]]+SUM(COSECHA[[#This Row],[PA]:[EE III]]) -> 4106206.3 | O8: =+IF(COSECHA[[#This Row],[Finca]]="Puente Alto",INDEX(Tabla2[kg pa],MATCH(COSECHA[[#This Row],[Mes]],Tabla2[Mes],0))*COSECHA[[#This Row],[KG]],"") -> 3523400.4 | U8: La Chimbera | V8: Combustible Cosecha | W8: =+(SUMIFS(TablaGeneral[Resumen de Jornales tractoristas de Cosecha],TablaGeneral[Finca],$U$8)*10*INDEX(Tabla2[Combustible],MATCH(W$2,Tabla2[Mes],0))*0.2)/W1 -> 440.77144 | X8: =+(SUMIFS(TablaGeneral[Resumen de Jornales tractoristas de Cosecha],TablaGeneral[Finca],$U$8)*10*INDEX(Tabla2[Combustible],MATCH(X$2,Tabla2[Mes],0))*0.2)/X1 -> 440.77144 | Y8: =+(SUMIFS(TablaGeneral[Resumen de Jornales tractoristas de Cosecha],TablaGeneral[Finca],$U$8)*10*INDEX(Tabla2[Combustible],MATCH(Y$2,Tabla2[Mes],0))*0.2)/Y1 -> 440.77144 | Z8: 0 | AB8: =+SUM(Cosechas[[#This Row],[Enero]:[Abril]])/40.5 -> 32.649736
A9: Puente Alto | B9: Flame | C9: Lavar Bines | D9: Bins | E9: 522280 | F9: 11.347907 | G9: =+COSECHA[[#This Row],[KG]]/300 -> 435.23333 | H9: =+IFERROR(COSECHA[[#This Row],[KG uva]]/COUNTIFS(COSECHA[Finca],COSECHA[[#This Row],[Finca]],COSECHA[Variedad],COSECHA[[#This Row],[Variedad]],COSECHA[Tipo de Cosecha],COSECHA[[#This Row],[Tipo de Cosecha]]),0) -> 130570 | K9: Febrero | L9: =+IFERROR(IF(COSECHA[[#This Row],[Bins]]="",COSECHA[[#This Row],[KG]]*INDEX(Tabla2[Precio Kg Uva Carro],MATCH(COSECHA[[#This Row],[Mes]],Tabla2[Mes],0)),COSECHA[[#This Row],[Bins]]*INDEX(Tabla2[Precio Bins],MATCH(COSECHA[[#This Row],[Mes]],Tabla2[Mes],0))),0) -> 2202125.2 | M9: =+IFERROR(INDEX(Tabla2[Precio Jornal],MATCH(COSECHA[[#This Row],[Mes]],Tabla2[Mes],0))*COSECHA[[#This Row],[Jornales]],0) -> 254808.17 | N9: =+COSECHA[[#This Row],[Jornales $]]+SUM(COSECHA[[#This Row],[PA]:[EE III]]) -> 3778208.6 | O9: =+IF(COSECHA[[#This Row],[Finca]]="Puente Alto",INDEX(Tabla2[kg pa],MATCH(COSECHA[[#This Row],[Mes]],Tabla2[Mes],0))*COSECHA[[#This Row],[KG]],"") -> 3523400.4 | U9: La Chimbera | V9: Alquiler Maquinaria Cos | W9: 1500 | X9: =1500*0.5 -> 750 | Y9: =1500*0.5 -> 750 | Z9: 0 | AB9: =+SUM(Cosechas[[#This Row],[Enero]:[Abril]])/40.5 -> 74.074074
A10: Puente Alto | B10: Arizul | C10: Anotador | D10: Bins | E10: 209520 | F10: 12.137234 | G10: =+COSECHA[[#This Row],[KG]]/300 -> 174.6 | H10: =+IFERROR(COSECHA[[#This Row],[KG uva]]/COUNTIFS(COSECHA[Finca],COSECHA[[#This Row],[Finca]],COSECHA[Variedad],COSECHA[[#This Row],[Variedad]],COSECHA[Tipo de Cosecha],COSECHA[[#This Row],[Tipo de Cosecha]]),0) -> 52380 | K10: Marzo | L10: =+IFERROR(IF(COSECHA[[#This Row],[Bins]]="",COSECHA[[#This Row],[KG]]*INDEX(Tabla2[Precio Kg Uva Carro],MATCH(COSECHA[[#This Row],[Mes]],Tabla2[Mes],0)),COSECHA[[#This Row],[Bins]]*INDEX(Tabla2[Precio Bins],MATCH(COSECHA[[#This Row],[Mes]],Tabla2[Mes],0))),0) -> 909973.23 | M10: =+IFERROR(INDEX(Tabla2[Precio Jornal],MATCH(COSECHA[[#This Row],[Mes]],Tabla2[Mes],0))*COSECHA[[#This Row],[Jornales]],0) -> 277144.03 | N10: =+COSECHA[[#This Row],[Jornales $]]+SUM(COSECHA[[#This Row],[PA]:[EE III]]) -> 1733101.2 | O10: =+IF(COSECHA[[#This Row],[Finca]]="Puente Alto",INDEX(Tabla2[kg pa],MATCH(COSECHA[[#This Row],[Mes]],Tabla2[Mes],0))*COSECHA[[#This Row],[KG]],"") -> 1455957.2 | U10: La Chimbera | V10: Flete Cosecha | W10: =+$AC$11/3/W1 -> 719.99461 | X10: =+$AC$11/3/X1 -> 712.86595 | Y10: =+$AC$11/3/Y1 -> 705.80787 | Z10: 0 | AB10: =+SUM(Cosechas[[#This Row],[Enero]:[Abril]])/40.5 -> 52.806628
A11: Puente Alto | B11: Arizul | C11: Tracto elevador | D11: Bins | E11: 209520 | F11: 12.137234 | G11: =+COSECHA[[#This Row],[KG]]/300 -> 174.6 | H11: =+IFERROR(COSECHA[[#This Row],[KG uva]]/COUNTIFS(COSECHA[Finca],COSECHA[[#This Row],[Finca]],COSECHA[Variedad],COSECHA[[#This Row],[Variedad]],COSECHA[Tipo de Cosecha],COSECHA[[#This Row],[Tipo de Cosecha]]),0) -> 52380 | K11: Marzo | L11: =+IFERROR(IF(COSECHA[[#This Row],[Bins]]="",COSECHA[[#This Row],[KG]]*INDEX(Tabla2[Precio Kg Uva Carro],MATCH(COSECHA[[#This Row],[Mes]],Tabla2[Mes],0)),COSECHA[[#This Row],[Bins]]*INDEX(Tabla2[Precio Bins],MATCH(COSECHA[[#This Row],[Mes]],Tabla2[Mes],0))),0) -> 909973.23 | M11: =+IFERROR(INDEX(Tabla2[Precio Jornal],MATCH(COSECHA[[#This Row],[Mes]],Tabla2[Mes],0))*COSECHA[[#This Row],[Jornales]],0) -> 277144.03 | N11: =+COSECHA[[#This Row],[Jornales $]]+SUM(COSECHA[[#This Row],[PA]:[EE III]]) -> 1733101.2 | O11: =+IF(COSECHA[[#This Row],[Finca]]="Puente Alto",INDEX(Tabla2[kg pa],MATCH(COSECHA[[#This Row],[Mes]],Tabla2[Mes],0))*COSECHA[[#This Row],[KG]],"") -> 1455957.2 | U11: Puente Alto | V11: Cosecha | W11: =+SUMIFS(COSECHA[Cosecha],COSECHA[Finca],$U$11,COSECHA[Mes],W$2)/W1 -> 2762.3631 | X11: =+SUMIFS(COSECHA[Cosecha],COSECHA[Finca],$U$11,COSECHA[Mes],X$2)/X1 -> 13059.424 | Y11: =+SUMIFS(COSECHA[Cosecha],COSECHA[Finca],$U$11,COSECHA[Mes],Y$2)/Y1 -> 5443.3135 | Z11: =+SUMIFS(COSECHA[Cosecha],COSECHA[Finca],$U$11,COSECHA[Mes],Z$2) -> 0 | AB11: =+SUM(Cosechas[[#This Row],[Enero]:[Abril]])/26.18 -> 812.2651 | AC11: 2636000 | AD11: =+$AC$11/3/AD13 -> 825.03912 | AE11: =+$AC$11/3/AE13 -> 825.03912 | AF11: =+$AC$11/3/AF13 -> 795.17345
A12: Puente Alto | B12: Arizul | C12: Tractor con uñas | D12: Bins | E12: 209520 | F12: 12.137234 | G12: =+COSECHA[[#This Row],[KG]]/300 -> 174.6 | H12: =+IFERROR(COSECHA[[#This Row],[KG uva]]/COUNTIFS(COSECHA[Finca],COSECHA[[#This Row],[Finca]],COSECHA[Variedad],COSECHA[[#This Row],[Variedad]],COSECHA[Tipo de Cosecha],COSECHA[[#This Row],[Tipo de Cosecha]]),0) -> 52380 | K12: Marzo | L12: =+IFERROR(IF(COSECHA[[#This Row],[Bins]]="",COSECHA[[#This Row],[KG]]*INDEX(Tabla2[Precio Kg Uva Carro],MATCH(COSECHA[[#This Row],[Mes]],Tabla2[Mes],0)),COSECHA[[#This Row],[Bins]]*INDEX(Tabla2[Precio Bins],MATCH(COSECHA[[#This Row],[Mes]],Tabla2[Mes],0))),0) -> 909973.23 | M12: =+IFERROR(INDEX(Tabla2[Precio Jornal],MATCH(COSECHA[[#This Row],[Mes]],Tabla2[Mes],0))*COSECHA[[#This Row],[Jornales]],0) -> 277144.03 | N12: =+COSECHA[[#This Row],[Jornales $]]+SUM(COSECHA[[#This Row],[PA]:[EE III]]) -> 1733101.2 | O12: =+IF(COSECHA[[#This Row],[Finca]]="Puente Alto",INDEX(Tabla2[kg pa],MATCH(COSECHA[[#This Row],[Mes]],Tabla2[Mes],0))*COSECHA[[#This Row],[KG]],"") -> 1455957.2 | U12: Puente Alto | V12: Combustible Cosecha | W12: =+(SUMIFS(TablaGeneral[Resumen de Jornales tractoristas de Cosecha],TablaGeneral[Finca],$U$12)*10*INDEX(Tabla2[Combustible],MATCH(W$2,Tabla2[Mes],0))*0.2)/W1 -> 196.82181 | X12: =+(SUMIFS(TablaGeneral[Resumen de Jornales tractoristas de Cosecha],TablaGeneral[Finca],$U$12)*10*INDEX(Tabla2[Combustible],MATCH(X$2,Tabla2[Mes],0))*0.2)/X1 -> 196.82181 | Y12: =+(SUMIFS(TablaGeneral[Resumen de Jornales tractoristas de Cosecha],TablaGeneral[Finca],$U$12)*10*INDEX(Tabla2[Combustible],MATCH(Y$2,Tabla2[Mes],0))*0.2)/Y1 -> 196.82181 | Z12: 0 | AB12: =+SUM(Cosechas[[#This Row],[Enero]:[Abril]])/26.18 -> 22.554065
A13: Puente Alto | B13: Arizul | C13: Lavar Bines | D13: Bins | E13: 209520 | F13: 5.3065116 | G13: =+COSECHA[[#This Row],[KG]]/300 -> 174.6 | H13: =+IFERROR(COSECHA[[#This Row],[KG uva]]/COUNTIFS(COSECHA[Finca],COSECHA[[#This Row],[Finca]],COSECHA[Variedad],COSECHA[[#This Row],[Variedad]],COSECHA[Tipo de Cosecha],COSECHA[[#This Row],[Tipo de Cosecha]]),0) -> 52380 | K13: Marzo | L13: =+IFERROR(IF(COSECHA[[#This Row],[Bins]]="",COSECHA[[#This Row],[KG]]*INDEX(Tabla2[Precio Kg Uva Carro],MATCH(COSECHA[[#This Row],[Mes]],Tabla2[Mes],0)),COSECHA[[#This Row],[Bins]]*INDEX(Tabla2[Precio Bins],MATCH(COSECHA[[#This Row],[Mes]],Tabla2[Mes],0))),0) -> 909973.23 | M13: =+IFERROR(INDEX(Tabla2[Precio Jornal],MATCH(COSECHA[[#This Row],[Mes]],Tabla2[Mes],0))*COSECHA[[#This Row],[Jornales]],0) -> 121169.95 | N13: =+COSECHA[[#This Row],[Jornales $]]+SUM(COSECHA[[#This Row],[PA]:[EE III]]) -> 1577127.1 | O13: =+IF(COSECHA[[#This Row],[Finca]]="Puente Alto",INDEX(Tabla2[kg pa],MATCH(COSECHA[[#This Row],[Mes]],Tabla2[Mes],0))*COSECHA[[#This Row],[KG]],"") -> 1455957.2 | U13: Puente Alto | V13: Alquiler Maquinaria Cos | W13: =1500*0.2 -> 300 | X13: =1500*0.4 -> 600 | Y13: =1500*0.4 -> 600 | Z13: 0 | AB13: =+SUM(Cosechas[[#This Row],[Enero]:[Abril]])/26.18 -> 57.295646 | AD13: 1065 | AE13: 1065 | AF13: 1105
A14: Camino Truncado | B14: Flame | C14: Anotador | D14: Bins | E14: 366060 | F14: 9.5545476 | G14: =+COSECHA[[#This Row],[KG]]/300 -> 244.04 | H14: =+IFERROR(COSECHA[[#This Row],[KG uva]]/COUNTIFS(COSECHA[Finca],COSECHA[[#This Row],[Finca]],COSECHA[Variedad],COSECHA[[#This Row],[Variedad]],COSECHA[Tipo de Cosecha],COSECHA[[#This Row],[Tipo de Cosecha]]),0) -> 73212 | I14: 4 | K14: Febrero | L14: =+IFERROR(IF(COSECHA[[#This Row],[Bins]]="",COSECHA[[#This Row],[KG]]*INDEX(Tabla2[Precio Kg Uva Carro],MATCH(COSECHA[[#This Row],[Mes]],Tabla2[Mes],0)),COSECHA[[#This Row],[Bins]]*INDEX(Tabla2[Precio Bins],MATCH(COSECHA[[#This Row],[Mes]],Tabla2[Mes],0))),0) -> 1234755.3 | M14: =+IFERROR(INDEX(Tabla2[Precio Jornal],MATCH(COSECHA[[#This Row],[Mes]],Tabla2[Mes],0))*COSECHA[[#This Row],[Jornales]],0) -> 214539.72 | N14: =+COSECHA[[#This Row],[Jornales $]]+SUM(COSECHA[[#This Row],[PA]:[EE III]]) -> 2190148.1 | O14: =+IF(COSECHA[[#This Row],[Finca]]="Puente Alto",INDEX(Tabla2[kg pa],MATCH(COSECHA[[#This Row],[Mes]],Tabla2[Mes],0))*COSECHA[[#This Row],[KG]],"") | P14: =+INDEX(Tabla2[kg pa],MATCH(COSECHA[[#This Row],[Mes]],Tabla2[Mes],0))*COSECHA[[#This Row],[KG]] -> 1975608.4 | U14: Puente Alto | V14: Flete Cosecha | W14: 3104.8513 | X14: 3104.8513 | Y14: 2992.4585 | Z14: 0 | AB14: =+SUM(Cosechas[[#This Row],[Enero]:[Abril]])/26.18 -> 351.49584 | AC14: 9920000 | AD14: =+$AC$14/3/AD13 -> 3104.8513 | AE14: =+$AC$14/3/AE13 -> 3104.8513 | AF14: =+$AC$14/3/AF13 -> 2992.4585
A15: Camino Truncado | B15: Flame | C15: Tracto elevador | D15: Bins | E15: 366060 | F15: 9.5545476 | G15: =+COSECHA[[#This Row],[KG]]/300 -> 244.04 | H15: =+IFERROR(COSECHA[[#This Row],[KG uva]]/COUNTIFS(COSECHA[Finca],COSECHA[[#This Row],[Finca]],COSECHA[Variedad],COSECHA[[#This Row],[Variedad]],COSECHA[Tipo de Cosecha],COSECHA[[#This Row],[Tipo de Cosecha]]),0) -> 73212 | I15: 4 | K15: Febrero | L15: =+IFERROR(IF(COSECHA[[#This Row],[Bins]]="",COSECHA[[#This Row],[KG]]*INDEX(Tabla2[Precio Kg Uva Carro],MATCH(COSECHA[[#This Row],[Mes]],Tabla2[Mes],0)),COSECHA[[#This Row],[Bins]]*INDEX(Tabla2[Precio Bins],MATCH(COSECHA[[#This Row],[Mes]],Tabla2[Mes],0))),0) -> 1234755.3 | M15: =+IFERROR(INDEX(Tabla2[Precio Jornal],MATCH(COSECHA[[#This Row],[Mes]],Tabla2[Mes],0))*COSECHA[[#This Row],[Jornales]],0) -> 214539.72 | N15: =+COSECHA[[#This Row],[Jornales $]]+SUM(COSECHA[[#This Row],[PA]:[EE III]]) -> 2190148.1 | O15: =+IF(COSECHA[[#This Row],[Finca]]="Puente Alto",INDEX(Tabla2[kg pa],MATCH(COSECHA[[#This Row],[Mes]],Tabla2[Mes],0))*COSECHA[[#This Row],[KG]],"") | P15: =+INDEX(Tabla2[kg pa],MATCH(COSECHA[[#This Row],[Mes]],Tabla2[Mes],0))*COSECHA[[#This Row],[KG]] -> 1975608.4 | U15: El Espejo I y II | V15: Cosecha | W15: =+SUMIFS(COSECHA[Cosecha],COSECHA[Finca],"El Espejo I",COSECHA[Mes],W$2)+SUMIFS(COSECHA[Cosecha],COSECHA[Finca],"El Espejo II",COSECHA[Mes],W$2)/W1 -> 0 | X15: =+(SUMIFS(COSECHA[Cosecha],COSECHA[Finca],"El Espejo I",COSECHA[Mes],X$2)+SUMIFS(COSECHA[Cosecha],COSECHA[Finca],"El Espejo II",COSECHA[Mes],X$2))/X1 -> 34680.599 | Y15: =+(SUMIFS(COSECHA[Cosecha],COSECHA[Finca],"El Espejo I",COSECHA[Mes],Y$2)+SUMIFS(COSECHA[Cosecha],COSECHA[Finca],"El Espejo II",COSECHA[Mes],Y$2))/Y1 -> 27783.56 | Z15: =+SUMIFS(COSECHA[Cosecha],COSECHA[Finca],$U$3,COSECHA[Mes],Z$2) -> 0 | AB15: =+SUM(Cosechas[[#This Row],[Enero]:[Abril]])/55.89 -> 1117.6268
A16: Camino Truncado | B16: Flame | C16: Tractor con uñas | D16: Bins | E16: 366060 | F16: 38.21819 | G16: =+COSECHA[[#This Row],[KG]]/300 -> 244.04 | H16: =+IFERROR(COSECHA[[#This Row],[KG uva]]/COUNTIFS(COSECHA[Finca],COSECHA[[#This Row],[Finca]],COSECHA[Variedad],COSECHA[[#This Row],[Variedad]],COSECHA[Tipo de Cosecha],COSECHA[[#This Row],[Tipo de Cosecha]]),0) -> 73212 | I16: 4 | K16: Febrero | L16: =+IFERROR(IF(COSECHA[[#This Row],[Bins]]="",COSECHA[[#This Row],[KG]]*INDEX(Tabla2[Precio Kg Uva Carro],MATCH(COSECHA[[#This Row],[Mes]],Tabla2[Mes],0)),COSECHA[[#This Row],[Bins]]*INDEX(Tabla2[Precio Bins],MATCH(COSECHA[[#This Row],[Mes]],Tabla2[Mes],0))),0) -> 1234755.3 | M16: =+IFERROR(INDEX(Tabla2[Precio Jornal],MATCH(COSECHA[[#This Row],[Mes]],Tabla2[Mes],0))*COSECHA[[#This Row],[Jornales]],0) -> 858158.89 | N16: =+COSECHA[[#This Row],[Jornales $]]+SUM(COSECHA[[#This Row],[PA]:[EE III]]) -> 2833767.3 | O16: =+IF(COSECHA[[#This Row],[Finca]]="Puente Alto",INDEX(Tabla2[kg pa],MATCH(COSECHA[[#This Row],[Mes]],Tabla2[Mes],0))*COSECHA[[#This Row],[KG]],"") | P16: =+INDEX(Tabla2[kg pa],MATCH(COSECHA[[#This Row],[Mes]],Tabla2[Mes],0))*COSECHA[[#This Row],[KG]] -> 1975608.4 | U16: El Espejo I y II | V16: Combustible Cosecha | W16: =+((SUMIFS(TablaGeneral[Resumen de Jornales tractoristas de Cosecha],TablaGeneral[Finca],"El Espejo I")*10*INDEX(Tabla2[Combustible],MATCH(W$2,Tabla2[Mes],0))*0.2/W1)+(SUMIFS(TablaGeneral[Resumen de Jornales tractoristas de Cosecha],TablaGeneral[Finca],"El Espejo II")*10*INDEX(Tabla2[Combustible],MATCH(W$2,Tabla2[Mes],0))*0.2))/W1 -> 337.12014 | X16: =+((SUMIFS(TablaGeneral[Resumen de Jornales tractoristas de Cosecha],TablaGeneral[Finca],"El Espejo I")*10*INDEX(Tabla2[Combustible],MATCH(X$2,Tabla2[Mes],0))*0.2/X1)+(SUMIFS(TablaGeneral[Resumen de Jornales tractoristas de Cosecha],TablaGeneral[Finca],"El Espejo II")*10*INDEX(Tabla2[Combustible],MATCH(X$2,Tabla2[Mes],0))*0.2))/X1 -> 337.11734 | Y16: =+((SUMIFS(TablaGeneral[Resumen de Jornales tractoristas de Cosecha],TablaGeneral[Finca],"El Espejo I")*10*INDEX(Tabla2[Combustible],MATCH(Y$2,Tabla2[Mes],0))*0.2/Y1)+(SUMIFS(TablaGeneral[Resumen de Jornales tractoristas de Cosecha],TablaGeneral[Finca],"El Espejo II")*10*INDEX(Tabla2[Combustible],MATCH(Y$2,Tabla2[Mes],0))*0.2))/Y1 -> 337.11456 | Z16: 0 | AB16: =+SUM(Cosechas[[#This Row],[Enero]:[Abril]])/55.89 -> 18.095402 | AD16: =+W14/SUM(W14:Y14) -> 0.33740458 | AE16: =+X14/SUM(W14:Y14) -> 0.33740458 | AF16: =+Y14/SUM(W14:Y14) -> 0.32519084
A17: Camino Truncado | B17: Flame | C17: Lavar Bines | D17: Bins | E17: 366060 | F17: 3.821819 | G17: =+COSECHA[[#This Row],[KG]]/300 -> 244.04 | H17: =+IFERROR(COSECHA[[#This Row],[KG uva]]/COUNTIFS(COSECHA[Finca],COSECHA[[#This Row],[Finca]],COSECHA[Variedad],COSECHA[[#This Row],[Variedad]],COSECHA[Tipo de Cosecha],COSECHA[[#This Row],[Tipo de Cosecha]]),0) -> 73212 | I17: 4 | K17: Febrero | L17: =+IFERROR(IF(COSECHA[[#This Row],[Bins]]="",COSECHA[[#This Row],[KG]]*INDEX(Tabla2[Precio Kg Uva Carro],MATCH(COSECHA[[#This Row],[Mes]],Tabla2[Mes],0)),COSECHA[[#This Row],[Bins]]*INDEX(Tabla2[Precio Bins],MATCH(COSECHA[[#This Row],[Mes]],Tabla2[Mes],0))),0) -> 1234755.3 | M17: =+IFERROR(INDEX(Tabla2[Precio Jornal],MATCH(COSECHA[[#This Row],[Mes]],Tabla2[Mes],0))*COSECHA[[#This Row],[Jornales]],0) -> 85815.889 | N17: =+COSECHA[[#This Row],[Jornales $]]+SUM(COSECHA[[#This Row],[PA]:[EE III]]) -> 2061424.3 | O17: =+IF(COSECHA[[#This Row],[Finca]]="Puente Alto",INDEX(Tabla2[kg pa],MATCH(COSECHA[[#This Row],[Mes]],Tabla2[Mes],0))*COSECHA[[#This Row],[KG]],"") | P17: =+INDEX(Tabla2[kg pa],MATCH(COSECHA[[#This Row],[Mes]],Tabla2[Mes],0))*COSECHA[[#This Row],[KG]] -> 1975608.4 | U17: El Espejo I y II | V17: Alquiler Maquinaria Cos | W17: 0 | X17: 0 | Y17: 0 | Z17: 0 | AB17: =+SUM(Cosechas[[#This Row],[Enero]:[Abril]])/55.89 -> 0 | AD17: =831760/300/16 -> 173.28333
A18: Camino Truncado | B18: Flame | C18: Tractor con acoplado | D18: Bins | E18: 366060 | F18: 19.109095 | G18: =+COSECHA[[#This Row],[KG]]/300 -> 244.04 | H18: =+IFERROR(COSECHA[[#This Row],[KG uva]]/COUNTIFS(COSECHA[Finca],COSECHA[[#This Row],[Finca]],COSECHA[Variedad],COSECHA[[#This Row],[Variedad]],COSECHA[Tipo de Cosecha],COSECHA[[#This Row],[Tipo de Cosecha]]),0) -> 73212 | I18: 4 | K18: Febrero | L18: =+IFERROR(IF(COSECHA[[#This Row],[Bins]]="",COSECHA[[#This Row],[KG]]*INDEX(Tabla2[Precio Kg Uva Carro],MATCH(COSECHA[[#This Row],[Mes]],Tabla2[Mes],0)),COSECHA[[#This Row],[Bins]]*INDEX(Tabla2[Precio Bins],MATCH(COSECHA[[#This Row],[Mes]],Tabla2[Mes],0))),0) -> 1234755.3 | M18: =+IFERROR(INDEX(Tabla2[Precio Jornal],MATCH(COSECHA[[#This Row],[Mes]],Tabla2[Mes],0))*COSECHA[[#This Row],[Jornales]],0) -> 429079.45 | N18: =+COSECHA[[#This Row],[Jornales $]]+SUM(COSECHA[[#This Row],[PA]:[EE III]]) -> 2404687.8 | O18: =+IF(COSECHA[[#This Row],[Finca]]="Puente Alto",INDEX(Tabla2[kg pa],MATCH(COSECHA[[#This Row],[Mes]],Tabla2[Mes],0))*COSECHA[[#This Row],[KG]],"") | P18: =+INDEX(Tabla2[kg pa],MATCH(COSECHA[[#This Row],[Mes]],Tabla2[Mes],0))*COSECHA[[#This Row],[KG]] -> 1975608.4 | U18: El Espejo I y II | V18: Flete Cosecha | W18: 0 | X18: 0 | Y18: 0 | Z18: 0 | AB18: =+SUM(Cosechas[[#This Row],[Enero]:[Abril]])/55.89 -> 0 | AD18: =64000*AD17 -> 11090133
A19: Camino Truncado | B19: Arizul | C19: Anotador | D19: Bins | E19: 347400 | F19: 10.969382 | G19: =+COSECHA[[#This Row],[KG]]/300 -> 231.6 | H19: =+IFERROR(COSECHA[[#This Row],[KG uva]]/COUNTIFS(COSECHA[Finca],COSECHA[[#This Row],[Finca]],COSECHA[Variedad],COSECHA[[#This Row],[Variedad]],COSECHA[Tipo de Cosecha],COSECHA[[#This Row],[Tipo de Cosecha]]),0) -> 69480 | I19: 3 | K19: Marzo | L19: =+IFERROR(IF(COSECHA[[#This Row],[Bins]]="",COSECHA[[#This Row],[KG]]*INDEX(Tabla2[Precio Kg Uva Carro],MATCH(COSECHA[[#This Row],[Mes]],Tabla2[Mes],0)),COSECHA[[#This Row],[Bins]]*INDEX(Tabla2[Precio Bins],MATCH(COSECHA[[#This Row],[Mes]],Tabla2[Mes],0))),0) -> 1207043.5 | M19: =+IFERROR(INDEX(Tabla2[Precio Jornal],MATCH(COSECHA[[#This Row],[Mes]],Tabla2[Mes],0))*COSECHA[[#This Row],[Jornales]],0) -> 250477.07 | N19: =+COSECHA[[#This Row],[Jornales $]]+SUM(COSECHA[[#This Row],[PA]:[EE III]]) -> 2181746.7 | O19: =+IF(COSECHA[[#This Row],[Finca]]="Puente Alto",INDEX(Tabla2[kg pa],MATCH(COSECHA[[#This Row],[Mes]],Tabla2[Mes],0))*COSECHA[[#This Row],[KG]],"") | P19: =+INDEX(Tabla2[kg pa],MATCH(COSECHA[[#This Row],[Mes]],Tabla2[Mes],0))*COSECHA[[#This Row],[KG]] -> 1931269.6 | U19: El Espejo III | V19: Cosecha | W19: =+SUMIFS(COSECHA[Cosecha],COSECHA[Finca],"El Espejo III",COSECHA[Mes],W$2)/W1 -> 26098.24 | X19: =+SUMIFS(COSECHA[Cosecha],COSECHA[Finca],"El Espejo III",COSECHA[Mes],X$2)/X1 -> 12165.5 | Y19: =+SUMIFS(COSECHA[Cosecha],COSECHA[Finca],"El Espejo III",COSECHA[Mes],Y$2)/Y1 -> 0 | Z19: 0 | AB19: =+SUM(Cosechas[[#This Row],[Enero]:[Abril]])/63.7 -> 600.68666 | AD19: =+$AD$18*AD16 -> 3741861.8 | AE19: =+$AD$18*AE16 -> 3741861.8 | AF19: =+$AD$18*AF16 -> 3606409.8
A20: Camino Truncado | B20: Arizul | C20: Tracto elevador | D20: Bins | E20: 347400 | F20: 10.969382 | G20: =+COSECHA[[#This Row],[KG]]/300 -> 231.6 | H20: =+IFERROR(COSECHA[[#This Row],[KG uva]]/COUNTIFS(COSECHA[Finca],COSECHA[[#This Row],[Finca]],COSECHA[Variedad],COSECHA[[#This Row],[Variedad]],COSECHA[Tipo de Cosecha],COSECHA[[#This Row],[Tipo de Cosecha]]),0) -> 69480 | I20: 3 | K20: Marzo | L20: =+IFERROR(IF(COSECHA[[#This Row],[Bins]]="",COSECHA[[#This Row],[KG]]*INDEX(Tabla2[Precio Kg Uva Carro],MATCH(COSECHA[[#This Row],[Mes]],Tabla2[Mes],0)),COSECHA[[#This Row],[Bins]]*INDEX(Tabla2[Precio Bins],MATCH(COSECHA[[#This Row],[Mes]],Tabla2[Mes],0))),0) -> 1207043.5 | M20: =+IFERROR(INDEX(Tabla2[Precio Jornal],MATCH(COSECHA[[#This Row],[Mes]],Tabla2[Mes],0))*COSECHA[[#This Row],[Jornales]],0) -> 250477.07 | N20: =+COSECHA[[#This Row],[Jornales $]]+SUM(COSECHA[[#This Row],[PA]:[EE III]]) -> 2181746.7 | O20: =+IF(COSECHA[[#This Row],[Finca]]="Puente Alto",INDEX(Tabla2[kg pa],MATCH(COSECHA[[#This Row],[Mes]],Tabla2[Mes],0))*COSECHA[[#This Row],[KG]],"") | P20: =+INDEX(Tabla2[kg pa],MATCH(COSECHA[[#This Row],[Mes]],Tabla2[Mes],0))*COSECHA[[#This Row],[KG]] -> 1931269.6 | U20: El Espejo III | V20: Combustible Cosecha | W20: =+(SUMIFS(TablaGeneral[Resumen de Jornales tractoristas de Cosecha],TablaGeneral[Finca],"El Espejo III")*10*INDEX(Tabla2[Combustible],MATCH(W$2,Tabla2[Mes],0))*0.2)/W1 -> 332.10264 | X20: =+(SUMIFS(TablaGeneral[Resumen de Jornales tractoristas de Cosecha],TablaGeneral[Finca],"El Espejo III")*10*INDEX(Tabla2[Combustible],MATCH(X$2,Tabla2[Mes],0))*0.2)/X1 -> 332.10264 | Y20: =+(SUMIFS(TablaGeneral[Resumen de Jornales tractoristas de Cosecha],TablaGeneral[Finca],"El Espejo III")*10*INDEX(Tabla2[Combustible],MATCH(Y$2,Tabla2[Mes],0))*0.2)/Y1 -> 332.10264 | Z20: 0 | AB20: =+SUM(Cosechas[[#This Row],[Enero]:[Abril]])/63.7 -> 15.640627 | AD20: =+AD19/W1 -> 3066.146 | AE20: =+AE19/X1 -> 3035.7881 | AF20: =+AF19/Y1 -> 2896.9261
A21: Camino Truncado | B21: Arizul | C21: Tractor con uñas | D21: Bins | E21: 347400 | F21: 43.87749 | G21: =+COSECHA[[#This Row],[KG]]/300 -> 231.6 | H21: =+IFERROR(COSECHA[[#This Row],[KG uva]]/COUNTIFS(COSECHA[Finca],COSECHA[[#This Row],[Finca]],COSECHA[Variedad],COSECHA[[#This Row],[Variedad]],COSECHA[Tipo de Cosecha],COSECHA[[#This Row],[Tipo de Cosecha]]),0) -> 69480 | I21: 3 | K21: Marzo | L21: =+IFERROR(IF(COSECHA[[#This Row],[Bins]]="",COSECHA[[#This Row],[KG]]*INDEX(Tabla2[Precio Kg Uva Carro],MATCH(COSECHA[[#This Row],[Mes]],Tabla2[Mes],0)),COSECHA[[#This Row],[Bins]]*INDEX(Tabla2[Precio Bins],MATCH(COSECHA[[#This Row],[Mes]],Tabla2[Mes],0))),0) -> 1207043.5 | M21: =+IFERROR(INDEX(Tabla2[Precio Jornal],MATCH(COSECHA[[#This Row],[Mes]],Tabla2[Mes],0))*COSECHA[[#This Row],[Jornales]],0) -> 1001907.4 | N21: =+COSECHA[[#This Row],[Jornales $]]+SUM(COSECHA[[#This Row],[PA]:[EE III]]) -> 2933177 | O21: =+IF(COSECHA[[#This Row],[Finca]]="Puente Alto",INDEX(Tabla2[kg pa],MATCH(COSECHA[[#This Row],[Mes]],Tabla2[Mes],0))*COSECHA[[#This Row],[KG]],"") | P21: =+INDEX(Tabla2[kg pa],MATCH(COSECHA[[#This Row],[Mes]],Tabla2[Mes],0))*COSECHA[[#This Row],[KG]] -> 1931269.6 | U21: El Espejo III | V21: Alquiler Maquinaria Cos | W21: 0 | X21: 0 | Y21: 0 | Z21: 0 | AB21: =+SUM(Cosechas[[#This Row],[Enero]:[Abril]])/63.7 -> 0
A22: Camino Truncado | B22: Arizul | C22: Lavar Bines | D22: Bins | E22: 347400 | F22: 4.387749 | G22: =+COSECHA[[#This Row],[KG]]/300 -> 231.6 | H22: =+IFERROR(COSECHA[[#This Row],[KG uva]]/COUNTIFS(COSECHA[Finca],COSECHA[[#This Row],[Finca]],COSECHA[Variedad],COSECHA[[#This Row],[Variedad]],COSECHA[Tipo de Cosecha],COSECHA[[#This Row],[Tipo de Cosecha]]),0) -> 69480 | I22: 3 | K22: Marzo | L22: =+IFERROR(IF(COSECHA[[#This Row],[Bins]]="",COSECHA[[#This Row],[KG]]*INDEX(Tabla2[Precio Kg Uva Carro],MATCH(COSECHA[[#This Row],[Mes]],Tabla2[Mes],0)),COSECHA[[#This Row],[Bins]]*INDEX(Tabla2[Precio Bins],MATCH(COSECHA[[#This Row],[Mes]],Tabla2[Mes],0))),0) -> 1207043.5 | M22: =+IFERROR(INDEX(Tabla2[Precio Jornal],MATCH(COSECHA[[#This Row],[Mes]],Tabla2[Mes],0))*COSECHA[[#This Row],[Jornales]],0) -> 100190.74 | N22: =+COSECHA[[#This Row],[Jornales $]]+SUM(COSECHA[[#This Row],[PA]:[EE III]]) -> 2031460.4 | O22: =+IF(COSECHA[[#This Row],[Finca]]="Puente Alto",INDEX(Tabla2[kg pa],MATCH(COSECHA[[#This Row],[Mes]],Tabla2[Mes],0))*COSECHA[[#This Row],[KG]],"") | P22: =+INDEX(Tabla2[kg pa],MATCH(COSECHA[[#This Row],[Mes]],Tabla2[Mes],0))*COSECHA[[#This Row],[KG]] -> 1931269.6 | U22: El Espejo III | V22: Flete Cosecha | W22: 0 | X22: 0 | Y22: 0 | Z22: 0 | AB22: =+SUM(Cosechas[[#This Row],[Enero]:[Abril]])/63.7 -> 0
A23: Camino Truncado | B23: Arizul | C23: Tractor con acoplado | D23: Bins | E23: 347400 | F23: 21.938667 | G23: =+COSECHA[[#This Row],[KG]]/300 -> 231.6 | H23: =+IFERROR(COSECHA[[#This Row],[KG uva]]/COUNTIFS(COSECHA[Finca],COSECHA[[#This Row],[Finca]],COSECHA[Variedad],COSECHA[[#This Row],[Variedad]],COSECHA[Tipo de Cosecha],COSECHA[[#This Row],[Tipo de Cosecha]]),0) -> 69480 | I23: 3 | K23: Marzo | L23: =+IFERROR(IF(COSECHA[[#This Row],[Bins]]="",COSECHA[[#This Row],[KG]]*INDEX(Tabla2[Precio Kg Uva Carro],MATCH(COSECHA[[#This Row],[Mes]],Tabla2[Mes],0)),COSECHA[[#This Row],[Bins]]*INDEX(Tabla2[Precio Bins],MATCH(COSECHA[[#This Row],[Mes]],Tabla2[Mes],0))),0) -> 1207043.5 | M23: =+IFERROR(INDEX(Tabla2[Precio Jornal],MATCH(COSECHA[[#This Row],[Mes]],Tabla2[Mes],0))*COSECHA[[#This Row],[Jornales]],0) -> 500951.92 | N23: =+COSECHA[[#This Row],[Jornales $]]+SUM(COSECHA[[#This Row],[PA]:[EE III]]) -> 2432221.6 | O23: =+IF(COSECHA[[#This Row],[Finca]]="Puente Alto",INDEX(Tabla2[kg pa],MATCH(COSECHA[[#This Row],[Mes]],Tabla2[Mes],0))*COSECHA[[#This Row],[KG]],"") | P23: =+INDEX(Tabla2[kg pa],MATCH(COSECHA[[#This Row],[Mes]],Tabla2[Mes],0))*COSECHA[[#This Row],[KG]] -> 1931269.6
A24: Camino Truncado | B24: Sultanina | C24: Anotador | D24: Carro | E24: 86700 | F24: 3.9250418 | H24: =+IFERROR(COSECHA[[#This Row],[KG uva]]/COUNTIFS(COSECHA[Finca],COSECHA[[#This Row],[Finca]],COSECHA[Variedad],COSECHA[[#This Row],[Variedad]],COSECHA[Tipo de Cosecha],COSECHA[[#This Row],[Tipo de Cosecha]]),0) -> 17340 | J24: =+COSECHA[[#This Row],[KG]]/1625 -> 10.670769 | K24: Febrero | L24: =+IFERROR(IF(COSECHA[[#This Row],[Bins]]="",COSECHA[[#This Row],[KG]]*INDEX(Tabla2[Precio Kg Uva Carro],MATCH(COSECHA[[#This Row],[Mes]],Tabla2[Mes],0)),COSECHA[[#This Row],[Bins]]*INDEX(Tabla2[Precio Bins],MATCH(COSECHA[[#This Row],[Mes]],Tabla2[Mes],0))),0) -> 421124.2 | M24: =+IFERROR(INDEX(Tabla2[Precio Jornal],MATCH(COSECHA[[#This Row],[Mes]],Tabla2[Mes],0))*COSECHA[[#This Row],[Jornales]],0) -> 88133.673 | N24: =+COSECHA[[#This Row],[Jornales $]]+SUM(COSECHA[[#This Row],[PA]:[EE III]]) -> 509257.87 | O24: =+IF(COSECHA[[#This Row],[Finca]]="Puente Alto",INDEX(Tabla2[kg pa],MATCH(COSECHA[[#This Row],[Mes]],Tabla2[Mes],0))*COSECHA[[#This Row],[KG]],"") | P24: =+IF(COSECHA[[#This Row],[Tipo de Cosecha]]="Carro",INDEX(Tabla2[Precio Kg Uva Carro],MATCH(COSECHA[[#This Row],[Mes]],Tabla2[Mes],0)),"")*COSECHA[[#This Row],[KG]] -> 421124.2
A25: Camino Truncado | B25: Sultanina | C25: Tracto elevador | D25: Carro | E25: 86700 | F25: 3.9250418 | H25: =+IFERROR(COSECHA[[#This Row],[KG uva]]/COUNTIFS(COSECHA[Finca],COSECHA[[#This Row],[Finca]],COSECHA[Variedad],COSECHA[[#This Row],[Variedad]],COSECHA[Tipo de Cosecha],COSECHA[[#This Row],[Tipo de Cosecha]]),0) -> 17340 | J25: =+COSECHA[[#This Row],[KG]]/1625 -> 10.670769 | K25: Febrero | L25: =+IFERROR(IF(COSECHA[[#This Row],[Bins]]="",COSECHA[[#This Row],[KG]]*INDEX(Tabla2[Precio Kg Uva Carro],MATCH(COSECHA[[#This Row],[Mes]],Tabla2[Mes],0)),COSECHA[[#This Row],[Bins]]*INDEX(Tabla2[Precio Bins],MATCH(COSECHA[[#This Row],[Mes]],Tabla2[Mes],0))),0) -> 421124.2 | M25: =+IFERROR(INDEX(Tabla2[Precio Jornal],MATCH(COSECHA[[#This Row],[Mes]],Tabla2[Mes],0))*COSECHA[[#This Row],[Jornales]],0) -> 88133.673 | N25: =+COSECHA[[#This Row],[Jornales $]]+SUM(COSECHA[[#This Row],[PA]:[EE III]]) -> 509257.87 | O25: =+IF(COSECHA[[#This Row],[Finca]]="Puente Alto",INDEX(Tabla2[kg pa],MATCH(COSECHA[[#This Row],[Mes]],Tabla2[Mes],0))*COSECHA[[#This Row],[KG]],"") | P25: =+IF(COSECHA[[#This Row],[Tipo de Cosecha]]="Carro",INDEX(Tabla2[Precio Kg Uva Carro],MATCH(COSECHA[[#This Row],[Mes]],Tabla2[Mes],0)),"")*COSECHA[[#This Row],[KG]] -> 421124.2
A26: Camino Truncado | B26: Sultanina | C26: Tractor con uñas | D26: Carro | E26: 86700 | F26: 15.700167 | H26: =+IFERROR(COSECHA[[#This Row],[KG uva]]/COUNTIFS(COSECHA[Finca],COSECHA[[#This Row],[Finca]],COSECHA[Variedad],COSECHA[[#This Row],[Variedad]],COSECHA[Tipo de Cosecha],COSECHA[[#This Row],[Tipo de Cosecha]]),0) -> 17340 | J26: =+COSECHA[[#This Row],[KG]]/1625 -> 10.670769 | K26: Febrero | L26: =+IFERROR(IF(COSECHA[[#This Row],[Bins]]="",COSECHA[[#This Row],[KG]]*INDEX(Tabla2[Precio Kg Uva Carro],MATCH(COSECHA[[#This Row],[Mes]],Tabla2[Mes],0)),COSECHA[[#This Row],[Bins]]*INDEX(Tabla2[Precio Bins],MATCH(COSECHA[[#This Row],[Mes]],Tabla2[Mes],0))),0) -> 421124.2 | M26: =+IFERROR(INDEX(Tabla2[Precio Jornal],MATCH(COSECHA[[#This Row],[Mes]],Tabla2[Mes],0))*COSECHA[[#This Row],[Jornales]],0) -> 352534.69 | N26: =+COSECHA[[#This Row],[Jornales $]]+SUM(COSECHA[[#This Row],[PA]:[EE III]]) -> 773658.89 | O26: =+IF(COSECHA[[#This Row],[Finca]]="Puente Alto",INDEX(Tabla2[kg pa],MATCH(COSECHA[[#This Row],[Mes]],Tabla2[Mes],0))*COSECHA[[#This Row],[KG]],"") | P26: =+IF(COSECHA[[#This Row],[Tipo de Cosecha]]="Carro",INDEX(Tabla2[Precio Kg Uva Carro],MATCH(COSECHA[[#This Row],[Mes]],Tabla2[Mes],0)),"")*COSECHA[[#This Row],[KG]] -> 421124.2
A27: Camino Truncado | B27: Sultanina | C27: Lavar Bines | D27: Carro | E27: 86700 | F27: 1.5700167 | H27: =+IFERROR(COSECHA[[#This Row],[KG uva]]/COUNTIFS(COSECHA[Finca],COSECHA[[#This Row],[Finca]],COSECHA[Variedad],COSECHA[[#This Row],[Variedad]],COSECHA[Tipo de Cosecha],COSECHA[[#This Row],[Tipo de Cosecha]]),0) -> 17340 | J27: =+COSECHA[[#This Row],[KG]]/1625 -> 10.670769 | K27: Febrero | L27: =+IFERROR(IF(COSECHA[[#This Row],[Bins]]="",COSECHA[[#This Row],[KG]]*INDEX(Tabla2[Precio Kg Uva Carro],MATCH(COSECHA[[#This Row],[Mes]],Tabla2[Mes],0)),COSECHA[[#This Row],[Bins]]*INDEX(Tabla2[Precio Bins],MATCH(COSECHA[[#This Row],[Mes]],Tabla2[Mes],0))),0) -> 421124.2 | M27: =+IFERROR(INDEX(Tabla2[Precio Jornal],MATCH(COSECHA[[#This Row],[Mes]],Tabla2[Mes],0))*COSECHA[[#This Row],[Jornales]],0) -> 35253.469 | N27: =+COSECHA[[#This Row],[Jornales $]]+SUM(COSECHA[[#This Row],[PA]:[EE III]]) -> 456377.67 | O27: =+IF(COSECHA[[#This Row],[Finca]]="Puente Alto",INDEX(Tabla2[kg pa],MATCH(COSECHA[[#This Row],[Mes]],Tabla2[Mes],0))*COSECHA[[#This Row],[KG]],"") | P27: =+IF(COSECHA[[#This Row],[Tipo de Cosecha]]="Carro",INDEX(Tabla2[Precio Kg Uva Carro],MATCH(COSECHA[[#This Row],[Mes]],Tabla2[Mes],0)),"")*COSECHA[[#This Row],[KG]] -> 421124.2
A28: Camino Truncado | B28: Sultanina | C28: Tractor con acoplado | D28: Carro | E28: 86700 | F28: 7.8500836 | H28: =+IFERROR(COSECHA[[#This Row],[KG uva]]/COUNTIFS(COSECHA[Finca],COSECHA[[#This Row],[Finca]],COSECHA[Variedad],COSECHA[[#This Row],[Variedad]],COSECHA[Tipo de Cosecha],COSECHA[[#This Row],[Tipo de Cosecha]]),0) -> 17340 | J28: =+COSECHA[[#This Row],[KG]]/1625 -> 10.670769 | K28: Febrero | L28: =+IFERROR(IF(COSECHA[[#This Row],[Bins]]="",COSECHA[[#This Row],[KG]]*INDEX(Tabla2[Precio Kg Uva Carro],MATCH(COSECHA[[#This Row],[Mes]],Tabla2[Mes],0)),COSECHA[[#This Row],[Bins]]*INDEX(Tabla2[Precio Bins],MATCH(COSECHA[[#This Row],[Mes]],Tabla2[Mes],0))),0) -> 421124.2 | M28: =+IFERROR(INDEX(Tabla2[Precio Jornal],MATCH(COSECHA[[#This Row],[Mes]],Tabla2[Mes],0))*COSECHA[[#This Row],[Jornales]],0) -> 176267.35 | N28: =+COSECHA[[#This Row],[Jornales $]]+SUM(COSECHA[[#This Row],[PA]:[EE III]]) -> 597391.54 | O28: =+IF(COSECHA[[#This Row],[Finca]]="Puente Alto",INDEX(Tabla2[kg pa],MATCH(COSECHA[[#This Row],[Mes]],Tabla2[Mes],0))*COSECHA[[#This Row],[KG]],"") | P28: =+IF(COSECHA[[#This Row],[Tipo de Cosecha]]="Carro",INDEX(Tabla2[Precio Kg Uva Carro],MATCH(COSECHA[[#This Row],[Mes]],Tabla2[Mes],0)),"")*COSECHA[[#This Row],[KG]] -> 421124.2
A29: Camino Truncado | B29: Fiesta | C29: Anotador | D29: Carro | E29: 555850 | F29: 6.9123473 | H29: =+IFERROR(COSECHA[[#This Row],[KG uva]]/COUNTIFS(COSECHA[Finca],COSECHA[[#This Row],[Finca]],COSECHA[Variedad],COSECHA[[#This Row],[Variedad]],COSECHA[Tipo de Cosecha],COSECHA[[#This Row],[Tipo de Cosecha]]),0) -> 111170 | J29: =+COSECHA[[#This Row],[KG]]/1625 -> 68.412308 | K29: Enero | L29: =+IFERROR(IF(COSECHA[[#This Row],[Bins]]="",COSECHA[[#This Row],[KG]]*INDEX(Tabla2[Precio Kg Uva Carro],MATCH(COSECHA[[#This Row],[Mes]],Tabla2[Mes],0)),COSECHA[[#This Row],[Bins]]*INDEX(Tabla2[Precio Bins],MATCH(COSECHA[[#This Row],[Mes]],Tabla2[Mes],0))),0) -> 2621388.6 | M29: =+IFERROR(INDEX(Tabla2[Precio Jornal],MATCH(COSECHA[[#This Row],[Mes]],Tabla2[Mes],0))*COSECHA[[#This Row],[Jornales]],0) -> 152650.2 | N29: =+COSECHA[[#This Row],[Jornales $]]+SUM(COSECHA[[#This Row],[PA]:[EE III]]) -> 2774038.8 | O29: =+IF(COSECHA[[#This Row],[Finca]]="Puente Alto",INDEX(Tabla2[kg pa],MATCH(COSECHA[[#This Row],[Mes]],Tabla2[Mes],0))*COSECHA[[#This Row],[KG]],"") | P29: =+IF(COSECHA[[#This Row],[Tipo de Cosecha]]="Carro",INDEX(Tabla2[Precio Kg Uva Carro],MATCH(COSECHA[[#This Row],[Mes]],Tabla2[Mes],0)),"")*COSECHA[[#This Row],[KG]] -> 2621388.6
A30: Camino Truncado | B30: Fiesta | C30: Tracto elevador | D30: Carro | E30: 555850 | F30: 6.9123473 | H30: =+IFERROR(COSECHA[[#This Row],[KG uva]]/COUNTIFS(COSECHA[Finca],COSECHA[[#This Row],[Finca]],COSECHA[Variedad],COSECHA[[#This Row],[Variedad]],COSECHA[Tipo de Cosecha],COSECHA[[#This Row],[Tipo de Cosecha]]),0) -> 111170 | J30: =+COSECHA[[#This Row],[KG]]/1625 -> 68.412308 | K30: Enero | L30: =+IFERROR(IF(COSECHA[[#This Row],[Bins]]="",COSECHA[[#This Row],[KG]]*INDEX(Tabla2[Precio Kg Uva Carro],MATCH(COSECHA[[#This Row],[Mes]],Tabla2[Mes],0)),COSECHA[[#This Row],[Bins]]*INDEX(Tabla2[Precio Bins],MATCH(COSECHA[[#This Row],[Mes]],Tabla2[Mes],0))),0) -> 2621388.6 | M30: =+IFERROR(INDEX(Tabla2[Precio Jornal],MATCH(COSECHA[[#This Row],[Mes]],Tabla2[Mes],0))*COSECHA[[#This Row],[Jornales]],0) -> 152650.2 | N30: =+COSECHA[[#This Row],[Jornales $]]+SUM(COSECHA[[#This Row],[PA]:[EE III]]) -> 2774038.8 | O30: =+IF(COSECHA[[#This Row],[Finca]]="Puente Alto",INDEX(Tabla2[kg pa],MATCH(COSECHA[[#This Row],[Mes]],Tabla2[Mes],0))*COSECHA[[#This Row],[KG]],"") | P30: =+IF(COSECHA[[#This Row],[Tipo de Cosecha]]="Carro",INDEX(Tabla2[Precio Kg Uva Carro],MATCH(COSECHA[[#This Row],[Mes]],Tabla2[Mes],0)),"")*COSECHA[[#This Row],[KG]] -> 2621388.6
A31: Camino Truncado | B31: Fiesta | C31: Tractor con uñas | D31: Carro | E31: 555850 | F31: 27.649389 | H31: =+IFERROR(COSECHA[[#This Row],[KG uva]]/COUNTIFS(COSECHA[Finca],COSECHA[[#This Row],[Finca]],COSECHA[Variedad],COSECHA[[#This Row],[Variedad]],COSECHA[Tipo de Cosecha],COSECHA[[#This Row],[Tipo de Cosecha]]),0) -> 111170 | J31: =+COSECHA[[#This Row],[KG]]/1625 -> 68.412308 | K31: Enero | L31: =+IFERROR(IF(COSECHA[[#This Row],[Bins]]="",COSECHA[[#This Row],[KG]]*INDEX(Tabla2[Precio Kg Uva Carro],MATCH(COSECHA[[#This Row],[Mes]],Tabla2[Mes],0)),COSECHA[[#This Row],[Bins]]*INDEX(Tabla2[Precio Bins],MATCH(COSECHA[[#This Row],[Mes]],Tabla2[Mes],0))),0) -> 2621388.6 | M31: =+IFERROR(INDEX(Tabla2[Precio Jornal],MATCH(COSECHA[[#This Row],[Mes]],Tabla2[Mes],0))*COSECHA[[#This Row],[Jornales]],0) -> 610600.82 | N31: =+COSECHA[[#This Row],[Jornales $]]+SUM(COSECHA[[#This Row],[PA]:[EE III]]) -> 3231989.4 | O31: =+IF(COSECHA[[#This Row],[Finca]]="Puente Alto",INDEX(Tabla2[kg pa],MATCH(COSECHA[[#This Row],[Mes]],Tabla2[Mes],0))*COSECHA[[#This Row],[KG]],"") | P31: =+IF(COSECHA[[#This Row],[Tipo de Cosecha]]="Carro",INDEX(Tabla2[Precio Kg Uva Carro],MATCH(COSECHA[[#This Row],[Mes]],Tabla2[Mes],0)),"")*COSECHA[[#This Row],[KG]] -> 2621388.6
A32: Camino Truncado | B32: Fiesta | C32: Lavar Bines | D32: Carro | E32: 555850 | F32: 1.3824695 | H32: =+IFERROR(COSECHA[[#This Row],[KG uva]]/COUNTIFS(COSECHA[Finca],COSECHA[[#This Row],[Finca]],COSECHA[Variedad],COSECHA[[#This Row],[Variedad]],COSECHA[Tipo de Cosecha],COSECHA[[#This Row],[Tipo de Cosecha]]),0) -> 111170 | J32: =+COSECHA[[#This Row],[KG]]/1625 -> 68.412308 | K32: Enero | L32: =+IFERROR(IF(COSECHA[[#This Row],[Bins]]="",COSECHA[[#This Row],[KG]]*INDEX(Tabla2[Precio Kg Uva Carro],MATCH(COSECHA[[#This Row],[Mes]],Tabla2[Mes],0)),COSECHA[[#This Row],[Bins]]*INDEX(Tabla2[Precio Bins],MATCH(COSECHA[[#This Row],[Mes]],Tabla2[Mes],0))),0) -> 2621388.6 | M32: =+IFERROR(INDEX(Tabla2[Precio Jornal],MATCH(COSECHA[[#This Row],[Mes]],Tabla2[Mes],0))*COSECHA[[#This Row],[Jornales]],0) -> 30530.041 | N32: =+COSECHA[[#This Row],[Jornales $]]+SUM(COSECHA[[#This Row],[PA]:[EE III]]) -> 2651918.6 | O32: =+IF(COSECHA[[#This Row],[Finca]]="Puente Alto",INDEX(Tabla2[kg pa],MATCH(COSECHA[[#This Row],[Mes]],Tabla2[Mes],0))*COSECHA[[#This Row],[KG]],"") | P32: =+IF(COSECHA[[#This Row],[Tipo de Cosecha]]="Carro",INDEX(Tabla2[Precio Kg Uva Carro],MATCH(COSECHA[[#This Row],[Mes]],Tabla2[Mes],0)),"")*COSECHA[[#This Row],[KG]] -> 2621388.6
A33: Camino Truncado | B33: Fiesta | C33: Tractor con acoplado | D33: Carro | E33: 555850 | F33: 13.824695 | H33: =+IFERROR(COSECHA[[#This Row],[KG uva]]/COUNTIFS(COSECHA[Finca],COSECHA[[#This Row],[Finca]],COSECHA[Variedad],COSECHA[[#This Row],[Variedad]],COSECHA[Tipo de Cosecha],COSECHA[[#This Row],[Tipo de Cosecha]]),0) -> 111170 | J33: =+COSECHA[[#This Row],[KG]]/1625 -> 68.412308 | K33: Enero | L33: =+IFERROR(IF(COSECHA[[#This Row],[Bins]]="",COSECHA[[#This Row],[KG]]*INDEX(Tabla2[Precio Kg Uva Carro],MATCH(COSECHA[[#This Row],[Mes]],Tabla2[Mes],0)),COSECHA[[#This Row],[Bins]]*INDEX(Tabla2[Precio Bins],MATCH(COSECHA[[#This Row],[Mes]],Tabla2[Mes],0))),0) -> 2621388.6 | M33: =+IFERROR(INDEX(Tabla2[Precio Jornal],MATCH(COSECHA[[#This Row],[Mes]],Tabla2[Mes],0))*COSECHA[[#This Row],[Jornales]],0) -> 305300.41 | N33: =+COSECHA[[#This Row],[Jornales $]]+SUM(COSECHA[[#This Row],[PA]:[EE III]]) -> 2926689 | O33: =+IF(COSECHA[[#This Row],[Finca]]="Puente Alto",INDEX(Tabla2[kg pa],MATCH(COSECHA[[#This Row],[Mes]],Tabla2[Mes],0))*COSECHA[[#This Row],[KG]],"") | P33: =+IF(COSECHA[[#This Row],[Tipo de Cosecha]]="Carro",INDEX(Tabla2[Precio Kg Uva Carro],MATCH(COSECHA[[#This Row],[Mes]],Tabla2[Mes],0)),"")*COSECHA[[#This Row],[KG]] -> 2621388.6
A34: Camino Truncado | B34: Fiesta | C34: Anotador | D34: Bins | E34: 98040 | F34: 1.7458498 | G34: =+COSECHA[[#This Row],[KG]]/300 -> 65.36 | H34: =+IFERROR(COSECHA[[#This Row],[KG uva]]/COUNTIFS(COSECHA[Finca],COSECHA[[#This Row],[Finca]],COSECHA[Variedad],COSECHA[[#This Row],[Variedad]],COSECHA[Tipo de Cosecha],COSECHA[[#This Row],[Tipo de Cosecha]]),0) -> 19608 | I34: 1 | K34: Enero | L34: =+IFERROR(IF(COSECHA[[#This Row],[Bins]]="",COSECHA[[#This Row],[KG]]*INDEX(Tabla2[Precio Kg Uva Carro],MATCH(COSECHA[[#This Row],[Mes]],Tabla2[Mes],0)),COSECHA[[#This Row],[Bins]]*INDEX(Tabla2[Precio Bins],MATCH(COSECHA[[#This Row],[Mes]],Tabla2[Mes],0))),0) -> 321081 | M34: =+IFERROR(INDEX(Tabla2[Precio Jornal],MATCH(COSECHA[[#This Row],[Mes]],Tabla2[Mes],0))*COSECHA[[#This Row],[Jornales]],0) -> 38554.824 | N34: =+COSECHA[[#This Row],[Jornales $]]+SUM(COSECHA[[#This Row],[PA]:[EE III]]) -> 552284.42 | O34: =+IF(COSECHA[[#This Row],[Finca]]="Puente Alto",INDEX(Tabla2[kg pa],MATCH(COSECHA[[#This Row],[Mes]],Tabla2[Mes],0))*COSECHA[[#This Row],[KG]],"") | P34: =+INDEX(Tabla2[kg pa],MATCH(COSECHA[[#This Row],[Mes]],Tabla2[Mes],0))*COSECHA[[#This Row],[KG]] -> 513729.6
A35: Camino Truncado | B35: Fiesta | C35: Tracto elevador | D35: Bins | E35: 98040 | F35: 1.7458498 | G35: =+COSECHA[[#This Row],[KG]]/300 -> 65.36 | H35: =+IFERROR(COSECHA[[#This Row],[KG uva]]/COUNTIFS(COSECHA[Finca],COSECHA[[#This Row],[Finca]],COSECHA[Variedad],COSECHA[[#This Row],[Variedad]],COSECHA[Tipo de Cosecha],COSECHA[[#This Row],[Tipo de Cosecha]]),0) -> 19608 | I35: 1 | K35: Enero | L35: =+IFERROR(IF(COSECHA[[#This Row],[Bins]]="",COSECHA[[#This Row],[KG]]*INDEX(Tabla2[Precio Kg Uva Carro],MATCH(COSECHA[[#This Row],[Mes]],Tabla2[Mes],0)),COSECHA[[#This Row],[Bins]]*INDEX(Tabla2[Precio Bins],MATCH(COSECHA[[#This Row],[Mes]],Tabla2[Mes],0))),0) -> 321081 | M35: =+IFERROR(INDEX(Tabla2[Precio Jornal],MATCH(COSECHA[[#This Row],[Mes]],Tabla2[Mes],0))*COSECHA[[#This Row],[Jornales]],0) -> 38554.824 | N35: =+COSECHA[[#This Row],[Jornales $]]+SUM(COSECHA[[#This Row],[PA]:[EE III]]) -> 552284.42 | O35: =+IF(COSECHA[[#This Row],[Finca]]="Puente Alto",INDEX(Tabla2[kg pa],MATCH(COSECHA[[#This Row],[Mes]],Tabla2[Mes],0))*COSECHA[[#This Row],[KG]],"") | P35: =+INDEX(Tabla2[kg pa],MATCH(COSECHA[[#This Row],[Mes]],Tabla2[Mes],0))*COSECHA[[#This Row],[KG]] -> 513729.6
A36: Camino Truncado | B36: Fiesta | C36: Tractor con uñas | D36: Bins | E36: 98040 | F36: 6.9833994 | G36: =+COSECHA[[#This Row],[KG]]/300 -> 65.36 | H36: =+IFERROR(COSECHA[[#This Row],[KG uva]]/COUNTIFS(COSECHA[Finca],COSECHA[[#This Row],[Finca]],COSECHA[Variedad],COSECHA[[#This Row],[Variedad]],COSECHA[Tipo de Cosecha],COSECHA[[#This Row],[Tipo de Cosecha]]),0) -> 19608 | I36: 1 | K36: Enero | L36: =+IFERROR(IF(COSECHA[[#This Row],[Bins]]="",COSECHA[[#This Row],[KG]]*INDEX(Tabla2[Precio Kg Uva Carro],MATCH(COSECHA[[#This Row],[Mes]],Tabla2[Mes],0)),COSECHA[[#This Row],[Bins]]*INDEX(Tabla2[Precio Bins],MATCH(COSECHA[[#This Row],[Mes]],Tabla2[Mes],0))),0) -> 321081 | M36: =+IFERROR(INDEX(Tabla2[Precio Jornal],MATCH(COSECHA[[#This Row],[Mes]],Tabla2[Mes],0))*COSECHA[[#This Row],[Jornales]],0) -> 154219.3 | N36: =+COSECHA[[#This Row],[Jornales $]]+SUM(COSECHA[[#This Row],[PA]:[EE III]]) -> 667948.9 | O36: =+IF(COSECHA[[#This Row],[Finca]]="Puente Alto",INDEX(Tabla2[kg pa],MATCH(COSECHA[[#This Row],[Mes]],Tabla2[Mes],0))*COSECHA[[#This Row],[KG]],"") | P36: =+INDEX(Tabla2[kg pa],MATCH(COSECHA[[#This Row],[Mes]],Tabla2[Mes],0))*COSECHA[[#This Row],[KG]] -> 513729.6
A37: Camino Truncado | B37: Fiesta | C37: Lavar Bines | D37: Bins | E37: 98040 | F37: 0.34916997 | G37: =+COSECHA[[#This Row],[KG]]/300 -> 65.36 | H37: =+IFERROR(COSECHA[[#This Row],[KG uva]]/COUNTIFS(COSECHA[Finca],COSECHA[[#This Row],[Finca]],COSECHA[Variedad],COSECHA[[#This Row],[Variedad]],COSECHA[Tipo de Cosecha],COSECHA[[#This Row],[Tipo de Cosecha]]),0) -> 19608 | I37: 1 | K37: Enero | L37: =+IFERROR(IF(COSECHA[[#This Row],[Bins]]="",COSECHA[[#This Row],[KG]]*INDEX(Tabla2[Precio Kg Uva Carro],MATCH(COSECHA[[#This Row],[Mes]],Tabla2[Mes],0)),COSECHA[[#This Row],[Bins]]*INDEX(Tabla2[Precio Bins],MATCH(COSECHA[[#This Row],[Mes]],Tabla2[Mes],0))),0) -> 321081 | M37: =+IFERROR(INDEX(Tabla2[Precio Jornal],MATCH(COSECHA[[#This Row],[Mes]],Tabla2[Mes],0))*COSECHA[[#This Row],[Jornales]],0) -> 7710.9648 | N37: =+COSECHA[[#This Row],[Jornales $]]+SUM(COSECHA[[#This Row],[PA]:[EE III]]) -> 521440.56 | O37: =+IF(COSECHA[[#This Row],[Finca]]="Puente Alto",INDEX(Tabla2[kg pa],MATCH(COSECHA[[#This Row],[Mes]],Tabla2[Mes],0))*COSECHA[[#This Row],[KG]],"") | P37: =+INDEX(Tabla2[kg pa],MATCH(COSECHA[[#This Row],[Mes]],Tabla2[Mes],0))*COSECHA[[#This Row],[KG]] -> 513729.6
A38: Camino Truncado | B38: Fiesta | C38: Tractor con acoplado | D38: Bins | E38: 98040 | F38: 3.4916997 | G38: =+COSECHA[[#This Row],[KG]]/300 -> 65.36 | H38: =+IFERROR(COSECHA[[#This Row],[KG uva]]/COUNTIFS(COSECHA[Finca],COSECHA[[#This Row],[Finca]],COSECHA[Variedad],COSECHA[[#This Row],[Variedad]],COSECHA[Tipo de Cosecha],COSECHA[[#This Row],[Tipo de Cosecha]]),0) -> 19608 | I38: 1 | K38: Enero | L38: =+IFERROR(IF(COSECHA[[#This Row],[Bins]]="",COSECHA[[#This Row],[KG]]*INDEX(Tabla2[Precio Kg Uva Carro],MATCH(COSECHA[[#This Row],[Mes]],Tabla2[Mes],0)),COSECHA[[#This Row],[Bins]]*INDEX(Tabla2[Precio Bins],MATCH(COSECHA[[#This Row],[Mes]],Tabla2[Mes],0))),0) -> 321081 | M38: =+IFERROR(INDEX(Tabla2[Precio Jornal],MATCH(COSECHA[[#This Row],[Mes]],Tabla2[Mes],0))*COSECHA[[#This Row],[Jornales]],0) -> 77109.648 | N38: =+COSECHA[[#This Row],[Jornales $]]+SUM(COSECHA[[#This Row],[PA]:[EE III]]) -> 590839.25 | O38: =+IF(COSECHA[[#This Row],[Finca]]="Puente Alto",INDEX(Tabla2[kg pa],MATCH(COSECHA[[#This Row],[Mes]],Tabla2[Mes],0))*COSECHA[[#This Row],[KG]],"") | P38: =+INDEX(Tabla2[kg pa],MATCH(COSECHA[[#This Row],[Mes]],Tabla2[Mes],0))*COSECHA[[#This Row],[KG]] -> 513729.6
A39: Camino Truncado | B39: Superior | C39: Anotador | D39: Bins | E39: 44850 | F39: 1.3418028 | G39: =+COSECHA[[#This Row],[KG]]/300 -> 29.9 | H39: =+IFERROR(COSECHA[[#This Row],[KG uva]]/COUNTIFS(COSECHA[Finca],COSECHA[[#This Row],[Finca]],COSECHA[Variedad],COSECHA[[#This Row],[Variedad]],COSECHA[Tipo de Cosecha],COSECHA[[#This Row],[Tipo de Cosecha]]),0) -> 8970 | I39: 1 | K39: Enero | L39: =+IFERROR(IF(COSECHA[[#This Row],[Bins]]="",COSECHA[[#This Row],[KG]]*INDEX(Tabla2[Precio Kg Uva Carro],MATCH(COSECHA[[#This Row],[Mes]],Tabla2[Mes],0)),COSECHA[[#This Row],[Bins]]*INDEX(Tabla2[Precio Bins],MATCH(COSECHA[[#This Row],[Mes]],Tabla2[Mes],0))),0) -> 146883.75 | M39: =+IFERROR(INDEX(Tabla2[Precio Jornal],MATCH(COSECHA[[#This Row],[Mes]],Tabla2[Mes],0))*COSECHA[[#This Row],[Jornales]],0) -> 29631.971 | N39: =+COSECHA[[#This Row],[Jornales $]]+SUM(COSECHA[[#This Row],[PA]:[EE III]]) -> 264645.97 | O39: =+IF(COSECHA[[#This Row],[Finca]]="Puente Alto",INDEX(Tabla2[kg pa],MATCH(COSECHA[[#This Row],[Mes]],Tabla2[Mes],0))*COSECHA[[#This Row],[KG]],"") | P39: =+INDEX(Tabla2[kg pa],MATCH(COSECHA[[#This Row],[Mes]],Tabla2[Mes],0))*COSECHA[[#This Row],[KG]] -> 235014
